Workbook

Sheet Vesti 08-25
A1: Fat.2025 | B1: ANIVERSÁRIO | C1: CANAL | D1: MARCA | E1: Subconta | F1: PLANO | G1: SETUP | H1: MENSALIDADE INICIAL | I1: VALOR REAJUSTE | J1: MENSALIDADE | K1: INTEGRAÇÃO | L1: ASSISTENTE | M1: FILIAL | N1: DESCONTOS | O1: TOTAL COBRADO | P1: OBSERVAÇÕES | Q1: Dia Vencimento | R1: Mês de Reajuste | S1: CPFCNPJ
A2: 08/2025 | B2: 42795 | C2: VESTI | D2: TNW Jeans | E2: Vesti (Fatura) | F2: Profissional | H2: 1156 | J2: 1156 | O2: =SUM(J2:M2)-N2 -> 1156 | Q2: 17 | R2: 04 | S2: 4937453000108
A3: 08/2025 | B3: 42937 | C3: Atta | D3: Peonia | E3: Atta | F3: Essencial | H3: 283 | J3: 283 | O3: =SUM(J3:M3)-N3 -> 283 | Q3: 20 | R3: 4 | S3: 07993188000165
A4: 08/2025 | B4: 43160 | C4: Atta | D4: Maria De Chita | E4: Vesti (Fatura) | F4: Profissional | H4: 724 | J4: 724 | O4: =SUM(J4:M4)-N4 -> 724 | Q4: 15 | R4: 04 | S4: 07402979000173
A5: 08/2025 | B5: 43160 | C5: Atta | D5: Shanes | E5: Vesti (Fatura) | F5: Profissional | H5: 1179 | J5: 1179 | O5: =SUM(J5:M5)-N5 -> 1179 | Q5: 20 | R5: 04 | S5: 46446130000153
A6: 08/2025 | B6: 43160 | C6: Atta | D6: Talgui | E6: Vesti (Fatura) | F6: Avançado | H6: 441.33 | J6: 441.33 | O6: =SUM(J6:M6)-N6 -> 441.33 | Q6: 15 | R6: 04 | S6: 05876663000198
A7: 08/2025 | B7: 43160 | C7: Atta | D7: Codi Codi | E7: Vesti (Fatura) | F7: Profissional | H7: 889 | J7: 889 | O7: =SUM(J7:M7)-N7 -> 889 | Q7: 15 | R7: 04 | S7: 18555123000154
A8: 08/2025 | B8: 43160 | C8: Atta | D8: Coinage | E8: Vesti (Fatura) | F8: Profissional | H8: 1179 | J8: 1179 | O8: =SUM(J8:M8)-N8 -> 1179 | Q8: 20 | R8: 04 | S8: 33724927000123
A9: 08/2025 | B9: 43160 | C9: Atta | D9: Moda Inn | E9: Vesti (Fatura) | F9: Essencial | H9: 283 | J9: 283 | O9: =SUM(J9:M9)-N9 -> 283 | Q9: 20 | R9: 04 | S9: 49921554000110
A10: 08/2025 | B10: 43160 | C10: Atta | D10: Licommo | E10: Vesti (Fatura) | F10: Avançado | H10: 425 | J10: 425 | O10: =SUM(J10:M10)-N10 -> 425 | Q10: 15 | R10: 04 | S10: 08325746000187
A11: 08/2025 | B11: 43160 | C11: Atta | D11: Betsey | E11: Vesti (Fatura) | F11: Profissional | H11: 1003 | J11: 1003 | O11: =SUM(J11:M11)-N11 -> 1003 | Q11: 15 | R11: 04 | S11: 06161024000109
A12: 08/2025 | B12: 43160 | C12: Atta | D12: Cashier | E12: Vesti (Fatura) | F12: Profissional | H12: 1015 | J12: 1015 | O12: =SUM(J12:M12)-N12 -> 1015 | Q12: 30 | R12: 04 | S12: 60368669000162
A13: 08/2025 | B13: 43160 | C13: Atta | D13: Cony Green | E13: Vesti (Fatura) | F13: Avançado | H13: 425 | J13: 425 | O13: =SUM(J13:M13)-N13 -> 425 | Q13: 15 | R13: 04 | S13: 44511277000154
A14: 08/2025 | B14: 43160 | C14: Atta | D14: Pury | E14: Vesti (Fatura) | F14: Profissional | H14: 1327 | J14: 1327 | M14: 359 | O14: =SUM(J14:M14)-N14 -> 1686 | Q14: 15 | R14: 04 | S14: 12576594000162
A15: 08/2025 | B15: 43160 | C15: Atta | D15: Nanaminze | E15: Vesti (Fatura) | F15: Profissional | H15: 1179 | J15: 1179 | M15: 359 | O15: =SUM(J15:M15)-N15 -> 1538 | Q15: 15 | R15: 04 | S15: 12656331000163
A16: 08/2025 | B16: 43160 | C16: VESTI | D16: Tricomix | E16: Vesti (Fatura) | F16: Avançado | H16: 1193 | J16: 1193 | K16: 350 | O16: =SUM(J16:M16)-N16 -> 1543 | Q16: 11 | R16: 04 | S16: 04665515000161
A17: 08/2025 | B17: 43160 | C17: Atta | D17: Lov It | E17: Vesti (Fatura) | F17: Avançado | H17: 425 | J17: 425 | O17: =SUM(J17:M17)-N17 -> 425 | Q17: 11 | R17: 04 | S17: 21749422000215
A18: 08/2025 | B18: 43160 | C18: Atta | D18: Hemix | E18: Vesti (Fatura) | F18: Essencial | H18: 283 | J18: 283 | L18: =550+120 -> 670 | O18: =SUM(J18:M18)-N18 -> 953 | Q18: 15 | R18: 04 | S18: 07389520000187
A19: 08/2025 | B19: 43160 | C19: Miredata | D19: Mottive | E19: Vesti (Fatura) | F19: Profissional | H19: 1179 | J19: 1179 | O19: =SUM(J19:M19)-N19 -> 1179 | Q19: 20 | R19: 04 | S19: 24330475000104
A20: 08/2025 | B20: 43160 | C20: Atta | D20: Miss Alfa | E20: Vesti (Fatura) | F20: Essencial | H20: 283 | J20: 283 | O20: =SUM(J20:M20)-N20 -> 283 | Q20: 15 | R20: 04 | S20: 28497561000167
A21: 08/2025 | B21: 43160 | C21: VESTI | D21: Anemone | E21: Vesti (Fatura) | F21: Avançado | H21: 1013 | J21: 1013 | O21: =SUM(J21:M21)-N21 -> 1013 | Q21: 11 | R21: 04 | S21: 30962814000178
A22: 08/2025 | B22: 43160 | C22: Miredata | D22: Pianeta | E22: Vesti (Fatura) | F22: Profissional | H22: 761 | J22: 761 | O22: =SUM(J22:M22)-N22 -> 761 | Q22: 20 | R22: 04 | S22: 31583000000195
A23: 08/2025 | B23: 43356 | C23: Atta | D23: Morina | E23: Vesti (Fatura) | F23: Profissional | H23: 1138 | J23: 1138 | O23: =SUM(J23:M23)-N23 -> 1138 | Q23: 15 | R23: 04 | S23: 44029041000186
A24: 08/2025 | B24: 43586 | C24: Atta | D24: Artemiss | E24: Vesti (Fatura) | F24: Avançado | H24: 569 | J24: 569 | M24: 275 | O24: =SUM(J24:M24)-N24 -> 844 | Q24: 11 | R24: 04 | S24: 05320347000135
A25: 08/2025 | B25: 43586 | C25: Atta | D25: IT LOOK | E25: Vesti (Fatura) | F25: Essencial | H25: 283 | J25: 283 | O25: =SUM(J25:M25)-N25 -> 283 | Q25: 15 | R25: 04 | S25: 21659326000103
A26: 08/2025 | B26: 43586 | C26: Atta | D26: E YUNIRE | E26: Vesti (Fatura) | F26: Essencial | H26: 354 | J26: 354 | O26: =SUM(J26:M26)-N26 -> 354 | Q26: 15 | R26: 04 | S26: 45375658000116
A27: 08/2025 | B27: 43593 | C27: Atta | D27: Incentive | E27: Vesti (Fatura) | F27: Essencial | H27: 528.33 | J27: 528.33 | L27: 850 | O27: =SUM(J27:M27)-N27 -> 1378.33 | Q27: 30 | R27: 04 | S27: 29780242000127
A28: 08/2025 | B28: 43593 | C28: Atta | D28: Mariá/Aurora | E28: Vesti (Fatura) | F28: Essencial | H28: 283 | J28: 283 | O28: =SUM(J28:M28)-N28 -> 283 | Q28: 20 | R28: 04 | S28: 33076814000169
A29: 08/2025 | B29: 43593 | C29: Atta | D29: Mazarin | E29: Vesti (Fatura) | F29: Essencial | H29: 326.67 | J29: 326.67 | O29: =SUM(J29:M29)-N29 -> 326.67 | Q29: 15 | R29: 04 | S29: 03598605000203
A30: 08/2025 | B30: 43600 | C30: Atta | D30: Blue Blossom | E30: Vesti (Fatura) | F30: Essencial | H30: 283 | J30: 283 | O30: =SUM(J30:M30)-N30 -> 283 | Q30: 15 | R30: 04 | S30: 30828978000107
A31: 08/2025 | B31: 43600 | C31: Atta | D31: Dolps | E31: Vesti (Fatura) | F31: Profissional | H31: 1269 | J31: 1269 | O31: =SUM(J31:M31)-N31 -> 1269 | Q31: 15 | R31: 05 | S31: 01802508000176
A32: 08/2025 | B32: 43606 | C32: VESTI | D32: Crocker | E32: Vesti (Fatura) | F32: Profissional | H32: 1179 | J32: 1179 | M32: 410 | O32: =SUM(J32:M32)-N32 -> 1589 | Q32: 15 | R32: 04 | S32: 60652948000153
A33: 08/2025 | B33: 43606 | C33: VESTI | D33: Lesto | E33: Vesti (Fatura) | F33: Essencial | H33: 284.33 | J33: 284.33 | O33: =SUM(J33:M33)-N33 -> 284.33 | Q33: 15 | R33: 04 | S33: 58418377000145
A34: 08/2025 | B34: 43619 | C34: Atta | D34: Ellen One | E34: Vesti (Cartão) | F34: Essencial | H34: 283 | J34: 283 | O34: =SUM(J34:M34)-N34 -> 283 | Q34: 06 | R34: 4 | S34: 07554437000116
A35: 08/2025 | B35: 43619 | C35: Atta | D35: Instar | E35: Vesti (Fatura) | F35: Essencial | H35: 283 | J35: 283 | O35: =SUM(J35:M35)-N35 -> 283 | Q35: 15 | R35: 04 | S35: 32649954000116
A36: 08/2025 | B36: 43633 | C36: Atta | D36: Aramodu | E36: Vesti (Fatura) | F36: Essencial | H36: 283 | J36: 283 | O36: =SUM(J36:M36)-N36 -> 283 | Q36: 11 | R36: 04 | S36: 97541061000106
A37: 08/2025 | B37: 43643 | C37: Atta | D37: Scera | E37: Vesti (Fatura) | F37: Essencial | H37: 283 | J37: 283 | O37: =SUM(J37:M37)-N37 -> 283 | Q37: 15 | R37: 04 | S37: 23333642000108
A38: 08/2025 | B38: 43649 | C38: Atta | D38: Fama Fashion | E38: Vesti (Fatura) | F38: Essencial | H38: 283 | J38: 283 | O38: =SUM(J38:M38)-N38 -> 283 | Q38: 20 | R38: 04 | S38: 54451398000101
A39: 08/2025 | B39: 43649 | C39: VESTI | D39: Paloma Concept | E39: Vesti (Fatura) | F39: Essencial | H39: 283 | J39: 283 | O39: =SUM(J39:M39)-N39 -> 283 | Q39: 15 | R39: 04 | S39: 16579598000155
A40: 08/2025 | B40: 43656 | C40: Atta | D40: Cheers | E40: Vesti (Fatura) | F40: Profissional | H40: 1179 | J40: 1179 | O40: =SUM(J40:M40)-N40 -> 1179 | Q40: 11 | R40: 04 | S40: 53659785000175
A41: 08/2025 | B41: 43656 | C41: Atta | D41: Fesperamor | E41: Vesti (Fatura) | F41: Profissional | H41: 1179 | J41: 1179 | O41: =SUM(J41:M41)-N41 -> 1179 | Q41: 15 | R41: 04 | S41: 22015485000120
A42: 08/2025 | B42: 43675 | C42: Atta | D42: Quebela | E42: Vesti (Fatura) | F42: Essencial | H42: 425 | J42: 425 | O42: =SUM(J42:M42)-N42 -> 425 | Q42: 20 | R42: 04 | S42: 58525007000107
A43: 08/2025 | B43: 43684 | C43: Atta | D43: Genesis Jeans | E43: Vesti (Fatura) | F43: Essencial | H43: 283 | J43: 283 | O43: =SUM(J43:M43)-N43 -> 283 | Q43: 15 | R43: 04 | S43: 21352130000163
A44: 08/2025 | B44: 43713 | C44: Vesti | D44: AMISKA - MISS MILLIE | E44: Vesti (Fatura) | F44: Essencial | H44: 303 | J44: 303 | O44: =SUM(J44:M44)-N44 -> 303 | Q44: 15 | R44: 04 | S44: 24721940000138
A45: 08/2025 | B45: 43718 | C45: VESTI | D45: Join Curves | E45: Vesti (Fatura) | F45: Avançado | H45: 486 | J45: 486 | L45: 1000 | M45: 600 | O45: =SUM(J45:M45)-N45 -> 2086 | Q45: 28 | R45: 04 | S45: 07867580000168
A46: 08/2025 | B46: 43719 | C46: Atta | D46: Namine | E46: Vesti (Fatura) | F46: Profissional | H46: 1005 | J46: 1005 | M46: =266+900 -> 1166 | O46: =SUM(J46:M46)-N46 -> 2171 | Q46: 15 | R46: 04 | S46: 17820490000256
A47: 08/2025 | B47: 43731 | C47: VESTI | D47: Diamantes | E47: Vesti (Fatura) | F47: Profissional | H47: 1400 | J47: 1400 | M47: =38*161.95+3 -> 6157.1 | O47: =SUM(J47:M47)-N47 -> 7557.1 | Q47: 15 | R47: 04 | S47: 13649755000163
A48: 08/2025 | B48: 43738 | C48: Atta | D48: Lily Daisy | E48: Vesti (Fatura) | F48: Essencial | H48: 283 | J48: 283 | O48: =SUM(J48:M48)-N48 -> 283 | Q48: 15 | R48: 04 | S48: 34500000000172
A49: 08/2025 | B49: 43745 | C49: VESTI | D49: Ana Gonçalves Tricot = Luis Guilherme | E49: Vesti (Fatura) | F49: Profissional | H49: 1179 | J49: 1179 | M49: 598 | O49: =SUM(J49:M49)-N49 -> 1777 | Q49: 15 | R49: 04 | S49: 11582787000163
A50: 08/2025 | B50: 43755 | C50: Atta | D50: Delight | E50: Vesti (Fatura) | F50: Essencial | H50: 283 | J50: 283 | O50: =SUM(J50:M50)-N50 -> 283 | Q50: 15 | R50: 04 | S50: 21520947000101
A51: 08/2025 | B51: 43755 | C51: Atta | D51: Sori | E51: Vesti (Fatura) | F51: Profissional | H51: 1179 | J51: 1179 | O51: =SUM(J51:M51)-N51 -> 1179 | Q51: 15 | R51: 04 | S51: 06987979000110
A52: 08/2025 | B52: 43768 | C52: Atta | D52: Mx | E52: Vesti (Fatura) | F52: Profissional | H52: 1179 | J52: 1179 | O52: =SUM(J52:M52)-N52 -> 1179 | Q52: 20 | R52: 04 | S52: 05888414000112
A53: 08/2025 | B53: 43774 | C53: Atta | D53: Donna Ritz | E53: Vesti (Fatura) | F53: Profissional | H53: 1076.67 | J53: 1076.67 | O53: =SUM(J53:M53)-N53 -> 1076.67 | Q53: 15 | R53: 04 | S53: 19521267000152
A54: 08/2025 | B54: 43802 | C54: VESTI | D54: Vida Bela | E54: Vesti (Fatura) | F54: Essencial | H54: 283 | J54: 283 | O54: =SUM(J54:M54)-N54 -> 283 | Q54: 15 | R54: 04 | S54: 45668696000167
A55: 08/2025 | B55: 43846 | C55: Atta | D55: Sedanbi | E55: Vesti (Fatura) | F55: Essencial | H55: 283 | J55: 283 | O55: =SUM(J55:M55)-N55 -> 283 | Q55: 15 | R55: 04 | S55: 00238342000306
A56: 08/2025 | B56: 43861 | C56: VESTI | D56: Rafa Brasil | E56: Vesti (Fatura) | F56: Essencial | H56: 283 | J56: 283 | O56: =SUM(J56:M56)-N56 -> 283 | Q56: 15 | R56: 04 | S56: 30827010000166
A57: 08/2025 | B57: 43867 | C57: Atta | D57: Elae | E57: Vesti (Fatura) | F57: Avançado | H57: 425 | J57: 425 | O57: =SUM(J57:M57)-N57 -> 425 | Q57: 20 | R57: 04 | S57: 46924221000157
A58: 08/2025 | B58: 43878 | C58: Atta | D58: As Marias | E58: Vesti (Fatura) | F58: Essencial | H58: 283 | J58: 283 | O58: =SUM(J58:M58)-N58 -> 283 | Q58: 15 | R58: 04 | S58: 24487541000154
A59: 08/2025 | B59: 43888 | C59: VESTI | D59: Suzan Zheng | E59: Vesti (Fatura) | F59: Essencial | H59: 283 | J59: 283 | O59: =SUM(J59:M59)-N59 -> 283 | Q59: 15 | R59: 04 | S59: 26551251000158
A60: 08/2025 | B60: 43892 | C60: VESTI | D60: Gliss Jeans | E60: Vesti (Fatura) | F60: Essencial | H60: 283 | J60: 283 | M60: 199 | O60: =SUM(J60:M60)-N60 -> 482 | Q60: 11 | R60: 04 | S60: 55251292001107
A61: 08/2025 | B61: 43896 | C61: Atta | D61: Idrissi | E61: Vesti (Fatura) | F61: Essencial | H61: 283 | J61: 283 | K61: 350 | N61: 156 | O61: =SUM(J61:M61)-N61 -> 477 | P61: Desconto concedido pelo Mourad permanente | Q61: 15 | R61: 04 | S61: 08914436000106
A62: 08/2025 | B62: 43903 | C62: VESTI | D62: Bauarte | E62: Vesti (Fatura) | F62: Avançado | H62: 1231 | J62: 1231 | K62: 350 | O62: =SUM(J62:M62)-N62 -> 1581 | Q62: 20 | R62: 04 | S62: 08754784000155
A63: 08/2025 | B63: 43920 | C63: Atta | D63: Alcance Jeans | E63: Vesti (Fatura) | F63: Profissional | H63: 1243.35 | J63: 1243.35 | L63: 1920 | M63: 250 | O63: =SUM(J63:M63)-N63 -> 3413.35 | Q63: 11 | R63: 04 | S63: 27760882000140
A64: 08/2025 | B64: 43943 | C64: VESTI | D64: Jezzian | E64: Vesti (Fatura) | F64: Profissional | H64: 5686 | J64: 5686 | O64: =SUM(J64:M64)-N64 -> 5686 | Q64: 11 | R64: 04 | S64: 08062888000107
A65: 08/2025 | B65: 43943 | C65: VESTI | D65: Sanreed | E65: Vesti (Fatura) | F65: Essencial | H65: 283 | J65: 283 | M65: 359 | O65: =SUM(J65:M65)-N65 -> 642 | Q65: 15 | R65: 04 | S65: 23735214000292
A66: 08/2025 | B66: 43949 | C66: VESTI | D66: Vigor Basic | E66: Vesti (Fatura) | F66: Essencial | H66: 283 | J66: 283 | O66: =SUM(J66:M66)-N66 -> 283 | Q66: 11 | R66: 04 | S66: 07085032000186
A67: 08/2025 | B67: 43950 | C67: VESTI | D67: Manaca= Visuh | E67: Vesti (Fatura) | F67: Profissional | H67: 1179 | J67: 1179 | O67: =SUM(J67:M67)-N67 -> 1179 | Q67: 20 | R67: 04 | S67: 22221114000102
A68: 08/2025 | B68: 43955 | C68: Atta | D68: Bokeh | E68: Vesti (Fatura) | F68: Avançado | H68: 425 | J68: 425 | O68: =SUM(J68:M68)-N68 -> 425 | Q68: 20 | R68: 04 | S68: 28489878000232
A69: 08/2025 | B69: 43957 | C69: VESTI | D69: Cratus | E69: Vesti (Fatura) | F69: Avançado | H69: 1179 | J69: 1179 | O69: =SUM(J69:M69)-N69 -> 1179 | Q69: 15 | R69: 04 | S69: 63917942000159
A70: 08/2025 | B70: 43957 | C70: VESTI | D70: Ezutus | E70: Vesti (Fatura) | F70: Avançado | H70: 1179 | J70: 1179 | O70: =SUM(J70:M70)-N70 -> 1179 | Q70: 15 | R70: 04 | S70: 63917942000159
A71: 08/2025 | B71: 43958 | C71: Atta | D71: Hanabee | E71: Vesti (Fatura) | F71: Avançado | H71: 425 | J71: 425 | O71: =SUM(J71:M71)-N71 -> 425 | Q71: 20 | R71: 04 | S71: 12395643000160
A72: 08/2025 | B72: 43958 | C72: Atta | D72: Innocence | E72: Vesti (Fatura) | F72: Avançado | H72: 835 | J72: 835 | K72: 250 | O72: =SUM(J72:M72)-N72 -> 1085 | Q72: 15 | R72: 04 | S72: 17258262000153
A73: 08/2025 | B73: 43962 | C73: VESTI | D73: Cris Fael | E73: Vesti (Fatura) | F73: Avançado | H73: 425 | J73: 425 | O73: =SUM(J73:M73)-N73 -> 425 | Q73: 15 | R73: 04 | S73: 52341858000113
A74: 08/2025 | B74: 43965 | C74: Atta | D74: Caroll | E74: Vesti (Fatura) | F74: Avançado | H74: 665 | J74: 665 | O74: =SUM(J74:M74)-N74 -> 665 | Q74: 11 | R74: 04 | S74: 02683338000110
A75: 08/2025 | B75: 43965 | C75: Atta | D75: Kalli | E75: Vesti (Fatura) | F75: Avançado | H75: 698 | J75: 698 | O75: =SUM(J75:M75)-N75 -> 698 | Q75: 11 | R75: 04 | S75: 17685726000108
A76: 08/2025 | B76: 43965 | C76: Atta | D76: Sexy Cookie | E76: Vesti (Fatura) | F76: Profissional | H76: 1179 | J76: 1179 | O76: =SUM(J76:M76)-N76 -> 1179 | Q76: 11 | R76: 04 | S76: 08151457000109
A77: 08/2025 | B77: 43966 | C77: VESTI | D77: Adizza | E77: Vesti (Fatura) | F77: Essencial | H77: 283 | J77: 283 | M77: 410 | O77: =SUM(J77:M77)-N77 -> 693 | Q77: 15 | R77: 04 | S77: 24881140000184
A78: 08/2025 | B78: 43966 | C78: VESTI | D78: Anahi | E78: Vesti (Fatura) | F78: Avançado | H78: 425 | J78: 425 | O78: =SUM(J78:M78)-N78 -> 425 | Q78: 20 | R78: 04 | S78: 04049767000166
A79: 08/2025 | B79: 43972 | C79: Atta | D79: Ezee | E79: Vesti (Fatura) | F79: Essencial | H79: 342.67 | J79: 342.67 | O79: =SUM(J79:M79)-N79 -> 342.67 | Q79: 15 | R79: 04 | S79: 28314192000120
A80: 08/2025 | B80: 43978 | C80: Atta | D80: Nakepe | E80: Vesti (Fatura) | F80: Avançado | H80: 425 | J80: 425 | O80: =SUM(J80:M80)-N80 -> 425 | Q80: 22 | R80: 04 | S80: 00764187000108
A81: 08/2025 | B81: 43978 | C81: Atta | D81: Ste Fashion | E81: Vesti (Fatura) | F81: Avançado | H81: 425 | J81: 425 | O81: =SUM(J81:M81)-N81 -> 425 | Q81: 15 | R81: 04 | S81: 12648298000120
A82: 08/2025 | B82: 43979 | C82: Atta | D82: Lilian Plus | E82: Vesti (Fatura) | F82: Avançado | H82: 425 | J82: 425 | O82: =SUM(J82:M82)-N82 -> 425 | Q82: 15 | R82: 04 | S82: 51200947000187
A83: 08/2025 | B83: 43983 | C83: VESTI | D83: Blubetty | E83: Vesti (Fatura) | F83: Profissional | H83: 1330 | J83: 1330 | K83: 350 | O83: =SUM(J83:M83)-N83 -> 1680 | Q83: 15 | R83: 04 | S83: 01102343000120
A84: 08/2025 | B84: 43983 | C84: VESTI | D84: Di Collani | E84: Vesti (Fatura) | F84: Profissional | H84: 2110.33 | J84: 2110.33 | K84: 500 | O84: =SUM(J84:M84)-N84 -> 2610.33 | Q84: 11 | R84: 04 | S84: 01102343000120
A85: 08/2025 | B85: 43983 | C85: VESTI | D85: Jeanseria | E85: Vesti (Fatura) | F85: Profissional | H85: 405 | J85: 405 | K85: 350 | O85: =SUM(J85:M85)-N85 -> 755 | Q85: 11 | R85: 04 | S85: 01102343000120
A86: 08/2025 | B86: 43984 | C86: Atta | D86: Coqueta | E86: Vesti (Fatura) | F86: Avançado | H86: 472.33 | J86: 472.33 | L86: =1530+240 -> 1770 | M86: 380 | O86: =SUM(J86:M86)-N86 -> 2622.33 | Q86: 11 | R86: 04 | S86: 58687526000171
A87: 08/2025 | B87: 43986 | C87: Atta | D87: Clio | E87: Vesti (Fatura) | F87: Avançado | H87: 425 | J87: 425 | O87: =SUM(J87:M87)-N87 -> 425 | Q87: 15 | R87: 04 | S87: 05550677000117
A88: 08/2025 | B88: 43986 | C88: Atta | D88: Planchet | E88: Vesti (Fatura) | F88: Avançado | H88: 425 | J88: 425 | O88: =SUM(J88:M88)-N88 -> 425 | Q88: 15 | R88: 04 | S88: 03243396000196
A89: 08/2025 | B89: 43990 | C89: Atta | D89: Bestié | E89: Vesti (Fatura) | F89: Avançado | H89: 425 | J89: 425 | O89: =SUM(J89:M89)-N89 -> 425 | Q89: 12 | R89: 04 | S89: 50751845000197
A90: 08/2025 | B90: 43992 | C90: VESTI | D90: Monclos | E90: Vesti (Fatura) | F90: Avançado | H90: 426.33 | J90: 426.33 | O90: =SUM(J90:M90)-N90 -> 426.33 | Q90: 11 | R90: 04 | S90: 59812453000246
A91: 08/2025 | B91: 43994 | C91: Atta | D91: Moirai | E91: Vesti (Fatura) | F91: Avançado | H91: 452.67 | J91: 452.67 | O91: =SUM(J91:M91)-N91 -> 452.67 | Q91: 15 | R91: 04 | S91: 29380107000194
A92: 08/2025 | B92: 44000 | C92: Atta | D92: Noir | E92: Vesti (Fatura) | F92: Avançado | H92: 425 | J92: 425 | O92: =SUM(J92:M92)-N92 -> 425 | Q92: 15 | R92: 04 | S92: 02415964000126
A93: 08/2025 | B93: 44006 | C93: Atta | D93: French Kiss | E93: Vesti (Fatura) | F93: Avançado | H93: 457 | J93: 457 | O93: =SUM(J93:M93)-N93 -> 457 | Q93: 15 | R93: 04 | S93: 65977878000127
A94: 08/2025 | B94: 44006 | C94: VESTI | D94: Wool Line | E94: Vesti (Fatura) | F94: Avançado | H94: 425 | J94: 425 | O94: =SUM(J94:M94)-N94 -> 425 | Q94: 11 | R94: 04 | S94: 23398902000123
A95: 08/2025 | B95: 44007 | C95: VESTI | D95: Amofany | E95: Vesti (Fatura) | F95: Profissional | H95: 1179 | J95: 1179 | K95: 350 | O95: =SUM(J95:M95)-N95 -> 1529 | Q95: 15 | R95: 04 | S95: 09657596000171
A96: 08/2025 | B96: 44008 | C96: VESTI | D96: Four One | E96: Vesti (Fatura) | F96: Avançado | H96: 425 | J96: 425 | M96: 359 | O96: =SUM(J96:M96)-N96 -> 784 | Q96: 15 | R96: 04 | S96: 55646228000145
A97: 08/2025 | B97: 44008 | C97: VESTI | D97: Peri Plus Size | E97: Vesti (Fatura) | F97: Avançado | H97: 425 | J97: 425 | O97: =SUM(J97:M97)-N97 -> 425 | Q97: 15 | R97: 04 | S97: 41090419000169
A98: 08/2025 | B98: 44013 | C98: Atta | D98: Vitral | E98: Vesti (Fatura) | F98: Profissional | H98: 1410 | J98: 1410 | O98: =SUM(J98:M98)-N98 -> 1410 | Q98: 20 | R98: 04 | S98: 13578271000170
A99: 08/2025 | B99: 44014 | C99: Atta | D99: Seiss & Deiss | E99: Vesti (Fatura) | F99: Essencial | H99: 408.67 | J99: 408.67 | O99: =SUM(J99:M99)-N99 -> 408.67 | Q99: 15 | R99: 04 | S99: 17685722000120
A100: 08/2025 | B100: 44015 | C100: VESTI | D100: Buccanes | E100: Vesti (Fatura) | F100: Essencial | H100: 283 | J100: 283 | O100: =SUM(J100:M100)-N100 -> 283 | Q100: 15 | R100: 04 | S100: 55251292000127
...

Sheet Vesti 09-25
A1: Fat.2025 | B1: ANIVERSÁRIO | C1: CANAL | D1: MARCA | E1: Subconta | F1: PLANO | G1: SETUP | H1: MENSALIDADE INICIAL | I1: VALOR REAJUSTE | J1: MENSALIDADE | K1: INTEGRAÇÃO | L1: ASSISTENTE | M1: FILIAL | N1: DESCONTOS | O1: TOTAL COBRADO | P1: OBSERVAÇÕES | Q1: Dia Vencimento | R1: Mês de Reajuste | S1: CPFCNPJ
A2: 09/2025 | B2: 42795 | C2: VESTI | D2: TNW Jeans | E2: Vesti (Assinatura) | F2: Profissional | H2: 1156 | J2: 1156 | O2: =SUM(J2:M2)-N2 -> 1156 | Q2: 17 | R2: 04 | S2: 4937453000108
A3: 09/2025 | B3: 42937 | C3: Atta | D3: Peonia | E3: Atta | F3: Essencial | H3: 302 | J3: 302 | O3: =SUM(J3:M3)-N3 -> 302 | Q3: 20 | R3: 4 | S3: 07993188000165
A4: 09/2025 | B4: 43160 | C4: Atta | D4: Maria De Chita | E4: Vesti (Assinatura) | F4: Profissional | H4: 724 | J4: 724 | O4: =SUM(J4:M4)-N4 -> 724 | Q4: 15 | R4: 04 | S4: 07402979000173
A5: 09/2025 | B5: 43160 | C5: Atta | D5: Shanes | E5: Vesti (Assinatura) | F5: Profissional | H5: 1179 | J5: 1179 | O5: =SUM(J5:M5)-N5 -> 1179 | Q5: 20 | R5: 04 | S5: 46446130000153
A6: 09/2025 | B6: 43160 | C6: Atta | D6: Talgui | E6: Vesti (Assinatura) | F6: Avançado | H6: 441.33 | J6: 441.33 | O6: =SUM(J6:M6)-N6 -> 441.33 | Q6: 15 | R6: 04 | S6: 05876663000198
A7: 09/2025 | B7: 43160 | C7: Atta | D7: Codi Codi | E7: Vesti (Assinatura) | F7: Profissional | H7: 889 | J7: 889 | O7: =SUM(J7:M7)-N7 -> 889 | Q7: 15 | R7: 04 | S7: 18555123000154
A8: 09/2025 | B8: 43160 | C8: Atta | D8: Coinage | E8: Vesti (Assinatura) | F8: Profissional | H8: 1179 | J8: 1179 | O8: =SUM(J8:M8)-N8 -> 1179 | Q8: 20 | R8: 04 | S8: 33724927000123
A9: 09/2025 | B9: 43160 | C9: Atta | D9: Moda Inn | E9: Vesti (Assinatura) | F9: Essencial | H9: 283 | J9: 283 | O9: =SUM(J9:M9)-N9 -> 283 | Q9: 20 | R9: 04 | S9: 49921554000110
A10: 09/2025 | B10: 43160 | C10: Atta | D10: Licommo | E10: Vesti (Assinatura) | F10: Avançado | H10: 425 | J10: 425 | O10: =SUM(J10:M10)-N10 -> 425 | Q10: 15 | R10: 04 | S10: 08325746000187
A11: 09/2025 | B11: 43160 | C11: Atta | D11: Betsey | E11: Vesti (Assinatura) | F11: Profissional | H11: 1003 | J11: 1003 | O11: =SUM(J11:M11)-N11 -> 1003 | Q11: 15 | R11: 04 | S11: 06161024000109
A12: 09/2025 | B12: 43160 | C12: Atta | D12: Cashier | E12: Vesti (Assinatura) | F12: Profissional | H12: 1015 | J12: 1015 | O12: =SUM(J12:M12)-N12 -> 1015 | Q12: 30 | R12: 04 | S12: 60368669000162
A13: 09/2025 | B13: 43160 | C13: Atta | D13: Cony Green | E13: Vesti (Assinatura) | F13: Avançado | H13: 425 | J13: 425 | O13: =SUM(J13:M13)-N13 -> 425 | Q13: 15 | R13: 04 | S13: 44511277000154
A14: 09/2025 | B14: 43160 | C14: Atta | D14: Pury | E14: Vesti (Assinatura) | F14: Profissional | H14: 1327 | J14: 1327 | M14: 359 | O14: =SUM(J14:M14)-N14 -> 1686 | Q14: 15 | R14: 04 | S14: 12576594000162
A15: 09/2025 | B15: 43160 | C15: Atta | D15: Nanaminze | E15: Vesti (Assinatura) | F15: Profissional | H15: 1179 | J15: 1179 | M15: 359 | O15: =SUM(J15:M15)-N15 -> 1538 | Q15: 15 | R15: 04 | S15: 12656331000163
A16: 09/2025 | B16: 43160 | C16: VESTI | D16: Tricomix | E16: Vesti (Assinatura) | F16: Avançado | H16: 1193 | J16: 1193 | K16: 350 | O16: =SUM(J16:M16)-N16 -> 1543 | Q16: 11 | R16: 04 | S16: 04665515000161
A17: 09/2025 | B17: 43160 | C17: Atta | D17: Lov It | E17: Vesti (Assinatura) | F17: Avançado | H17: 425 | J17: 425 | O17: =SUM(J17:M17)-N17 -> 425 | Q17: 11 | R17: 04 | S17: 21749422000215
A18: 09/2025 | B18: 43160 | C18: Atta | D18: Hemix | E18: Vesti (Assinatura) | F18: Essencial | H18: 283 | J18: 283 | L18: =550+120 -> 670 | O18: =SUM(J18:M18)-N18 -> 953 | Q18: 15 | R18: 04 | S18: 07389520000187
A19: 09/2025 | B19: 43160 | C19: Miredata | D19: Mottive | E19: Vesti (Assinatura) | F19: Profissional | H19: 1179 | J19: 1179 | O19: =SUM(J19:M19)-N19 -> 1179 | Q19: 20 | R19: 04 | S19: 24330475000104
A20: 09/2025 | B20: 43160 | C20: Atta | D20: Miss Alfa | E20: Vesti (Assinatura) | F20: Essencial | H20: 283 | J20: 283 | O20: =SUM(J20:M20)-N20 -> 283 | Q20: 15 | R20: 04 | S20: 28497561000167
A21: 09/2025 | B21: 43160 | C21: VESTI | D21: Anemone | E21: Vesti (Assinatura) | F21: Avançado | H21: 1013 | J21: 1013 | O21: =SUM(J21:M21)-N21 -> 1013 | Q21: 11 | R21: 04 | S21: 30962814000178
A22: 09/2025 | B22: 43160 | C22: Miredata | D22: Pianeta | E22: Vesti (Assinatura) | F22: Profissional | H22: 761 | J22: 761 | O22: =SUM(J22:M22)-N22 -> 761 | Q22: 20 | R22: 04 | S22: 31583000000195
A23: 09/2025 | B23: 43356 | C23: Atta | D23: Morina | E23: Vesti (Assinatura) | F23: Profissional | H23: 1138 | J23: 1138 | O23: =SUM(J23:M23)-N23 -> 1138 | Q23: 15 | R23: 04 | S23: 44029041000186
A24: 09/2025 | B24: 43586 | C24: Atta | D24: Artemiss | E24: Vesti (Assinatura) | F24: Avançado | H24: 569 | J24: 569 | M24: 275 | O24: =SUM(J24:M24)-N24 -> 844 | Q24: 11 | R24: 04 | S24: 05320347000135
A25: 09/2025 | B25: 43586 | C25: Atta | D25: IT LOOK | E25: Vesti (Assinatura) | F25: Essencial | H25: 283 | J25: 283 | O25: =SUM(J25:M25)-N25 -> 283 | Q25: 15 | R25: 04 | S25: 21659326000103
A26: 09/2025 | B26: 43586 | C26: Atta | D26: E YUNIRE | E26: Vesti (Assinatura) | F26: Essencial | H26: 354 | J26: 354 | O26: =SUM(J26:M26)-N26 -> 354 | Q26: 15 | R26: 04 | S26: 45375658000116
A27: 09/2025 | B27: 43593 | C27: Atta | D27: Incentive | E27: Vesti (Assinatura) | F27: Essencial | H27: 528.33 | J27: 528.33 | L27: 850 | O27: =SUM(J27:M27)-N27 -> 1378.33 | Q27: 30 | R27: 04 | S27: 29780242000127
A28: 09/2025 | B28: 43593 | C28: Atta | D28: Mariá/Aurora | E28: Vesti (Assinatura) | F28: Essencial | H28: 283 | J28: 283 | O28: =SUM(J28:M28)-N28 -> 283 | Q28: 20 | R28: 04 | S28: 33076814000169
A29: 09/2025 | B29: 43593 | C29: Atta | D29: Mazarin | E29: Vesti (Assinatura) | F29: Essencial | H29: 326.67 | J29: 326.67 | O29: =SUM(J29:M29)-N29 -> 326.67 | Q29: 15 | R29: 04 | S29: 03598605000203
A30: 09/2025 | B30: 43600 | C30: Atta | D30: Blue Blossom | E30: Vesti (Assinatura) | F30: Essencial | H30: 283 | J30: 283 | M30: 410 | O30: =SUM(J30:M30)-N30 -> 693 | Q30: 15 | R30: 04 | S30: 30828978000107
A31: 09/2025 | B31: 43606 | C31: VESTI | D31: Crocker | E31: Vesti (Assinatura) | F31: Profissional | H31: 1179 | J31: 1179 | M31: 410 | O31: =SUM(J31:M31)-N31 -> 1589 | Q31: 15 | R31: 04 | S31: 60652948000153
A32: 09/2025 | B32: 43606 | C32: VESTI | D32: Lesto | E32: Vesti (Assinatura) | F32: Essencial | H32: 284.33 | J32: 284.33 | O32: =SUM(J32:M32)-N32 -> 284.33 | Q32: 15 | R32: 04 | S32: 58418377000145
A33: 09/2025 | B33: 43619 | C33: Atta | D33: Ellen One | E33: Vesti (Cartão) | F33: Essencial | H33: 283 | J33: 283 | O33: =SUM(J33:M33)-N33 -> 283 | Q33: 06 | R33: 4 | S33: 07554437000116
A34: 09/2025 | B34: 43619 | C34: Atta | D34: Instar | E34: Vesti (Assinatura) | F34: Essencial | H34: 283 | J34: 283 | O34: =SUM(J34:M34)-N34 -> 283 | Q34: 15 | R34: 04 | S34: 32649954000116
A35: 09/2025 | B35: 43633 | C35: Atta | D35: Aramodu | E35: Vesti (Assinatura) | F35: Essencial | H35: 283 | J35: 283 | O35: =SUM(J35:M35)-N35 -> 283 | Q35: 11 | R35: 04 | S35: 97541061000106
A36: 09/2025 | B36: 43643 | C36: Atta | D36: Scera | E36: Vesti (Assinatura) | F36: Essencial | H36: 283 | J36: 283 | M36: 410 | O36: =SUM(J36:M36)-N36 -> 693 | Q36: 15 | R36: 04 | S36: 23333642000108
A37: 09/2025 | B37: 43649 | C37: Atta | D37: Fama Fashion | E37: Vesti (Assinatura) | F37: Essencial | H37: 283 | J37: 283 | O37: =SUM(J37:M37)-N37 -> 283 | Q37: 20 | R37: 04 | S37: 54451398000101
A38: 09/2025 | B38: 43649 | C38: VESTI | D38: Paloma Concept | E38: Vesti (Assinatura) | F38: Essencial | H38: 283 | J38: 283 | O38: =SUM(J38:M38)-N38 -> 283 | Q38: 15 | R38: 04 | S38: 16579598000155
A39: 09/2025 | B39: 43656 | C39: Atta | D39: Cheers | E39: Vesti (Assinatura) | F39: Profissional | H39: 1179 | J39: 1179 | O39: =SUM(J39:M39)-N39 -> 1179 | Q39: 11 | R39: 04 | S39: 53659785000175
A40: 09/2025 | B40: 43656 | C40: Atta | D40: Fesperamor | E40: Vesti (Assinatura) | F40: Profissional | H40: 1179 | J40: 1179 | O40: =SUM(J40:M40)-N40 -> 1179 | Q40: 15 | R40: 04 | S40: 22015485000120
A41: 09/2025 | B41: 43675 | C41: Atta | D41: Quebela | E41: Vesti (Assinatura) | F41: Essencial | H41: 425 | J41: 425 | O41: =SUM(J41:M41)-N41 -> 425 | Q41: 20 | R41: 04 | S41: 58525007000107
A42: 09/2025 | B42: 43684 | C42: Atta | D42: Genesis Jeans | E42: Vesti (Assinatura) | F42: Essencial | H42: 283 | J42: 283 | O42: =SUM(J42:M42)-N42 -> 283 | Q42: 15 | R42: 04 | S42: 21352130000163
A43: 09/2025 | B43: 43713 | C43: Vesti | D43: AMISKA - MISS MILLIE | E43: Vesti (Assinatura) | F43: Essencial | H43: 303 | J43: 303 | O43: =SUM(J43:M43)-N43 -> 303 | Q43: 15 | R43: 04 | S43: 24721940000138
A44: 09/2025 | B44: 43718 | C44: VESTI | D44: Join Curves | E44: Vesti (Assinatura) | F44: Avançado | H44: 486 | J44: 486 | L44: 1000 | M44: 600 | O44: =SUM(J44:M44)-N44 -> 2086 | Q44: 28 | R44: 04 | S44: 07867580000168
A45: 09/2025 | B45: 43719 | C45: Atta | D45: Namine | E45: Vesti (Assinatura) | F45: Profissional | H45: 1005 | J45: 1005 | M45: =266+900 -> 1166 | O45: =SUM(J45:M45)-N45 -> 2171 | Q45: 15 | R45: 04 | S45: 17820490000256
A46: 09/2025 | B46: 43731 | C46: VESTI | D46: Diamantes | E46: Vesti (Assinatura) | F46: Profissional | H46: 1400 | J46: 1400 | M46: =38*161.95+5 -> 6159.1 | O46: =SUM(J46:M46)-N46 -> 7559.1 | Q46: 15 | R46: 04 | S46: 13649755000163
A47: 09/2025 | B47: 43738 | C47: Atta | D47: Lily Daisy | E47: Vesti (Assinatura) | F47: Essencial | H47: 283 | J47: 283 | O47: =SUM(J47:M47)-N47 -> 283 | Q47: 15 | R47: 04 | S47: 34500000000172
A48: 09/2025 | B48: 43745 | C48: VESTI | D48: Ana Gonçalves Tricot = Luis Guilherme | E48: Vesti (Assinatura) | F48: Profissional | H48: 1179 | J48: 1179 | M48: 598 | O48: =SUM(J48:M48)-N48 -> 1777 | Q48: 15 | R48: 04 | S48: 11582787000163
A49: 09/2025 | B49: 43755 | C49: Atta | D49: Delight | E49: Vesti (Assinatura) | F49: Essencial | H49: 283 | J49: 283 | O49: =SUM(J49:M49)-N49 -> 283 | Q49: 15 | R49: 04 | S49: 21520947000101
A50: 09/2025 | B50: 43755 | C50: Atta | D50: Sori | E50: Vesti (Assinatura) | F50: Profissional | H50: 1179 | J50: 1179 | O50: =SUM(J50:M50)-N50 -> 1179 | Q50: 15 | R50: 04 | S50: 06987979000110
A51: 09/2025 | B51: 43768 | C51: Atta | D51: Mx | E51: Vesti (Assinatura) | F51: Profissional | H51: 1179 | J51: 1179 | O51: =SUM(J51:M51)-N51 -> 1179 | Q51: 20 | R51: 04 | S51: 05888414000112
A52: 09/2025 | B52: 43774 | C52: Atta | D52: Donna Ritz | E52: Vesti (Assinatura) | F52: Profissional | H52: 1076.67 | J52: 1076.67 | O52: =SUM(J52:M52)-N52 -> 1076.67 | Q52: 15 | R52: 04 | S52: 19521267000152
A53: 09/2025 | B53: 43802 | C53: VESTI | D53: Vida Bela | E53: Vesti (Assinatura) | F53: Essencial | H53: 283 | J53: 283 | O53: =SUM(J53:M53)-N53 -> 283 | Q53: 15 | R53: 04 | S53: 45668696000167
A54: 09/2025 | B54: 43846 | C54: Atta | D54: Sedanbi | E54: Vesti (Assinatura) | F54: Essencial | H54: 283 | J54: 283 | O54: =SUM(J54:M54)-N54 -> 283 | Q54: 15 | R54: 04 | S54: 00238342000306
A55: 09/2025 | B55: 43861 | C55: VESTI | D55: Rafa Brasil | E55: Vesti (Assinatura) | F55: Essencial | H55: 283 | J55: 283 | O55: =SUM(J55:M55)-N55 -> 283 | Q55: 15 | R55: 04 | S55: 30827010000166
A56: 09/2025 | B56: 43867 | C56: Atta | D56: Elae | E56: Vesti (Assinatura) | F56: Avançado | H56: 425 | J56: 425 | O56: =SUM(J56:M56)-N56 -> 425 | Q56: 20 | R56: 04 | S56: 46924221000157
A57: 09/2025 | B57: 43878 | C57: Atta | D57: As Marias | E57: Vesti (Assinatura) | F57: Essencial | H57: 283 | J57: 283 | O57: =SUM(J57:M57)-N57 -> 283 | Q57: 15 | R57: 04 | S57: 24487541000154
A58: 09/2025 | B58: 43888 | C58: VESTI | D58: Suzan Zheng | E58: Vesti (Assinatura) | F58: Essencial | H58: 283 | J58: 283 | O58: =SUM(J58:M58)-N58 -> 283 | Q58: 15 | R58: 04 | S58: 26551251000158
A59: 09/2025 | B59: 43892 | C59: VESTI | D59: Gliss Jeans | E59: Vesti (Assinatura) | F59: Essencial | H59: 283 | J59: 283 | M59: 199 | O59: =SUM(J59:M59)-N59 -> 482 | Q59: 11 | R59: 04 | S59: 55251292001107
A60: 09/2025 | B60: 43903 | C60: VESTI | D60: Bauarte | E60: Vesti (Assinatura) | F60: Avançado | H60: 1231 | J60: 1231 | K60: 350 | O60: =SUM(J60:M60)-N60 -> 1581 | Q60: 20 | R60: 04 | S60: 08754784000155
A61: 09/2025 | B61: 43920 | C61: Atta | D61: Alcance Jeans | E61: Vesti (Assinatura) | F61: Profissional | H61: 1243.35 | J61: 1243.35 | L61: 1920 | M61: 250 | O61: =SUM(J61:M61)-N61 -> 3413.35 | Q61: 11 | R61: 04 | S61: 27760882000140
A62: 09/2025 | B62: 43943 | C62: VESTI | D62: Sanreed | E62: Vesti (Assinatura) | F62: Essencial | H62: 283 | J62: 283 | M62: 359 | O62: =SUM(J62:M62)-N62 -> 642 | Q62: 15 | R62: 04 | S62: 23735214000292
A63: 09/2025 | B63: 43949 | C63: VESTI | D63: Vigor Basic | E63: Vesti (Assinatura) | F63: Essencial | H63: 283 | J63: 283 | O63: =SUM(J63:M63)-N63 -> 283 | Q63: 11 | R63: 04 | S63: 07085032000186
A64: 09/2025 | B64: 43950 | C64: VESTI | D64: Manaca= Visuh | E64: Vesti (Assinatura) | F64: Profissional | H64: 1179 | J64: 1179 | O64: =SUM(J64:M64)-N64 -> 1179 | Q64: 20 | R64: 04 | S64: 22221114000102
A65: 09/2025 | B65: 43955 | C65: Atta | D65: Bokeh | E65: Vesti (Assinatura) | F65: Avançado | H65: 425 | J65: 425 | O65: =SUM(J65:M65)-N65 -> 425 | Q65: 20 | R65: 04 | S65: 28489878000232
A66: 09/2025 | B66: 43958 | C66: Atta | D66: Hanabee | E66: Vesti (Assinatura) | F66: Avançado | H66: 425 | J66: 425 | O66: =SUM(J66:M66)-N66 -> 425 | Q66: 20 | R66: 04 | S66: 12395643000160
A67: 09/2025 | B67: 43958 | C67: Atta | D67: Innocence | E67: Vesti (Assinatura) | F67: Avançado | H67: 835 | J67: 835 | K67: 250 | O67: =SUM(J67:M67)-N67 -> 1085 | Q67: 15 | R67: 04 | S67: 17258262000153
A68: 09/2025 | B68: 43962 | C68: VESTI | D68: Cris Fael | E68: Vesti (Assinatura) | F68: Avançado | H68: 425 | J68: 425 | O68: =SUM(J68:M68)-N68 -> 425 | Q68: 15 | R68: 04 | S68: 52341858000113
A69: 09/2025 | B69: 43965 | C69: Atta | D69: Caroll | E69: Vesti (Assinatura) | F69: Avançado | H69: 665 | J69: 665 | O69: =SUM(J69:M69)-N69 -> 665 | Q69: 11 | R69: 04 | S69: 02683338000110
A70: 09/2025 | B70: 43965 | C70: Atta | D70: Kalli | E70: Vesti (Assinatura) | F70: Avançado | H70: 698 | J70: 698 | O70: =SUM(J70:M70)-N70 -> 698 | Q70: 11 | R70: 04 | S70: 17685726000108
A71: 09/2025 | B71: 43965 | C71: Atta | D71: Sexy Cookie | E71: Vesti (Assinatura) | F71: Profissional | H71: 1179 | J71: 1179 | O71: =SUM(J71:M71)-N71 -> 1179 | Q71: 11 | R71: 04 | S71: 08151457000109
A72: 09/2025 | B72: 43966 | C72: VESTI | D72: Adizza | E72: Vesti (Assinatura) | F72: Essencial | H72: 283 | J72: 283 | M72: 410 | O72: =SUM(J72:M72)-N72 -> 693 | Q72: 15 | R72: 04 | S72: 24881140000184
A73: 09/2025 | B73: 43966 | C73: VESTI | D73: Anahi | E73: Vesti (Assinatura) | F73: Avançado | H73: 425 | J73: 425 | O73: =SUM(J73:M73)-N73 -> 425 | Q73: 20 | R73: 04 | S73: 04049767000166
A74: 09/2025 | B74: 43972 | C74: Atta | D74: Ezee | E74: Vesti (Assinatura) | F74: Essencial | H74: 342.67 | J74: 342.67 | O74: =SUM(J74:M74)-N74 -> 342.67 | Q74: 15 | R74: 04 | S74: 28314192000120
A75: 09/2025 | B75: 43978 | C75: Atta | D75: Nakepe | E75: Vesti (Assinatura) | F75: Avançado | H75: 425 | J75: 425 | O75: =SUM(J75:M75)-N75 -> 425 | Q75: 22 | R75: 04 | S75: 00764187000108
A76: 09/2025 | B76: 43978 | C76: Atta | D76: Ste Fashion | E76: Vesti (Assinatura) | F76: Avançado | H76: 425 | J76: 425 | O76: =SUM(J76:M76)-N76 -> 425 | Q76: 15 | R76: 04 | S76: 12648298000120
A77: 09/2025 | B77: 43979 | C77: Atta | D77: Lilian Plus | E77: Vesti (Assinatura) | F77: Avançado | H77: 425 | J77: 425 | O77: =SUM(J77:M77)-N77 -> 425 | Q77: 15 | R77: 04 | S77: 51200947000187
A78: 09/2025 | B78: 43983 | C78: VESTI | D78: Blubetty | E78: Vesti (Assinatura) | F78: Profissional | H78: 1330 | J78: 1330 | K78: 350 | O78: =SUM(J78:M78)-N78 -> 1680 | Q78: 15 | R78: 04 | S78: 01102343000120
A79: 09/2025 | B79: 43983 | C79: VESTI | D79: Di Collani | E79: Vesti (Assinatura) | F79: Profissional | H79: 2110.33 | J79: 2110.33 | K79: 500 | O79: =SUM(J79:M79)-N79 -> 2610.33 | Q79: 11 | R79: 04 | S79: 01102343000120
A80: 09/2025 | B80: 43983 | C80: VESTI | D80: Jeanseria | E80: Vesti (Assinatura) | F80: Profissional | H80: 405 | J80: 405 | K80: 350 | O80: =SUM(J80:M80)-N80 -> 755 | Q80: 11 | R80: 04 | S80: 01102343000120
A81: 09/2025 | B81: 43984 | C81: Atta | D81: Coqueta | E81: Vesti (Assinatura) | F81: Avançado | H81: 472.33 | J81: 472.33 | L81: =1530+240 -> 1770 | M81: 380 | O81: =SUM(J81:M81)-N81 -> 2622.33 | Q81: 11 | R81: 04 | S81: 58687526000171
A82: 09/2025 | B82: 43986 | C82: Atta | D82: Clio | E82: Vesti (Assinatura) | F82: Avançado | H82: 425 | J82: 425 | O82: =SUM(J82:M82)-N82 -> 425 | Q82: 15 | R82: 04 | S82: 05550677000117
A83: 09/2025 | B83: 43986 | C83: Atta | D83: Planchet | E83: Vesti (Assinatura) | F83: Avançado | H83: 425 | J83: 425 | O83: =SUM(J83:M83)-N83 -> 425 | Q83: 15 | R83: 04 | S83: 03243396000196
A84: 09/2025 | B84: 43990 | C84: Atta | D84: Bestié | E84: Vesti (Assinatura) | F84: Avançado | H84: 425 | J84: 425 | O84: =SUM(J84:M84)-N84 -> 425 | Q84: 12 | R84: 04 | S84: 50751845000197
A85: 09/2025 | B85: 43992 | C85: VESTI | D85: Monclos | E85: Vesti (Assinatura) | F85: Avançado | H85: 426.33 | J85: 426.33 | O85: =SUM(J85:M85)-N85 -> 426.33 | Q85: 11 | R85: 04 | S85: 59812453000246
A86: 09/2025 | B86: 43994 | C86: Atta | D86: Moirai | E86: Vesti (Assinatura) | F86: Avançado | H86: 452.67 | J86: 452.67 | O86: =SUM(J86:M86)-N86 -> 452.67 | Q86: 15 | R86: 04 | S86: 29380107000194
A87: 09/2025 | B87: 44000 | C87: Atta | D87: Noir | E87: Vesti (Assinatura) | F87: Avançado | H87: 425 | J87: 425 | O87: =SUM(J87:M87)-N87 -> 425 | Q87: 15 | R87: 04 | S87: 02415964000126
A88: 09/2025 | B88: 44006 | C88: Atta | D88: French Kiss | E88: Vesti (Assinatura) | F88: Avançado | H88: 457 | J88: 457 | O88: =SUM(J88:M88)-N88 -> 457 | Q88: 15 | R88: 04 | S88: 65977878000127
A89: 09/2025 | B89: 44006 | C89: VESTI | D89: Wool Line | E89: Vesti (Assinatura) | F89: Avançado | H89: 425 | J89: 425 | O89: =SUM(J89:M89)-N89 -> 425 | Q89: 11 | R89: 04 | S89: 23398902000123
A90: 09/2025 | B90: 44007 | C90: VESTI | D90: Amofany | E90: Vesti (Assinatura) | F90: Profissional | H90: 1179 | J90: 1179 | K90: 350 | O90: =SUM(J90:M90)-N90 -> 1529 | Q90: 15 | R90: 04 | S90: 09657596000171
A91: 09/2025 | B91: 44008 | C91: VESTI | D91: Four One | E91: Vesti (Assinatura) | F91: Avançado | H91: 425 | J91: 425 | M91: 359 | O91: =SUM(J91:M91)-N91 -> 784 | Q91: 15 | R91: 04 | S91: 55646228000145
A92: 09/2025 | B92: 44008 | C92: VESTI | D92: Peri Plus Size | E92: Vesti (Assinatura) | F92: Avançado | H92: 425 | J92: 425 | O92: =SUM(J92:M92)-N92 -> 425 | Q92: 15 | R92: 04 | S92: 41090419000169
A93: 09/2025 | B93: 44013 | C93: Atta | D93: Vitral | E93: Vesti (Assinatura) | F93: Profissional | H93: 1179 | J93: 1179 | O93: =SUM(J93:M93)-N93 -> 1179 | Q93: 20 | R93: 04 | S93: 13578271000170
A94: 09/2025 | B94: 44014 | C94: Atta | D94: Seiss & Deiss | E94: Vesti (Assinatura) | F94: Essencial | H94: 364.67 | J94: 364.67 | O94: =SUM(J94:M94)-N94 -> 364.67 | Q94: 15 | R94: 04 | S94: 17685722000120
A95: 09/2025 | B95: 44015 | C95: VESTI | D95: Buccanes | E95: Vesti (Assinatura) | F95: Essencial | H95: 283 | J95: 283 | O95: =SUM(J95:M95)-N95 -> 283 | Q95: 15 | R95: 04 | S95: 55251292000127
A96: 09/2025 | B96: 44017 | C96: Atta | D96: Hirus | E96: Vesti (Assinatura) | F96: Avançado | H96: 509 | J96: 509 | O96: =SUM(J96:M96)-N96 -> 509 | Q96: 15 | R96: 04 | S96: 07752324000206
A97: 09/2025 | B97: 44020 | C97: Atta | D97: Rubicon | E97: Vesti (Assinatura) | F97: Avançado | H97: 425 | J97: 425 | O97: =SUM(J97:M97)-N97 -> 425 | Q97: 15 | R97: 04 | S97: 24002700000183
A98: 09/2025 | B98: 44021 | C98: VESTI | D98: Lorsa | E98: Vesti (Assinatura) | F98: Avançado | H98: 425 | J98: 425 | O98: =SUM(J98:M98)-N98 -> 425 | Q98: 22 | R98: 04 | S98: 46046876000170
A99: 09/2025 | B99: 44025 | C99: VESTI | D99: Equivoco | E99: Vesti (Assinatura) | F99: Avançado | H99: 425 | J99: 425 | O99: =SUM(J99:M99)-N99 -> 425 | Q99: 22 | R99: 04 | S99: 46046876000927
A100: 09/2025 | B100: 44027 | C100: Atta | D100: Acqua Marine | E100: Vesti (Assinatura) | F100: Avançado | H100: 509 | J100: 509 | O100: =SUM(J100:M100)-N100 -> 509 | Q100: 20 | R100: 04 | S100: 56353866000130
...

Sheet Vesti 10-25
A1: Fat.2025 | B1: ANIVERSÁRIO | C1: CANAL | D1: MARCA | E1: Subconta | F1: PLANO | G1: SETUP | H1: MENSALIDADE INICIAL | I1: VALOR REAJUSTE | J1: MENSALIDADE | K1: INTEGRAÇÃO | L1: ASSISTENTE | M1: FILIAL | N1: DESCONTOS | O1: TOTAL COBRADO | P1: OBSERVAÇÕES | Q1: Dia Vencimento | R1: Mês de Reajuste | S1: CPFCNPJ | T1: NOME/RAZÃO SOCIAL
A2: 10/2025 | B2: 42795 | C2: VESTI | D2: TNW Jeans | E2: Vesti (Assinatura) | F2: Profissional | H2: 1156 | J2: 1156 | O2: =SUM(J2:M2)-N2 -> 1156 | Q2: 17 | R2: 04 | S2: 4937453000108 | T2: TNW JEANS = TNW CONFECCOES LTDA
A3: 10/2025 | B3: 42937 | C3: Atta | D3: Peonia | E3: Atta | F3: Essencial | H3: 302 | J3: 302 | O3: =SUM(J3:M3)-N3 -> 302 | Q3: 20 | R3: 4 | S3: 07993188000165
A4: 10/2025 | B4: 43160 | C4: Atta | D4: Maria De Chita | E4: Vesti (Assinatura) | F4: Profissional | H4: 724 | J4: 724 | O4: =SUM(J4:M4)-N4 -> 724 | Q4: 15 | R4: 04 | S4: 07402979000173 | T4: MARIA DE CHITA = MARIA DE CHITA CONFECCOES LTDA
A5: 10/2025 | B5: 43160 | C5: Atta | D5: Shanes | E5: Vesti (Assinatura) | F5: Profissional | H5: 1179 | J5: 1179 | O5: =SUM(J5:M5)-N5 -> 1179 | Q5: 20 | R5: 04 | S5: 46446130000153 | T5: SHANES = CONFECCOES SHANES LTDA
A6: 10/2025 | B6: 43160 | C6: Atta | D6: Talgui | E6: Vesti (Assinatura) | F6: Avançado | H6: 441.33 | J6: 441.33 | O6: =SUM(J6:M6)-N6 -> 441.33 | Q6: 15 | R6: 04 | S6: 05876663000198 | T6: TALGUI = TALGUI CONFECCOES DE ROUPAS LTDA
A7: 10/2025 | B7: 43160 | C7: Atta | D7: Codi Codi | E7: Vesti (Assinatura) | F7: Profissional | H7: 889 | J7: 889 | O7: =SUM(J7:M7)-N7 -> 889 | Q7: 15 | R7: 04 | S7: 18555123000154 | T7: CODI CODI = MOONKA CONFECCOES LTDA EPP
A8: 10/2025 | B8: 43160 | C8: Atta | D8: Coinage | E8: Vesti (Assinatura) | F8: Profissional | H8: 1179 | J8: 1179 | O8: =SUM(J8:M8)-N8 -> 1179 | Q8: 20 | R8: 04 | S8: 33724927000123 | T8: Coinage = DON IN CONFECCOES LTDA
A9: 10/2025 | B9: 43160 | C9: Atta | D9: Moda Inn | E9: Vesti (Assinatura) | F9: Essencial | H9: 283 | J9: 283 | O9: =SUM(J9:M9)-N9 -> 283 | Q9: 20 | R9: 04 | S9: 49921554000110 | T9: MODA INN = CONFECCOES SIMON LTDA
A10: 10/2025 | B10: 43160 | C10: Atta | D10: Licommo | E10: Vesti (Assinatura) | F10: Avançado | H10: 425 | J10: 425 | O10: =SUM(J10:M10)-N10 -> 425 | Q10: 15 | R10: 04 | S10: 08325746000187 | T10: LICOMMO = CONFECCOES LICOMMO LTDA
A11: 10/2025 | B11: 43160 | C11: Atta | D11: Betsey | E11: Vesti (Assinatura) | F11: Profissional | H11: 1003 | J11: 1003 | O11: =SUM(J11:M11)-N11 -> 1003 | Q11: 15 | R11: 04 | S11: 06161024000109 | T11: BETSEY = BETSEY CONFECCOES LTDA
A12: 10/2025 | B12: 43160 | C12: Atta | D12: Cashier | E12: Vesti (Assinatura) | F12: Profissional | H12: 1015 | J12: 1015 | O12: =SUM(J12:M12)-N12 -> 1015 | Q12: 30 | R12: 04 | S12: 60368669000162 | T12: CASHIER = CASHIER CONFECCOES LTDA
A13: 10/2025 | B13: 43160 | C13: Atta | D13: Cony Green | E13: Vesti (Assinatura) | F13: Avançado | H13: 425 | J13: 425 | O13: =SUM(J13:M13)-N13 -> 425 | Q13: 15 | R13: 04 | S13: 44511277000154 | T13: CONY GREEN = CONFECCOES E MODAS CONY GREEN LTDA
A14: 10/2025 | B14: 43160 | C14: Atta | D14: Pury | E14: Vesti (Assinatura) | F14: Profissional | H14: 1327 | J14: 1327 | M14: 359 | O14: =SUM(J14:M14)-N14 -> 1686 | Q14: 15 | R14: 04 | S14: 12576594000162 | T14: PURY = CONFECCOES PURY LTDA
A15: 10/2025 | B15: 43160 | C15: Atta | D15: Nanaminze | E15: Vesti (Assinatura) | F15: Profissional | H15: 1179 | J15: 1179 | M15: 359 | O15: =SUM(J15:M15)-N15 -> 1538 | Q15: 15 | R15: 04 | S15: 12656331000163 | T15: NANAMINZE = HELIAS DAI KIM
A16: 10/2025 | B16: 43160 | C16: VESTI | D16: Tricomix | E16: Vesti (Assinatura) | F16: Avançado | H16: 1193 | J16: 1193 | K16: 350 | O16: =SUM(J16:M16)-N16 -> 1543 | Q16: 11 | R16: 04 | S16: 04665515000161 | T16: TRICOMIX = TRICOMIX INDUSTRIA E COMERCIO DE CONFECCOES EIRELI
A17: 10/2025 | B17: 43160 | C17: Atta | D17: Lov It | E17: Vesti (Assinatura) | F17: Avançado | H17: 425 | J17: 425 | O17: =SUM(J17:M17)-N17 -> 425 | Q17: 11 | R17: 04 | S17: 21749422000215 | T17: LOV IT = WELOVIT CONFECCOES LTDA
A18: 10/2025 | B18: 43160 | C18: Atta | D18: Hemix | E18: Vesti (Assinatura) | F18: Essencial | H18: 283 | J18: 283 | L18: =550+120 -> 670 | O18: =SUM(J18:M18)-N18 -> 953 | Q18: 15 | R18: 04 | S18: 07389520000187 | T18: HEMIX = HEMIX CONFECCOES LTDA
A19: 10/2025 | B19: 43160 | C19: Miredata | D19: Mottive | E19: Vesti (Assinatura) | F19: Profissional | H19: 1179 | J19: 1179 | O19: =SUM(J19:M19)-N19 -> 1179 | Q19: 20 | R19: 04 | S19: 24330475000104 | T19: MOTTIVE = PROBELLAS CONFECCOES LTDA EPP
A20: 10/2025 | B20: 43160 | C20: Atta | D20: Miss Alfa | E20: Vesti (Assinatura) | F20: Essencial | H20: 283 | J20: 283 | O20: =SUM(J20:M20)-N20 -> 283 | Q20: 15 | R20: 04 | S20: 28497561000167 | T20: MISS ALFA = MISS ALFA COMERCIO DE ROUPAS LTDA
A21: 10/2025 | B21: 43160 | C21: VESTI | D21: Anemone | E21: Vesti (Assinatura) | F21: Avançado | H21: 1013 | J21: 1013 | O21: =SUM(J21:M21)-N21 -> 1013 | Q21: 11 | R21: 04 | S21: 30962814000178 | T21: ANEMONE = MM21 INDUSTRIA E COMERCIO DE ROUPAS LTDA
A22: 10/2025 | B22: 43160 | C22: Miredata | D22: Pianeta | E22: Vesti (Assinatura) | F22: Profissional | H22: 761 | J22: 761 | O22: =SUM(J22:M22)-N22 -> 761 | Q22: 20 | R22: 04 | S22: 31583000000195 | T22: PIANETA = INTERMIX CONFECCOES DE ROUPAS LTDA
A23: 10/2025 | B23: 43356 | C23: Atta | D23: Morina | E23: Vesti (Assinatura) | F23: Profissional | H23: 1138 | J23: 1138 | O23: =SUM(J23:M23)-N23 -> 1138 | Q23: 15 | R23: 04 | S23: 44029041000186 | T23: Morina = FYK CONFECCOES LTDA
A24: 10/2025 | B24: 43586 | C24: Atta | D24: Artemiss | E24: Vesti (Assinatura) | F24: Avançado | H24: 569 | J24: 569 | M24: 275 | O24: =SUM(J24:M24)-N24 -> 844 | Q24: 11 | R24: 04 | S24: 05320347000135 | T24: ARTEMISS = CONFECCOES ARTE E MISS LTDA
A25: 10/2025 | B25: 43586 | C25: Atta | D25: IT LOOK | E25: Vesti (Assinatura) | F25: Essencial | H25: 283 | J25: 283 | O25: =SUM(J25:M25)-N25 -> 283 | Q25: 15 | R25: 04 | S25: 21659326000103 | T25: IT LOOK = IT LOOK CONFECCAO E COMERCIO DE ROUPAS LTDA
A26: 10/2025 | B26: 43586 | C26: Atta | D26: E YUNIRE | E26: Vesti (Assinatura) | F26: Essencial | H26: 354 | J26: 354 | O26: =SUM(J26:M26)-N26 -> 354 | Q26: 15 | R26: 04 | S26: 45375658000116 | T26: E YUNIRE = YUNIVEST CONFECCOES LTDA
A27: 10/2025 | B27: 43593 | C27: Atta | D27: Incentive | E27: Vesti (Assinatura) | F27: Essencial | H27: 528.33 | J27: 528.33 | L27: 850 | O27: =SUM(J27:M27)-N27 -> 1378.33 | Q27: 30 | R27: 04 | S27: 29780242000127 | T27: INCENTIVE = CONFECCOES INCENTIVE LTDA
A28: 10/2025 | B28: 43593 | C28: Atta | D28: Mariá/Aurora | E28: Vesti (Assinatura) | F28: Essencial | H28: 283 | J28: 283 | O28: =SUM(J28:M28)-N28 -> 283 | Q28: 20 | R28: 04 | S28: 33076814000169 | T28: Maria/Aurora = OK MI DO
A29: 10/2025 | B29: 43593 | C29: Atta | D29: Mazarin | E29: Vesti (Assinatura) | F29: Essencial | H29: 326.67 | J29: 326.67 | O29: =SUM(J29:M29)-N29 -> 326.67 | Q29: 15 | R29: 04 | S29: 03598605000203 | T29: MAZARIN = CONFECCOES MAZARIN LTDA
A30: 10/2025 | B30: 43600 | C30: Atta | D30: Blue Blossom | E30: Vesti (Assinatura) | F30: Essencial | H30: 283 | J30: 283 | M30: 410 | O30: =SUM(J30:M30)-N30 -> 693 | Q30: 15 | R30: 04 | S30: 30828978000107 | T30: BLUE BLOSSOM = BLUE BLOSSOM CONFECCOES EIRELI
A31: 10/2025 | B31: 43606 | C31: VESTI | D31: Crocker | E31: Vesti (Assinatura) | F31: Profissional | H31: 1179 | J31: 1179 | M31: 410 | O31: =SUM(J31:M31)-N31 -> 1589 | Q31: 15 | R31: 04 | S31: 60652948000153 | T31: CROCKER = US BRASIL INDUSTRIA E COMERCIO DE ROUPAS LTDA
A32: 10/2025 | B32: 43606 | C32: VESTI | D32: Lesto | E32: Vesti (Assinatura) | F32: Essencial | H32: 284.33 | J32: 284.33 | O32: =SUM(J32:M32)-N32 -> 284.33 | Q32: 15 | R32: 04 | S32: 58418377000145 | T32: LESTO = LESTO CONFECCOES LTDA
A33: 10/2025 | B33: 43619 | C33: Atta | D33: Ellen One | E33: Vesti (Cartão) | F33: Essencial | H33: 283 | J33: 283 | O33: =SUM(J33:M33)-N33 -> 283 | Q33: 06 | R33: 4 | S33: 07554437000116 | T33: Ellen One = CONFECCOES ELLEN ONE EIRELI
A34: 10/2025 | B34: 43619 | C34: Atta | D34: Instar | E34: Vesti (Assinatura) | F34: Essencial | H34: 283 | J34: 283 | O34: =SUM(J34:M34)-N34 -> 283 | Q34: 15 | R34: 04 | S34: 32649954000116 | T34: INSTAR = CLASSY MISSY CONFECCAO DE ROUPAS LTDA
A35: 10/2025 | B35: 43633 | C35: Atta | D35: Aramodu | E35: Vesti (Assinatura) | F35: Essencial | H35: 283 | J35: 283 | O35: =SUM(J35:M35)-N35 -> 283 | Q35: 11 | R35: 04 | S35: 97541061000106 | T35: ARAMODU = CONFECCOES ARAMODU EIRELI
A36: 10/2025 | B36: 43643 | C36: Atta | D36: Scera | E36: Vesti (Assinatura) | F36: Essencial | H36: 283 | J36: 283 | O36: =SUM(J36:M36)-N36 -> 283 | Q36: 15 | R36: 04 | S36: 23333642000108 | T36: SCERA = SCERA MODA FEMININA LTDA
A37: 10/2025 | B37: 43649 | C37: Atta | D37: Fama Fashion | E37: Vesti (Assinatura) | F37: Essencial | H37: 283 | J37: 283 | O37: =SUM(J37:M37)-N37 -> 283 | Q37: 20 | R37: 04 | S37: 54451398000101 | T37: FAMA FASHION = FAMA FASHION CREACOES LTDA
A38: 10/2025 | B38: 43649 | C38: VESTI | D38: Paloma Concept | E38: Vesti (Assinatura) | F38: Essencial | H38: 283 | J38: 283 | O38: =SUM(J38:M38)-N38 -> 283 | Q38: 15 | R38: 04 | S38: 16579598000155 | T38: PALOMA CONCEPT = FABIO DE ARAUJO LIMA FERREIRA EIRELI
A39: 10/2025 | B39: 43656 | C39: Atta | D39: Cheers | E39: Vesti (Assinatura) | F39: Profissional | H39: 1179 | J39: 1179 | O39: =SUM(J39:M39)-N39 -> 1179 | Q39: 11 | R39: 04 | S39: 53659785000175 | T39: CHEERS = MODAS VISION LTDA
A40: 10/2025 | B40: 43656 | C40: Atta | D40: Fesperamor | E40: Vesti (Assinatura) | F40: Profissional | H40: 1179 | J40: 1179 | O40: =SUM(J40:M40)-N40 -> 1179 | Q40: 15 | R40: 04 | S40: 22015485000120 | T40: FESPERAMOR = JEH CONFECCOES LTDA
A41: 10/2025 | B41: 43675 | C41: Atta | D41: Quebela | E41: Vesti (Assinatura) | F41: Essencial | H41: 425 | J41: 425 | O41: =SUM(J41:M41)-N41 -> 425 | Q41: 20 | R41: 04 | S41: 58525007000107 | T41: QUEBELA = CONFECCOES QUEBELA LTDA
A42: 10/2025 | B42: 43684 | C42: Atta | D42: Genesis Jeans | E42: Vesti (Assinatura) | F42: Essencial | H42: 283 | J42: 283 | O42: =SUM(J42:M42)-N42 -> 283 | Q42: 15 | R42: 04 | S42: 21352130000163 | T42: GENESIS JEANS = GENESIS JEANS LTDA
A43: 10/2025 | B43: 43713 | C43: Vesti | D43: AMISKA - MISS MILLIE | E43: Vesti (Assinatura) | F43: Essencial | H43: 303 | J43: 303 | O43: =SUM(J43:M43)-N43 -> 303 | Q43: 15 | R43: 04 | S43: 24721940000138 | T43: AMISKA MISS MILLIE = CONFECCOES MISS MILLIE INDUSTRIA E COMERCIO DE ROUPAS LTDA EPP
A44: 10/2025 | B44: 43718 | C44: VESTI | D44: Join Curves | E44: Vesti (Assinatura) | F44: Avançado | H44: 486 | J44: 486 | L44: 1000 | M44: 600 | O44: =SUM(J44:M44)-N44 -> 2086 | Q44: 28 | R44: 04 | S44: 07867580000168 | T44: Join Curves = JULIA A H INDUSTRIA E COMERCIO DE ROUPAS LTDA
A45: 10/2025 | B45: 43719 | C45: Atta | D45: Namine | E45: Vesti (Assinatura) | F45: Profissional | H45: 1005 | J45: 1005 | M45: =266+900 -> 1166 | O45: =SUM(J45:M45)-N45 -> 2171 | Q45: 15 | R45: 04 | S45: 17820490000256 | T45: NAMINE = NAMINE CONFECCOES LTDA
A46: 10/2025 | B46: 43731 | C46: VESTI | D46: Diamantes | E46: Vesti (Assinatura) | F46: Profissional | H46: 1400 | J46: 1400 | M46: =38*161.95+5 -> 6159.1 | O46: =SUM(J46:M46)-N46 -> 7559.1 | Q46: 15 | R46: 04 | S46: 13649755000163 | T46: DIAMANTES = DIAMANTES LINGERIE LTDA
A47: 10/2025 | B47: 43738 | C47: Atta | D47: Lily Daisy | E47: Vesti (Assinatura) | F47: Essencial | H47: 283 | J47: 283 | O47: =SUM(J47:M47)-N47 -> 283 | Q47: 15 | R47: 04 | S47: 34500000000172 | T47: LILY DAISY = ATELIER LILY DAISY CONFECCOES LTDA
A48: 10/2025 | B48: 43745 | C48: VESTI | D48: Ana Gonçalves Tricot = Luis Guilherme | E48: Vesti (Assinatura) | F48: Profissional | H48: 1179 | J48: 1179 | M48: 598 | O48: =SUM(J48:M48)-N48 -> 1777 | Q48: 15 | R48: 04 | S48: 11582787000163 | T48: Ana Goncalves Tricot = LUIS GUILHERME GONCALVES LEMES EIRELI
A49: 10/2025 | B49: 43755 | C49: Atta | D49: Delight | E49: Vesti (Assinatura) | F49: Essencial | H49: 283 | J49: 283 | O49: =SUM(J49:M49)-N49 -> 283 | Q49: 15 | R49: 04 | S49: 21520947000101 | T49: DELIGHT = DELIGHT MODA FEMININA LTDA
A50: 10/2025 | B50: 43755 | C50: Atta | D50: Sori | E50: Vesti (Assinatura) | F50: Profissional | H50: 1179 | J50: 1179 | O50: =SUM(J50:M50)-N50 -> 1179 | Q50: 15 | R50: 04 | S50: 06987979000110 | T50: SORI = C. S. CHOI MODAS
A51: 10/2025 | B51: 43768 | C51: Atta | D51: Mx | E51: Vesti (Assinatura) | F51: Profissional | H51: 1179 | J51: 1179 | O51: =SUM(J51:M51)-N51 -> 1179 | Q51: 20 | R51: 04 | S51: 05888414000112 | T51: MX = CREACOES MX FASHION LTDA
A52: 10/2025 | B52: 43774 | C52: Atta | D52: Donna Ritz | E52: Vesti (Assinatura) | F52: Profissional | H52: 1076.67 | J52: 1076.67 | O52: =SUM(J52:M52)-N52 -> 1076.67 | Q52: 15 | R52: 04 | S52: 19521267000152 | T52: DONNA RITZ = RITZ FASHION CONFECCOES EIRELI EPP
A53: 10/2025 | B53: 43802 | C53: VESTI | D53: Vida Bela | E53: Vesti (Assinatura) | F53: Essencial | H53: 283 | J53: 283 | O53: =SUM(J53:M53)-N53 -> 283 | Q53: 15 | R53: 04 | S53: 45668696000167 | T53: VIDA BELA = SAMIR ABRAO BASSITT E CIA LTDA
A54: 10/2025 | B54: 43846 | C54: Atta | D54: Sedanbi | E54: Vesti (Assinatura) | F54: Essencial | H54: 283 | J54: 283 | O54: =SUM(J54:M54)-N54 -> 283 | Q54: 15 | R54: 04 | S54: 00238342000306 | T54: SEDANBI = COMERCIO E CONFECCOES DE ROUPAS S H EIRELI
A55: 10/2025 | B55: 43861 | C55: VESTI | D55: Rafa Brasil | E55: Vesti (Assinatura) | F55: Essencial | H55: 283 | J55: 283 | O55: =SUM(J55:M55)-N55 -> 283 | Q55: 15 | R55: 04 | S55: 30827010000166 | T55: RAFA BRASIL = EDUARDO FERREIRA MARQUES 06879922651
A56: 10/2025 | B56: 43867 | C56: Atta | D56: Elae | E56: Vesti (Assinatura) | F56: Avançado | H56: 425 | J56: 425 | O56: =SUM(J56:M56)-N56 -> 425 | Q56: 20 | R56: 04 | S56: 46924221000157 | T56: ELAE = CONFECCOES GERACAO ELAE LTDA
A57: 10/2025 | B57: 43878 | C57: Atta | D57: As Marias | E57: Vesti (Assinatura) | F57: Essencial | H57: 283 | J57: 283 | O57: =SUM(J57:M57)-N57 -> 283 | Q57: 15 | R57: 04 | S57: 24487541000154 | T57: As Marias = ELSA MARIA DA SILVA SOUZA
A58: 10/2025 | B58: 43888 | C58: VESTI | D58: Suzan Zheng | E58: Vesti (Assinatura) | F58: Essencial | H58: 283 | J58: 283 | O58: =SUM(J58:M58)-N58 -> 283 | Q58: 15 | R58: 04 | S58: 26551251000158 | T58: SUZAN ZHENG = Z COMERCIO DE ROUPAS EIRELI
A59: 10/2025 | B59: 43892 | C59: VESTI | D59: Gliss Jeans | E59: Vesti (Assinatura) | F59: Essencial | H59: 283 | J59: 283 | M59: 199 | O59: =SUM(J59:M59)-N59 -> 482 | Q59: 11 | R59: 04 | S59: 55251292001107 | T59: GLISS JEANS = JURRO INDUSTRIA E COMERCIO DE CONFECCOES LTDA
A60: 10/2025 | B60: 43903 | C60: VESTI | D60: Bauarte | E60: Vesti (Assinatura) | F60: Avançado | H60: 1231 | J60: 1231 | K60: 350 | O60: =SUM(J60:M60)-N60 -> 1581 | Q60: 20 | R60: 04 | S60: 08754784000155 | T60: BAUARTE = JP MONTEIRO ACESSORIOS DA MODA LTDA
A61: 10/2025 | B61: 43920 | C61: Atta | D61: Alcance Jeans | E61: Vesti (Assinatura) | F61: Profissional | H61: 1243.35 | J61: 1243.35 | M61: 250 | O61: =SUM(J61:M61)-N61 -> 1493.35 | Q61: 11 | R61: 04 | S61: 27760882000140 | T61: ALCANCE JEANS = MANUELA COSTA FILGUEIRAS
A62: 10/2025 | B62: 43943 | C62: VESTI | D62: Sanreed | E62: Vesti (Assinatura) | F62: Essencial | H62: 283 | J62: 283 | M62: 359 | O62: =SUM(J62:M62)-N62 -> 642 | Q62: 15 | R62: 04 | S62: 23735214000292 | T62: Sanreed = WIBE CONFECCOES EIRELI
A63: 10/2025 | B63: 43949 | C63: VESTI | D63: Vigor Basic | E63: Vesti (Assinatura) | F63: Essencial | H63: 283 | J63: 283 | O63: =SUM(J63:M63)-N63 -> 283 | Q63: 11 | R63: 04 | S63: 07085032000186 | T63: Vigor Basic = VIGOR TOTAL INDUSTRIA E COMERCIO DO VESTUARIO LTDA
A64: 10/2025 | B64: 43950 | C64: VESTI | D64: Manaca= Visuh | E64: Vesti (Assinatura) | F64: Profissional | H64: 1179 | J64: 1179 | O64: =SUM(J64:M64)-N64 -> 1179 | Q64: 20 | R64: 04 | S64: 22221114000102 | T64: MANACA = VISUH CONFECCOES LTDA EPP
A65: 10/2025 | B65: 43955 | C65: Atta | D65: Bokeh | E65: Vesti (Assinatura) | F65: Avançado | H65: 425 | J65: 425 | O65: =SUM(J65:M65)-N65 -> 425 | Q65: 20 | R65: 04 | S65: 28489878000232 | T65: BOKEH = CONFECCOES CHESED LTDA EPP
A66: 10/2025 | B66: 43958 | C66: Atta | D66: Hanabee | E66: Vesti (Assinatura) | F66: Avançado | H66: 425 | J66: 425 | O66: =SUM(J66:M66)-N66 -> 425 | Q66: 20 | R66: 04 | S66: 12395643000160 | T66: HANABEE = ESLEE CONFECCOES LTDA EPP
A67: 10/2025 | B67: 43958 | C67: Atta | D67: Innocence | E67: Vesti (Assinatura) | F67: Avançado | H67: 835 | J67: 835 | K67: 250 | O67: =SUM(J67:M67)-N67 -> 1085 | Q67: 15 | R67: 04 | S67: 17258262000153 | T67: INNOCENCE = SUN JOO KIM CONFECCOES
A68: 10/2025 | B68: 43962 | C68: VESTI | D68: Cris Fael | E68: Vesti (Assinatura) | F68: Avançado | H68: 425 | J68: 425 | O68: =SUM(J68:M68)-N68 -> 425 | Q68: 15 | R68: 04 | S68: 52341858000113 | T68: CRIS FAEL = CRISFAEL COMERCIO DE ACESSORIOS DA MODA LTDA
A69: 10/2025 | B69: 43965 | C69: Atta | D69: Caroll | E69: Vesti (Assinatura) | F69: Avançado | H69: 665 | J69: 665 | O69: =SUM(J69:M69)-N69 -> 665 | Q69: 11 | R69: 04 | S69: 02683338000110 | T69: CAROLL COLLECTION = CAROLL CONFECCOES IMPORTACAO E EXPORTACAO LTDA
A70: 10/2025 | B70: 43965 | C70: Atta | D70: Kalli | E70: Vesti (Assinatura) | F70: Avançado | H70: 698 | J70: 698 | O70: =SUM(J70:M70)-N70 -> 698 | Q70: 11 | R70: 04 | S70: 17685726000108 | T70: Kalli = CONFECCOES KALLI LTDA
A71: 10/2025 | B71: 43965 | C71: Atta | D71: Sexy Cookie | E71: Vesti (Assinatura) | F71: Profissional | H71: 1179 | J71: 1179 | O71: =SUM(J71:M71)-N71 -> 1179 | Q71: 11 | R71: 04 | S71: 08151457000109 | T71: Sexy Cookie = SEXY COOKIE CONFECCOES LTDA
A72: 10/2025 | B72: 43966 | C72: VESTI | D72: Adizza | E72: Vesti (Assinatura) | F72: Essencial | H72: 283 | J72: 283 | M72: 410 | O72: =SUM(J72:M72)-N72 -> 693 | Q72: 15 | R72: 04 | S72: 24881140000184 | T72: ADIZZA = PAULO CESAR VALERIANO SILVA
A73: 10/2025 | B73: 43966 | C73: VESTI | D73: Anahi | E73: Vesti (Assinatura) | F73: Avançado | H73: 425 | J73: 425 | O73: =SUM(J73:M73)-N73 -> 425 | Q73: 20 | R73: 04 | S73: 04049767000166 | T73: Anahi = ALTA MUN BIANCA CONFECCOES LTDA EPP
A74: 10/2025 | B74: 43972 | C74: Atta | D74: Ezee | E74: Vesti (Assinatura) | F74: Essencial | H74: 342.67 | J74: 342.67 | O74: =SUM(J74:M74)-N74 -> 342.67 | Q74: 15 | R74: 04 | S74: 28314192000120 | T74: EZEE = EZEE CONFECCOES DE ROUPAS EIRELI
A75: 10/2025 | B75: 43978 | C75: Atta | D75: Nakepe | E75: Vesti (Assinatura) | F75: Avançado | H75: 425 | J75: 425 | O75: =SUM(J75:M75)-N75 -> 425 | Q75: 22 | R75: 04 | S75: 00764187000108 | T75: NAKEPE = NAKEPE CREACOES LTDA
A76: 10/2025 | B76: 43978 | C76: Atta | D76: Ste Fashion | E76: Vesti (Assinatura) | F76: Avançado | H76: 425 | J76: 425 | O76: =SUM(J76:M76)-N76 -> 425 | Q76: 15 | R76: 04 | S76: 12648298000120 | T76: STE FASHION = CHOCO'S ARTIGOS DO VESTUARIO EIRELI
A77: 10/2025 | B77: 43979 | C77: Atta | D77: Lilian Plus | E77: Vesti (Assinatura) | F77: Avançado | H77: 425 | J77: 425 | O77: =SUM(J77:M77)-N77 -> 425 | Q77: 15 | R77: 04 | S77: 51200947000187 | T77: Lilian Plus = CONFECCOES LILIAN LTDA
A78: 10/2025 | B78: 43983 | C78: VESTI | D78: Blubetty | E78: Vesti (Assinatura) | F78: Profissional | H78: 1330 | J78: 1330 | K78: 350 | O78: =SUM(J78:M78)-N78 -> 1680 | Q78: 15 | R78: 04 | S78: 01102343000120 | T78: Blubetty = KAPITON CONFECCOES LTDA
A79: 10/2025 | B79: 43983 | C79: VESTI | D79: Di Collani | E79: Vesti (Assinatura) | F79: Profissional | H79: 2110.33 | J79: 2110.33 | K79: 500 | O79: =SUM(J79:M79)-N79 -> 2610.33 | Q79: 11 | R79: 04 | S79: 01102343000120 | T79: Di Collani = KAPITON CONFECCOES LTDA
A80: 10/2025 | B80: 43983 | C80: VESTI | D80: Jeanseria | E80: Vesti (Assinatura) | F80: Profissional | H80: 405 | J80: 405 | K80: 350 | O80: =SUM(J80:M80)-N80 -> 755 | Q80: 11 | R80: 04 | S80: 01102343000120 | T80: Jeanseria = KAPITON CONFECCOES LTDA
A81: 10/2025 | B81: 43984 | C81: Atta | D81: Coqueta | E81: Vesti (Assinatura) | F81: Avançado | H81: 472.33 | J81: 472.33 | L81: =1530+240 -> 1770 | M81: 380 | O81: =SUM(J81:M81)-N81 -> 2622.33 | Q81: 11 | R81: 04 | S81: 58687526000171 | T81: Coqueta = CONFECCOES COQUETA LTDA
A82: 10/2025 | B82: 43986 | C82: Atta | D82: Clio | E82: Vesti (Assinatura) | F82: Avançado | H82: 425 | J82: 425 | O82: =SUM(J82:M82)-N82 -> 425 | Q82: 15 | R82: 04 | S82: 05550677000117 | T82: Clio = CLIO CONFECCOES IMPORTACAO E EXPORTACAO LTDA
A83: 10/2025 | B83: 43986 | C83: Atta | D83: Planchet | E83: Vesti (Assinatura) | F83: Avançado | H83: 425 | J83: 425 | O83: =SUM(J83:M83)-N83 -> 425 | Q83: 15 | R83: 04 | S83: 03243396000196 | T83: Planchet = CONFECCOES PLANCHET EIRELI
A84: 10/2025 | B84: 43990 | C84: Atta | D84: Bestié | E84: Vesti (Assinatura) | F84: Avançado | H84: 425 | J84: 425 | O84: =SUM(J84:M84)-N84 -> 425 | Q84: 12 | R84: 04 | S84: 50751845000197 | T84: Bestie = CONFECCOES BESTIE LTDA
A85: 10/2025 | B85: 43992 | C85: VESTI | D85: Monclos | E85: Vesti (Assinatura) | F85: Avançado | H85: 426.33 | J85: 426.33 | O85: =SUM(J85:M85)-N85 -> 426.33 | Q85: 11 | R85: 04 | S85: 59812453000246 | T85: Monclos = CAN FLOW CONFECCOES LTDA
A86: 10/2025 | B86: 43994 | C86: Atta | D86: Moirai | E86: Vesti (Assinatura) | F86: Avançado | H86: 452.67 | J86: 452.67 | O86: =SUM(J86:M86)-N86 -> 452.67 | Q86: 15 | R86: 04 | S86: 29380107000194 | T86: MOIRAI = MOIRAI CONFECCAO DE ROUPAS EIRELI
A87: 10/2025 | B87: 44000 | C87: Atta | D87: Noir | E87: Vesti (Assinatura) | F87: Avançado | H87: 425 | J87: 425 | O87: =SUM(J87:M87)-N87 -> 425 | Q87: 15 | R87: 04 | S87: 02415964000126 | T87: Noir = CONFECCOES NOIR LTDA
A88: 10/2025 | B88: 44006 | C88: Atta | D88: French Kiss | E88: Vesti (Assinatura) | F88: Avançado | H88: 457 | J88: 457 | O88: =SUM(J88:M88)-N88 -> 457 | Q88: 15 | R88: 04 | S88: 65977878000127 | T88: French Kiss = GUARNIERIUS MODAS LTDA
A89: 10/2025 | B89: 44006 | C89: VESTI | D89: Wool Line | E89: Vesti (Assinatura) | F89: Avançado | H89: 425 | J89: 425 | O89: =SUM(J89:M89)-N89 -> 425 | Q89: 11 | R89: 04 | S89: 23398902000123 | T89: Wool Line = WOOL LINE CONFECCOES EIRELI
A90: 10/2025 | B90: 44007 | C90: VESTI | D90: Amofany | E90: Vesti (Assinatura) | F90: Profissional | H90: 1179 | J90: 1179 | K90: 350 | O90: =SUM(J90:M90)-N90 -> 1529 | Q90: 15 | R90: 04 | S90: 09657596000171 | T90: AMOFANY = Mabli confeccoes de roupas LTDA EPP
A91: 10/2025 | B91: 44008 | C91: VESTI | D91: Four One | E91: Vesti (Assinatura) | F91: Avançado | H91: 425 | J91: 425 | M91: 359 | O91: =SUM(J91:M91)-N91 -> 784 | Q91: 15 | R91: 04 | S91: 55646228000145 | T91: Four One Jeans = FOUR ONE INDUSTRIA E COMERCIO EIRELI
A92: 10/2025 | B92: 44008 | C92: VESTI | D92: Peri Plus Size | E92: Vesti (Assinatura) | F92: Avançado | H92: 425 | J92: 425 | O92: =SUM(J92:M92)-N92 -> 425 | Q92: 15 | R92: 04 | S92: 41090419000169 | T92: Peri Plus Size = MODAS PERI LTDA
A93: 10/2025 | B93: 44013 | C93: Atta | D93: Vitral | E93: Vesti (Assinatura) | F93: Profissional | H93: 1179 | J93: 1179 | O93: =SUM(J93:M93)-N93 -> 1179 | Q93: 20 | R93: 04 | S93: 13578271000170 | T93: VITRAL = J Y KIM CONFECCOES LTDA
A94: 10/2025 | B94: 44014 | C94: Atta | D94: Seiss & Deiss | E94: Vesti (Assinatura) | F94: Essencial | H94: 364.67 | J94: 364.67 | O94: =SUM(J94:M94)-N94 -> 364.67 | Q94: 15 | R94: 04 | S94: 17685722000120 | T94: SEISS & DEISS = DEISS CONFECCOES EIRELI
A95: 10/2025 | B95: 44015 | C95: VESTI | D95: Buccanes | E95: Vesti (Assinatura) | F95: Essencial | H95: 283 | J95: 283 | O95: =SUM(J95:M95)-N95 -> 283 | Q95: 15 | R95: 04 | S95: 55251292000127 | T95: BUCCANES = JURRO INDUSTRIA E COMERCIO DE CONFECCOES LTDA
A96: 10/2025 | B96: 44017 | C96: Atta | D96: Hirus | E96: Vesti (Assinatura) | F96: Avançado | H96: 509 | J96: 509 | O96: =SUM(J96:M96)-N96 -> 509 | Q96: 15 | R96: 04 | S96: 07752324000206 | T96: HIRUS = CONFECCOES BONDADE LTDA
A97: 10/2025 | B97: 44020 | C97: Atta | D97: Rubicon | E97: Vesti (Assinatura) | F97: Avançado | H97: 425 | J97: 425 | O97: =SUM(J97:M97)-N97 -> 425 | Q97: 15 | R97: 04 | S97: 24002700000183 | T97: RUBICON = RUBICON MODAS LTDA
A98: 10/2025 | B98: 44021 | C98: VESTI | D98: Lorsa | E98: Vesti (Assinatura) | F98: Avançado | H98: 425 | J98: 425 | L98: =2520+150 -> 2670 | O98: =SUM(J98:M98)-N98 -> 3095 | Q98: 22 | R98: 04 | S98: 46046876000170 | T98: LORSA = L ORSA MODAS E CONFECCOES LTDA
A99: 10/2025 | B99: 44025 | C99: VESTI | D99: Equivoco | E99: Vesti (Assinatura) | F99: Avançado | H99: 425 | J99: 425 | O99: =SUM(J99:M99)-N99 -> 425 | Q99: 22 | R99: 04 | S99: 46046876000927 | T99: Equivoco Jeans = L ORSA MODAS E CONFECCOES LTDA
A100: 10/2025 | B100: 44027 | C100: Atta | D100: Acqua Marine | E100: Vesti (Assinatura) | F100: Avançado | H100: 509 | J100: 509 | O100: =SUM(J100:M100)-N100 -> 509 | Q100: 20 | R100: 04 | S100: 56353866000130 | T100: ACQUA MARINE = SJLEE CONFECCOES ME
...

Sheet Vesti 1225
A1: Fat.2025 | B1: ANIVERSÁRIO | C1: CANAL | D1: MARCA | E1: Subconta | F1: PLANO | G1: SETUP | H1: MENSALIDADE INICIAL | I1: VALOR REAJUSTE | J1: MENSALIDADE | K1: INTEGRAÇÃO | L1: ASSISTENTE | M1: FILIAL | N1: DESCONTOS | O1: TOTAL COBRADO | P1: OBSERVAÇÕES | Q1: Dia Vencimento | R1: Mês de Reajuste | S1: CPFCNPJ | T1: NOME/RAZÃO SOCIAL
A2: 12/2025 | B2: 42795 | C2: VESTI | D2: TNW Jeans | E2: Vesti (Assinatura) | F2: Profissional | H2: 1156 | J2: 1156 | O2: =SUM(J2:M2)-N2 -> 1156 | Q2: 17 | R2: 04 | S2: 4937453000108 | T2: TNW JEANS = TNW CONFECCOES LTDA
A3: 12/2025 | B3: 42937 | C3: Atta | D3: Peonia | E3: Atta | F3: Essencial | H3: 302 | J3: 302 | O3: =SUM(J3:M3)-N3 -> 302 | Q3: 20 | R3: 4 | S3: 07993188000165
A4: 12/2025 | B4: 43160 | C4: Atta | D4: Maria De Chita | E4: Vesti (Assinatura) | F4: Profissional | H4: 724 | J4: 724 | O4: =SUM(J4:M4)-N4 -> 724 | Q4: 15 | R4: 04 | S4: 07402979000173 | T4: MARIA DE CHITA = MARIA DE CHITA CONFECCOES LTDA
A5: 12/2025 | B5: 43160 | C5: Atta | D5: Shanes | E5: Vesti (Assinatura) | F5: Profissional | H5: 1179 | J5: 1179 | O5: =SUM(J5:M5)-N5 -> 1179 | Q5: 20 | R5: 04 | S5: 46446130000153 | T5: SHANES = CONFECCOES SHANES LTDA
A6: 12/2025 | B6: 43160 | C6: Atta | D6: Talgui | E6: Vesti (Assinatura) | F6: Avançado | H6: 441.33 | J6: 441.33 | O6: =SUM(J6:M6)-N6 -> 441.33 | Q6: 15 | R6: 04 | S6: 05876663000198 | T6: TALGUI = TALGUI CONFECCOES DE ROUPAS LTDA
A7: 12/2025 | B7: 43160 | C7: Atta | D7: Coinage | E7: Vesti (Assinatura) | F7: Profissional | H7: 1179 | J7: 1179 | O7: =SUM(J7:M7)-N7 -> 1179 | Q7: 20 | R7: 04 | S7: 33724927000123 | T7: Coinage = DON IN CONFECCOES LTDA
A8: 12/2025 | B8: 43160 | C8: Atta | D8: Moda Inn | E8: Vesti (Assinatura) | F8: Essencial | H8: 283 | J8: 283 | O8: =SUM(J8:M8)-N8 -> 283 | Q8: 20 | R8: 04 | S8: 49921554000110 | T8: MODA INN = CONFECCOES SIMON LTDA
A9: 12/2025 | B9: 43160 | C9: Atta | D9: Licommo | E9: Vesti (Assinatura) | F9: Avançado | H9: 425 | J9: 425 | O9: =SUM(J9:M9)-N9 -> 425 | Q9: 15 | R9: 04 | S9: 08325746000187 | T9: LICOMMO = CONFECCOES LICOMMO LTDA
A10: 12/2025 | B10: 43160 | C10: Atta | D10: Betsey | E10: Vesti (Assinatura) | F10: Profissional | H10: 1003 | J10: 1003 | O10: =SUM(J10:M10)-N10 -> 1003 | Q10: 15 | R10: 04 | S10: 06161024000109 | T10: BETSEY = BETSEY CONFECCOES LTDA
A11: 12/2025 | B11: 43160 | C11: Atta | D11: Cashier | E11: Vesti (Assinatura) | F11: Profissional | H11: 1015 | J11: 1015 | O11: =SUM(J11:M11)-N11 -> 1015 | Q11: 30 | R11: 04 | S11: 60368669000162 | T11: CASHIER = CASHIER CONFECCOES LTDA
A12: 12/2025 | B12: 43160 | C12: Atta | D12: Cony Green | E12: Vesti (Assinatura) | F12: Avançado | H12: 425 | J12: 425 | O12: =SUM(J12:M12)-N12 -> 425 | Q12: 15 | R12: 04 | S12: 44511277000154 | T12: CONY GREEN = CONFECCOES E MODAS CONY GREEN LTDA
A13: 12/2025 | B13: 43160 | C13: Atta | D13: Pury | E13: Vesti (Assinatura) | F13: Profissional | H13: 1327 | J13: 1327 | M13: 359 | O13: =SUM(J13:M13)-N13 -> 1686 | Q13: 15 | R13: 04 | S13: 12576594000162 | T13: PURY = CONFECCOES PURY LTDA
A14: 12/2025 | B14: 43160 | C14: VESTI | D14: Tricomix | E14: Vesti (Assinatura) | F14: Avançado | H14: 1193 | J14: 1193 | K14: 350 | O14: =SUM(J14:M14)-N14 -> 1543 | Q14: 11 | R14: 04 | S14: 04665515000161 | T14: TRICOMIX = TRICOMIX INDUSTRIA E COMERCIO DE CONFECCOES EIRELI
A15: 12/2025 | B15: 43160 | C15: Atta | D15: Lov It | E15: Vesti (Assinatura) | F15: Avançado | H15: 425 | J15: 425 | O15: =SUM(J15:M15)-N15 -> 425 | Q15: 11 | R15: 04 | S15: 21749422000215 | T15: LOV IT = WELOVIT CONFECCOES LTDA
A16: 12/2025 | B16: 43160 | C16: Atta | D16: Hemix | E16: Vesti (Assinatura) | F16: Essencial | H16: 283 | J16: 283 | L16: =550+120 -> 670 | O16: =SUM(J16:M16)-N16 -> 953 | Q16: 15 | R16: 04 | S16: 07389520000187 | T16: HEMIX = HEMIX CONFECCOES LTDA
A17: 12/2025 | B17: 43160 | C17: Miredata | D17: Mottive | E17: Vesti (Assinatura) | F17: Profissional | H17: 1179 | J17: 1179 | O17: =SUM(J17:M17)-N17 -> 1179 | Q17: 20 | R17: 04 | S17: 24330475000104 | T17: MOTTIVE = PROBELLAS CONFECCOES LTDA EPP
A18: 12/2025 | B18: 43160 | C18: Atta | D18: Miss Alfa | E18: Vesti (Assinatura) | F18: Essencial | H18: 283 | J18: 283 | O18: =SUM(J18:M18)-N18 -> 283 | Q18: 15 | R18: 04 | S18: 28497561000167 | T18: MISS ALFA = MISS ALFA COMERCIO DE ROUPAS LTDA
A19: 12/2025 | B19: 43160 | C19: VESTI | D19: Anemone | E19: Vesti (Assinatura) | F19: Avançado | H19: 1013 | J19: 1013 | O19: =SUM(J19:M19)-N19 -> 1013 | Q19: 11 | R19: 04 | S19: 30962814000178 | T19: ANEMONE = MM21 INDUSTRIA E COMERCIO DE ROUPAS LTDA
A20: 12/2025 | B20: 43160 | C20: Miredata | D20: Pianeta | E20: Vesti (Assinatura) | F20: Profissional | H20: 761 | J20: 761 | O20: =SUM(J20:M20)-N20 -> 761 | Q20: 20 | R20: 04 | S20: 31583000000195 | T20: PIANETA = INTERMIX CONFECCOES DE ROUPAS LTDA
A21: 12/2025 | B21: 43356 | C21: Atta | D21: Morina | E21: Vesti (Assinatura) | F21: Profissional | H21: 1138 | J21: 1138 | O21: =SUM(J21:M21)-N21 -> 1138 | Q21: 15 | R21: 04 | S21: 44029041000186 | T21: Morina = FYK CONFECCOES LTDA
A22: 12/2025 | B22: 43586 | C22: Atta | D22: Artemiss | E22: Vesti (Assinatura) | F22: Avançado | H22: 569 | J22: 569 | M22: 275 | O22: =SUM(J22:M22)-N22 -> 844 | Q22: 11 | R22: 04 | S22: 05320347000135 | T22: ARTEMISS = CONFECCOES ARTE E MISS LTDA
A23: 12/2025 | B23: 43586 | C23: Atta | D23: IT LOOK | E23: Vesti (Assinatura) | F23: Essencial | H23: 283 | J23: 283 | O23: =SUM(J23:M23)-N23 -> 283 | Q23: 15 | R23: 04 | S23: 21659326000103 | T23: IT LOOK = IT LOOK CONFECCAO E COMERCIO DE ROUPAS LTDA
A24: 12/2025 | B24: 43586 | C24: Atta | D24: E YUNIRE | E24: Vesti (Assinatura) | F24: Essencial | H24: 354 | J24: 354 | O24: =SUM(J24:M24)-N24 -> 354 | Q24: 15 | R24: 04 | S24: 45375658000116 | T24: E YUNIRE = YUNIVEST CONFECCOES LTDA
A25: 12/2025 | B25: 43593 | C25: Atta | D25: Incentive | E25: Vesti (Assinatura) | F25: Essencial | H25: 528.33 | J25: 528.33 | O25: =SUM(J25:M25)-N25 -> 528.33 | Q25: 30 | R25: 04 | S25: 29780242000127 | T25: INCENTIVE = CONFECCOES INCENTIVE LTDA
A26: 12/2025 | B26: 43593 | C26: Atta | D26: Mariá/Aurora | E26: Vesti (Assinatura) | F26: Essencial | H26: 283 | J26: 283 | O26: =SUM(J26:M26)-N26 -> 283 | Q26: 20 | R26: 04 | S26: 33076814000169 | T26: Maria/Aurora = OK MI DO
A27: 12/2025 | B27: 43593 | C27: Atta | D27: Mazarin | E27: Vesti (Assinatura) | F27: Essencial | H27: 326.67 | J27: 326.67 | O27: =SUM(J27:M27)-N27 -> 326.67 | Q27: 15 | R27: 04 | S27: 03598605000203 | T27: MAZARIN = CONFECCOES MAZARIN LTDA
A28: 12/2025 | B28: 43600 | C28: Atta | D28: Blue Blossom | E28: Vesti (Assinatura) | F28: Essencial | H28: 283 | J28: 283 | M28: 410 | O28: =SUM(J28:M28)-N28 -> 693 | Q28: 15 | R28: 04 | S28: 30828978000107 | T28: BLUE BLOSSOM = BLUE BLOSSOM CONFECCOES EIRELI
A29: 12/2025 | B29: 43606 | C29: VESTI | D29: Crocker | E29: Vesti (Assinatura) | F29: Profissional | H29: 1179 | J29: 1179 | M29: 410 | O29: =SUM(J29:M29)-N29 -> 1589 | Q29: 15 | R29: 04 | S29: 60652948000153 | T29: CROCKER = US BRASIL INDUSTRIA E COMERCIO DE ROUPAS LTDA
A30: 12/2025 | B30: 43606 | C30: VESTI | D30: Lesto | E30: Vesti (Assinatura) | F30: Essencial | H30: 284.33 | J30: 284.33 | O30: =SUM(J30:M30)-N30 -> 284.33 | Q30: 15 | R30: 04 | S30: 58418377000145 | T30: LESTO = LESTO CONFECCOES LTDA
A31: 12/2025 | B31: 43619 | C31: Atta | D31: Ellen One | E31: Vesti (Cartão) | F31: Essencial | H31: 283 | J31: 283 | O31: =SUM(J31:M31)-N31 -> 283 | Q31: 06 | R31: 4 | S31: 07554437000116 | T31: Ellen One = CONFECCOES ELLEN ONE EIRELI
A32: 12/2025 | B32: 43619 | C32: Atta | D32: Instar | E32: Vesti (Assinatura) | F32: Essencial | H32: 283 | J32: 283 | O32: =SUM(J32:M32)-N32 -> 283 | Q32: 15 | R32: 04 | S32: 32649954000116 | T32: INSTAR = CLASSY MISSY CONFECCAO DE ROUPAS LTDA
A33: 12/2025 | B33: 43633 | C33: Atta | D33: Aramodu | E33: Vesti (Assinatura) | F33: Essencial | H33: 283 | J33: 283 | O33: =SUM(J33:M33)-N33 -> 283 | Q33: 11 | R33: 04 | S33: 97541061000106 | T33: ARAMODU = CONFECCOES ARAMODU EIRELI
A34: 12/2025 | B34: 43643 | C34: Atta | D34: Scera | E34: Vesti (Assinatura) | F34: Essencial | H34: 283 | J34: 283 | O34: =SUM(J34:M34)-N34 -> 283 | Q34: 15 | R34: 04 | S34: 23333642000108 | T34: SCERA = SCERA MODA FEMININA LTDA
A35: 12/2025 | B35: 43649 | C35: Atta | D35: Fama Fashion | E35: Vesti (Assinatura) | F35: Essencial | H35: 283 | J35: 283 | O35: =SUM(J35:M35)-N35 -> 283 | Q35: 20 | R35: 04 | S35: 54451398000101 | T35: FAMA FASHION = FAMA FASHION CREACOES LTDA
A36: 12/2025 | B36: 43649 | C36: VESTI | D36: Paloma Concept | E36: Vesti (Assinatura) | F36: Essencial | H36: 283 | J36: 283 | O36: =SUM(J36:M36)-N36 -> 283 | Q36: 15 | R36: 04 | S36: 16579598000155 | T36: PALOMA CONCEPT = FABIO DE ARAUJO LIMA FERREIRA EIRELI
A37: 12/2025 | B37: 43656 | C37: Atta | D37: Cheers | E37: Vesti (Assinatura) | F37: Profissional | H37: 1179 | J37: 1179 | O37: =SUM(J37:M37)-N37 -> 1179 | Q37: 11 | R37: 04 | S37: 53659785000175 | T37: CHEERS = MODAS VISION LTDA
A38: 12/2025 | B38: 43656 | C38: Atta | D38: Fesperamor | E38: Vesti (Assinatura) | F38: Profissional | H38: 1179 | J38: 1179 | O38: =SUM(J38:M38)-N38 -> 1179 | Q38: 15 | R38: 04 | S38: 22015485000120 | T38: FESPERAMOR = JEH CONFECCOES LTDA
A39: 12/2025 | B39: 43675 | C39: Atta | D39: Quebela | E39: Vesti (Assinatura) | F39: Essencial | H39: 425 | J39: 425 | M39: 369 | O39: =SUM(J39:M39)-N39 -> 794 | Q39: 20 | R39: 04 | S39: 58525007000107 | T39: QUEBELA = CONFECCOES QUEBELA LTDA
A40: 12/2025 | B40: 43684 | C40: Atta | D40: Genesis Jeans | E40: Vesti (Assinatura) | F40: Essencial | H40: 283 | J40: 283 | O40: =SUM(J40:M40)-N40 -> 283 | Q40: 15 | R40: 04 | S40: 21352130000163 | T40: GENESIS JEANS = GENESIS JEANS LTDA
A41: 12/2025 | B41: 43713 | C41: Vesti | D41: AMISKA - MISS MILLIE | E41: Vesti (Assinatura) | F41: Essencial | H41: 303 | J41: 303 | O41: =SUM(J41:M41)-N41 -> 303 | Q41: 15 | R41: 04 | S41: 24721940000138 | T41: AMISKA MISS MILLIE = CONFECCOES MISS MILLIE INDUSTRIA E COMERCIO DE ROUPAS LTDA EPP
A42: 12/2025 | B42: 43718 | C42: VESTI | D42: Join Curves | E42: Vesti (Assinatura) | F42: Avançado | H42: 486 | J42: 486 | L42: 1000 | M42: 600 | O42: =SUM(J42:M42)-N42 -> 2086 | Q42: 28 | R42: 04 | S42: 07867580000168 | T42: Join Curves = JULIA A H INDUSTRIA E COMERCIO DE ROUPAS LTDA
A43: 12/2025 | B43: 43719 | C43: Atta | D43: Namine | E43: Vesti (Assinatura) | F43: Profissional | H43: 1005 | J43: 1005 | M43: =266+900 -> 1166 | O43: =SUM(J43:M43)-N43 -> 2171 | Q43: 15 | R43: 04 | S43: 17820490000256 | T43: NAMINE = NAMINE CONFECCOES LTDA
A44: 12/2025 | B44: 43731 | C44: VESTI | D44: Diamantes | E44: Vesti (Assinatura) | F44: Profissional | H44: 1400 | J44: 1400 | M44: =38*161.95+5 -> 6159.1 | O44: =SUM(J44:M44)-N44 -> 7559.1 | Q44: 15 | R44: 04 | S44: 13649755000163 | T44: DIAMANTES = DIAMANTES LINGERIE LTDA
A45: 12/2025 | B45: 43738 | C45: Atta | D45: Lily Daisy | E45: Vesti (Assinatura) | F45: Essencial | H45: 283 | J45: 283 | O45: =SUM(J45:M45)-N45 -> 283 | Q45: 15 | R45: 04 | S45: 34500000000172 | T45: LILY DAISY = ATELIER LILY DAISY CONFECCOES LTDA
A46: 12/2025 | B46: 43745 | C46: VESTI | D46: Ana Gonçalves Tricot = Luis Guilherme | E46: Vesti (Assinatura) | F46: Profissional | H46: 1179 | J46: 1179 | M46: 598 | O46: =SUM(J46:M46)-N46 -> 1777 | Q46: 15 | R46: 04 | S46: 11582787000163 | T46: Ana Goncalves Tricot = LUIS GUILHERME GONCALVES LEMES EIRELI
A47: 12/2025 | B47: 43755 | C47: Atta | D47: Delight | E47: Vesti (Assinatura) | F47: Essencial | H47: 283 | J47: 283 | O47: =SUM(J47:M47)-N47 -> 283 | Q47: 15 | R47: 04 | S47: 21520947000101 | T47: DELIGHT = DELIGHT MODA FEMININA LTDA
A48: 12/2025 | B48: 43755 | C48: Atta | D48: Sori | E48: Vesti (Assinatura) | F48: Profissional | H48: 1179 | J48: 1179 | O48: =SUM(J48:M48)-N48 -> 1179 | Q48: 15 | R48: 04 | S48: 06987979000110 | T48: SORI = C. S. CHOI MODAS
A49: 12/2025 | B49: 43768 | C49: Atta | D49: Mx | E49: Vesti (Assinatura) | F49: Profissional | H49: 1179 | J49: 1179 | O49: =SUM(J49:M49)-N49 -> 1179 | Q49: 20 | R49: 04 | S49: 05888414000112 | T49: MX = CREACOES MX FASHION LTDA
A50: 12/2025 | B50: 43774 | C50: Atta | D50: Donna Ritz | E50: Vesti (Assinatura) | F50: Profissional | H50: 1076.67 | J50: 1076.67 | O50: =SUM(J50:M50)-N50 -> 1076.67 | Q50: 15 | R50: 04 | S50: 19521267000152 | T50: DONNA RITZ = RITZ FASHION CONFECCOES EIRELI EPP
A51: 12/2025 | B51: 43802 | C51: VESTI | D51: Vida Bela | E51: Vesti (Assinatura) | F51: Essencial | H51: 283 | J51: 283 | O51: =SUM(J51:M51)-N51 -> 283 | Q51: 15 | R51: 04 | S51: 45668696000167 | T51: VIDA BELA = SAMIR ABRAO BASSITT E CIA LTDA
A52: 12/2025 | B52: 43846 | C52: Atta | D52: Sedanbi | E52: Vesti (Assinatura) | F52: Essencial | H52: 283 | J52: 283 | O52: =SUM(J52:M52)-N52 -> 283 | Q52: 15 | R52: 04 | S52: 00238342000306 | T52: SEDANBI = COMERCIO E CONFECCOES DE ROUPAS S H EIRELI
A53: 12/2025 | B53: 43861 | C53: VESTI | D53: Rafa Brasil | E53: Vesti (Assinatura) | F53: Essencial | H53: 283 | J53: 283 | O53: =SUM(J53:M53)-N53 -> 283 | Q53: 15 | R53: 04 | S53: 30827010000166 | T53: RAFA BRASIL = EDUARDO FERREIRA MARQUES 06879922651
A54: 12/2025 | B54: 43867 | C54: Atta | D54: Elae | E54: Vesti (Assinatura) | F54: Avançado | H54: 425 | J54: 425 | O54: =SUM(J54:M54)-N54 -> 425 | Q54: 20 | R54: 04 | S54: 46924221000157 | T54: ELAE = CONFECCOES GERACAO ELAE LTDA
A55: 12/2025 | B55: 43878 | C55: Atta | D55: As Marias | E55: Vesti (Assinatura) | F55: Essencial | H55: 283 | J55: 283 | O55: =SUM(J55:M55)-N55 -> 283 | Q55: 15 | R55: 04 | S55: 24487541000154 | T55: As Marias = ELSA MARIA DA SILVA SOUZA
A56: 12/2025 | B56: 43888 | C56: VESTI | D56: Suzan Zheng | E56: Vesti (Assinatura) | F56: Essencial | H56: 283 | J56: 283 | O56: =SUM(J56:M56)-N56 -> 283 | Q56: 15 | R56: 04 | S56: 26551251000158 | T56: SUZAN ZHENG = Z COMERCIO DE ROUPAS EIRELI
A57: 12/2025 | B57: 43892 | C57: VESTI | D57: Gliss Jeans | E57: Vesti (Assinatura) | F57: Essencial | H57: 283 | J57: 283 | M57: 199 | O57: =SUM(J57:M57)-N57 -> 482 | Q57: 11 | R57: 04 | S57: 55251292001107 | T57: GLISS JEANS = JURRO INDUSTRIA E COMERCIO DE CONFECCOES LTDA
A58: 12/2025 | B58: 43903 | C58: VESTI | D58: Bauarte | E58: Vesti (Assinatura) | F58: Avançado | H58: 1231 | J58: 1231 | K58: 350 | O58: =SUM(J58:M58)-N58 -> 1581 | Q58: 20 | R58: 04 | S58: 08754784000155 | T58: BAUARTE = JP MONTEIRO ACESSORIOS DA MODA LTDA
A59: 12/2025 | B59: 43920 | C59: Atta | D59: Alcance Jeans | E59: Vesti (Assinatura) | F59: Profissional | H59: 1243.35 | J59: 1243.35 | M59: 250 | O59: =SUM(J59:M59)-N59 -> 1493.35 | Q59: 11 | R59: 04 | S59: 34411241000145 | T59: ALCANCE JEANS = ALC INDUSTRIA E COMERCIO DE ROUPAS LTDA
A60: 12/2025 | B60: 43943 | C60: VESTI | D60: Sanreed | E60: Vesti (Assinatura) | F60: Essencial | H60: 283 | J60: 283 | M60: 359 | O60: =SUM(J60:M60)-N60 -> 642 | Q60: 15 | R60: 04 | S60: 23735214000292 | T60: Sanreed = WIBE CONFECCOES EIRELI
A61: 12/2025 | B61: 43949 | C61: VESTI | D61: Vigor Basic | E61: Vesti (Assinatura) | F61: Essencial | H61: 283 | J61: 283 | O61: =SUM(J61:M61)-N61 -> 283 | Q61: 11 | R61: 04 | S61: 07085032000186 | T61: Vigor Basic = VIGOR TOTAL INDUSTRIA E COMERCIO DO VESTUARIO LTDA
A62: 12/2025 | B62: 43950 | C62: VESTI | D62: Manaca= Visuh | E62: Vesti (Assinatura) | F62: Profissional | H62: 1179 | J62: 1179 | O62: =SUM(J62:M62)-N62 -> 1179 | Q62: 20 | R62: 04 | S62: 22221114000102 | T62: MANACA = VISUH CONFECCOES LTDA EPP
A63: 12/2025 | B63: 43955 | C63: Atta | D63: Bokeh | E63: Vesti (Assinatura) | F63: Avançado | H63: 425 | J63: 425 | O63: =SUM(J63:M63)-N63 -> 425 | Q63: 20 | R63: 04 | S63: 28489878000232 | T63: BOKEH = CONFECCOES CHESED LTDA EPP
A64: 12/2025 | B64: 43958 | C64: Atta | D64: Hanabee | E64: Vesti (Assinatura) | F64: Avançado | H64: 425 | J64: 425 | O64: =SUM(J64:M64)-N64 -> 425 | Q64: 20 | R64: 04 | S64: 12395643000160 | T64: HANABEE = ESLEE CONFECCOES LTDA EPP
A65: 12/2025 | B65: 43958 | C65: Atta | D65: Innocence | E65: Vesti (Assinatura) | F65: Avançado | H65: 835 | J65: 835 | K65: 250 | O65: =SUM(J65:M65)-N65 -> 1085 | Q65: 15 | R65: 04 | S65: 17258262000153 | T65: INNOCENCE = SUN JOO KIM CONFECCOES
A66: 12/2025 | B66: 43962 | C66: VESTI | D66: Cris Fael | E66: Vesti (Assinatura) | F66: Avançado | H66: 425 | J66: 425 | O66: =SUM(J66:M66)-N66 -> 425 | Q66: 15 | R66: 04 | S66: 52341858000113 | T66: CRIS FAEL = CRISFAEL COMERCIO DE ACESSORIOS DA MODA LTDA
A67: 12/2025 | B67: 43965 | C67: Atta | D67: Caroll | E67: Vesti (Assinatura) | F67: Avançado | H67: 665 | J67: 665 | O67: =SUM(J67:M67)-N67 -> 665 | Q67: 11 | R67: 04 | S67: 02683338000110 | T67: CAROLL COLLECTION = CAROLL CONFECCOES IMPORTACAO E EXPORTACAO LTDA
A68: 12/2025 | B68: 43965 | C68: Atta | D68: Kalli | E68: Vesti (Assinatura) | F68: Avançado | H68: 698 | J68: 698 | O68: =SUM(J68:M68)-N68 -> 698 | Q68: 11 | R68: 04 | S68: 17685726000108 | T68: Kalli = CONFECCOES KALLI LTDA
A69: 12/2025 | B69: 43965 | C69: Atta | D69: Sexy Cookie | E69: Vesti (Assinatura) | F69: Profissional | H69: 1179 | J69: 1179 | O69: =SUM(J69:M69)-N69 -> 1179 | Q69: 11 | R69: 04 | S69: 08151457000109 | T69: Sexy Cookie = SEXY COOKIE CONFECCOES LTDA
A70: 12/2025 | B70: 43966 | C70: VESTI | D70: Adizza | E70: Vesti (Assinatura) | F70: Essencial | H70: 283 | J70: 283 | M70: 410 | O70: =SUM(J70:M70)-N70 -> 693 | Q70: 15 | R70: 04 | S70: 24881140000184 | T70: ADIZZA = PAULO CESAR VALERIANO SILVA
A71: 12/2025 | B71: 43966 | C71: VESTI | D71: Anahi | E71: Vesti (Assinatura) | F71: Avançado | H71: 425 | J71: 425 | O71: =SUM(J71:M71)-N71 -> 425 | Q71: 20 | R71: 04 | S71: 04049767000166 | T71: Anahi = ALTA MUN BIANCA CONFECCOES LTDA EPP
A72: 12/2025 | B72: 43972 | C72: Atta | D72: Ezee | E72: Vesti (Assinatura) | F72: Essencial | H72: 342.67 | J72: 342.67 | O72: =SUM(J72:M72)-N72 -> 342.67 | Q72: 15 | R72: 04 | S72: 28314192000120 | T72: EZEE = EZEE CONFECCOES DE ROUPAS EIRELI
A73: 12/2025 | B73: 43978 | C73: Atta | D73: Nakepe | E73: Vesti (Assinatura) | F73: Avançado | H73: 425 | J73: 425 | O73: =SUM(J73:M73)-N73 -> 425 | Q73: 22 | R73: 04 | S73: 00764187000108 | T73: NAKEPE = NAKEPE CREACOES LTDA
A74: 12/2025 | B74: 43978 | C74: Atta | D74: Ste Fashion | E74: Vesti (Assinatura) | F74: Avançado | H74: 425 | J74: 425 | O74: =SUM(J74:M74)-N74 -> 425 | Q74: 15 | R74: 04 | S74: 12648298000120 | T74: STE FASHION = CHOCO'S ARTIGOS DO VESTUARIO EIRELI
A75: 12/2025 | B75: 43979 | C75: Atta | D75: Lilian Plus | E75: Vesti (Assinatura) | F75: Avançado | H75: 425 | J75: 425 | O75: =SUM(J75:M75)-N75 -> 425 | Q75: 15 | R75: 04 | S75: 51200947000187 | T75: Lilian Plus = CONFECCOES LILIAN LTDA
A76: 12/2025 | B76: 43983 | C76: VESTI | D76: Blubetty | E76: Vesti (Assinatura) | F76: Profissional | H76: 1330 | J76: 1330 | K76: 350 | O76: =SUM(J76:M76)-N76 -> 1680 | Q76: 15 | R76: 04 | S76: 01102343000120 | T76: Blubetty = KAPITON CONFECCOES LTDA
A77: 12/2025 | B77: 43983 | C77: VESTI | D77: Di Collani | E77: Vesti (Assinatura) | F77: Profissional | H77: 2110.33 | J77: 2110.33 | K77: 500 | O77: =SUM(J77:M77)-N77 -> 2610.33 | Q77: 11 | R77: 04 | S77: 01102343000120 | T77: Di Collani = KAPITON CONFECCOES LTDA
A78: 12/2025 | B78: 43983 | C78: VESTI | D78: Jeanseria | E78: Vesti (Assinatura) | F78: Profissional | H78: 405 | J78: 405 | K78: 350 | O78: =SUM(J78:M78)-N78 -> 755 | Q78: 11 | R78: 04 | S78: 01102343000120 | T78: Jeanseria = KAPITON CONFECCOES LTDA
A79: 12/2025 | B79: 43984 | C79: Atta | D79: Coqueta | E79: Vesti (Assinatura) | F79: Avançado | H79: 472.33 | J79: 472.33 | M79: 380 | O79: =SUM(J79:M79)-N79 -> 852.33 | Q79: 11 | R79: 04 | S79: 58687526000171 | T79: Coqueta = CONFECCOES COQUETA LTDA
A80: 12/2025 | B80: 43986 | C80: Atta | D80: Clio | E80: Vesti (Assinatura) | F80: Avançado | H80: 425 | J80: 425 | O80: =SUM(J80:M80)-N80 -> 425 | Q80: 15 | R80: 04 | S80: 05550677000117 | T80: Clio = CLIO CONFECCOES IMPORTACAO E EXPORTACAO LTDA
A81: 12/2025 | B81: 43986 | C81: Atta | D81: Planchet | E81: Vesti (Assinatura) | F81: Avançado | H81: 425 | J81: 425 | O81: =SUM(J81:M81)-N81 -> 425 | Q81: 15 | R81: 04 | S81: 03243396000196 | T81: Planchet = CONFECCOES PLANCHET EIRELI
A82: 12/2025 | B82: 43990 | C82: Atta | D82: Bestié | E82: Vesti (Assinatura) | F82: Avançado | H82: 425 | J82: 425 | O82: =SUM(J82:M82)-N82 -> 425 | Q82: 12 | R82: 04 | S82: 50751845000197 | T82: Bestie = CONFECCOES BESTIE LTDA
A83: 12/2025 | B83: 43992 | C83: VESTI | D83: Monclos | E83: Vesti (Assinatura) | F83: Avançado | H83: 426.33 | J83: 426.33 | O83: =SUM(J83:M83)-N83 -> 426.33 | Q83: 11 | R83: 04 | S83: 59812453000246 | T83: Monclos = CAN FLOW CONFECCOES LTDA
A84: 12/2025 | B84: 43994 | C84: Atta | D84: Moirai | E84: Vesti (Assinatura) | F84: Avançado | H84: 452.67 | J84: 452.67 | O84: =SUM(J84:M84)-N84 -> 452.67 | Q84: 15 | R84: 04 | S84: 29380107000194 | T84: MOIRAI = MOIRAI CONFECCAO DE ROUPAS EIRELI
A85: 12/2025 | B85: 44000 | C85: Atta | D85: Noir | E85: Vesti (Assinatura) | F85: Avançado | H85: 425 | J85: 425 | O85: =SUM(J85:M85)-N85 -> 425 | Q85: 15 | R85: 04 | S85: 02415964000126 | T85: Noir = CONFECCOES NOIR LTDA
A86: 12/2025 | B86: 44006 | C86: Atta | D86: French Kiss | E86: Vesti (Assinatura) | F86: Avançado | H86: 457 | J86: 457 | O86: =SUM(J86:M86)-N86 -> 457 | Q86: 15 | R86: 04 | S86: 65977878000127 | T86: French Kiss = GUARNIERIUS MODAS LTDA
A87: 12/2025 | B87: 44006 | C87: VESTI | D87: Wool Line | E87: Vesti (Assinatura) | F87: Avançado | H87: 425 | J87: 425 | O87: =SUM(J87:M87)-N87 -> 425 | Q87: 11 | R87: 04 | S87: 23398902000123 | T87: Wool Line = WOOL LINE CONFECCOES EIRELI
A88: 12/2025 | B88: 44007 | C88: VESTI | D88: Amofany | E88: Vesti (Assinatura) | F88: Profissional | H88: 1179 | J88: 1179 | K88: 350 | O88: =SUM(J88:M88)-N88 -> 1529 | Q88: 15 | R88: 04 | S88: 09657596000171 | T88: AMOFANY = Mabli confeccoes de roupas LTDA EPP
A89: 12/2025 | B89: 44008 | C89: VESTI | D89: Four One | E89: Vesti (Assinatura) | F89: Avançado | H89: 425 | J89: 425 | M89: 359 | O89: =SUM(J89:M89)-N89 -> 784 | Q89: 15 | R89: 04 | S89: 55646228000145 | T89: Four One Jeans = FOUR ONE INDUSTRIA E COMERCIO EIRELI
A90: 12/2025 | B90: 44008 | C90: VESTI | D90: Peri Plus Size | E90: Vesti (Assinatura) | F90: Avançado | H90: 425 | J90: 425 | O90: =SUM(J90:M90)-N90 -> 425 | Q90: 15 | R90: 04 | S90: 41090419000169 | T90: Peri Plus Size = MODAS PERI LTDA
A91: 12/2025 | B91: 44013 | C91: Atta | D91: Vitral | E91: Vesti (Assinatura) | F91: Profissional | H91: 1179 | J91: 1179 | O91: =SUM(J91:M91)-N91 -> 1179 | Q91: 20 | R91: 04 | S91: 13578271000170 | T91: VITRAL = J Y KIM CONFECCOES LTDA
A92: 12/2025 | B92: 44014 | C92: Atta | D92: Seiss & Deiss | E92: Vesti (Assinatura) | F92: Essencial | H92: 364.67 | J92: 364.67 | O92: =SUM(J92:M92)-N92 -> 364.67 | Q92: 15 | R92: 04 | S92: 17685722000120 | T92: SEISS & DEISS = DEISS CONFECCOES EIRELI
A93: 12/2025 | B93: 44015 | C93: VESTI | D93: Buccanes | E93: Vesti (Assinatura) | F93: Essencial | H93: 283 | J93: 283 | O93: =SUM(J93:M93)-N93 -> 283 | Q93: 15 | R93: 04 | S93: 55251292000127 | T93: BUCCANES = JURRO INDUSTRIA E COMERCIO DE CONFECCOES LTDA
A94: 12/2025 | B94: 44017 | C94: Atta | D94: Hirus | E94: Vesti (Assinatura) | F94: Avançado | H94: 509 | J94: 509 | O94: =SUM(J94:M94)-N94 -> 509 | Q94: 15 | R94: 04 | S94: 07752324000206 | T94: HIRUS = CONFECCOES BONDADE LTDA
A95: 12/2025 | B95: 44020 | C95: Atta | D95: Rubicon | E95: Vesti (Assinatura) | F95: Avançado | H95: 425 | J95: 425 | O95: =SUM(J95:M95)-N95 -> 425 | Q95: 15 | R95: 04 | S95: 24002700000183 | T95: RUBICON = RUBICON MODAS LTDA
A96: 12/2025 | B96: 44021 | C96: VESTI | D96: Lorsa | E96: Vesti (Assinatura) | F96: Avançado | H96: 425 | J96: 425 | L96: =2520+150 -> 2670 | O96: =SUM(J96:M96)-N96 -> 3095 | Q96: 22 | R96: 04 | S96: 46046876000170 | T96: LORSA = L ORSA MODAS E CONFECCOES LTDA
A97: 12/2025 | B97: 44025 | C97: VESTI | D97: Equivoco | E97: Vesti (Assinatura) | F97: Avançado | H97: 425 | J97: 425 | O97: =SUM(J97:M97)-N97 -> 425 | Q97: 22 | R97: 04 | S97: 46046876000927 | T97: Equivoco Jeans = L ORSA MODAS E CONFECCOES LTDA
A98: 12/2025 | B98: 44027 | C98: Atta | D98: Acqua Marine | E98: Vesti (Assinatura) | F98: Avançado | H98: 509 | J98: 509 | O98: =SUM(J98:M98)-N98 -> 509 | Q98: 20 | R98: 04 | S98: 56353866000130 | T98: ACQUA MARINE = SJLEE CONFECCOES ME
A99: 12/2025 | B99: 44032 | C99: VESTI | D99: Lupim Camisaria | E99: Vesti (Assinatura) | F99: Avançado | H99: 509 | J99: 509 | O99: =SUM(J99:M99)-N99 -> 509 | Q99: 15 | R99: 04 | S99: 92302520000177 | T99: Lupim Camisaria = LUPIM INDUSTRIA E COMERCIO DO VESTUARIO LTDA
A100: 12/2025 | B100: 44033 | C100: Atta | D100: Bem me quer | E100: Vesti (Assinatura) | F100: Avançado | H100: 453 | J100: 453 | O100: =SUM(J100:M100)-N100 -> 453 | Q100: 20 | R100: 04 | S100: 22905439000287 | T100: BEM ME QUER = E T LEE CONFECOES EPP
...

Sheet Starter 0126
A1: Fat.2025 | B1: ANIVERSÁRIO | C1: REAJUSTE ANUAL | D1: CANAL/Agência | E1: MARCA | F1: Subconta | G1: PLANO | H1: SETUP | I1: MENSALIDADE INICIAL | J1: VALOR REAJUSTE | K1: MENSALIDADE | L1: INTEGRAÇÃO | M1: ASSISTENTE | N1: FILIAL | O1: DESCONTOS | P1: TOTAL COBRADO | Q1: OBSERVAÇÕES | R1: CPF e CNPJ | S1: Mês de Reajuste
A2: 01/2026 | B2: 45259 | D2: Zoom- Cardume | E2: WA Baby | F2: Vesti (Cartão) | G2: Vesti Light | H2: 0 | I2: 317 | K2: =I2+J2 -> 317 | P2: =SUM(K2:N2)-O2 -> 317 | S2: =MONTH(B2) -> 11
A3: 01/2026 | B3: 45307 | C3: OK | D3: Vesti - Glads | E3: Levitheo | F3: Vesti (Cartão) | G3: Vesti Light | H3: 249 | I3: 267 | K3: =I3+J3 -> 267 | P3: =SUM(K3:N3)-O3 -> 267 | S3: =MONTH(B3) -> 1
A4: 01/2026 | B4: 45315 | C4: OK | D4: Sete | E4: Donna Stella | F4: Vesti (Cartão) | G4: Vesti Light | H4: 249 | I4: 267 | K4: =I4+J4 -> 267 | P4: =SUM(K4:N4)-O4 -> 267 | S4: =MONTH(B4) -> 1
A5: 01/2026 | B5: 45320 | C5: OK | D5: VESTI | E5: Nadri | F5: Vesti (Cartão) | G5: Vesti Light | H5: 249 | I5: 267 | K5: =I5+J5 -> 267 | P5: =SUM(K5:N5)-O5 -> 267 | S5: =MONTH(B5) -> 1
A6: 01/2026 | B6: 45323 | C6: OK | D6: Zoom- Cardume | E6: GO Padel | F6: Vesti (Cartão) | G6: Vesti Light | H6: 249 | I6: 249 | K6: 267 | P6: =SUM(K6:N6)-O6 -> 267 | S6: =MONTH(B6) -> 2
A7: 01/2026 | B7: 45323 | C7: OK | D7: Vesti - Glads | E7: Kroft Oficial | F7: Vesti (Cartão) | G7: Vesti Light | H7: 249 | I7: 249 | K7: 267 | P7: =SUM(K7:N7)-O7 -> 267 | S7: =MONTH(B7) -> 2
A8: 01/2026 | B8: 45337 | C8: OK | D8: Zoom- Cardume | E8: Divas Vero | F8: Vesti (Cartão) | G8: Vesti Light | H8: 249 | I8: 249 | K8: 267 | P8: =SUM(K8:N8)-O8 -> 267 | S8: =MONTH(B8) -> 2
A9: 01/2026 | B9: 45342 | C9: OK | D9: Vesti - ProRoi | E9: Repete Conf | F9: Vesti (Cartão) | G9: Vesti Light | H9: 249 | I9: 249 | K9: 267 | P9: =SUM(K9:N9)-O9 -> 267 | S9: =MONTH(B9) -> 2
A10: 01/2026 | B10: 45352 | D10: Sete | E10: Monnika Marikinha Brand | F10: Vesti (Cartão) | G10: Vesti Light | H10: 249 | I10: 249 | K10: 267 | P10: =SUM(K10:N10)-O10 -> 267 | S10: =MONTH(B10) -> 3
A11: 01/2026 | B11: 45352 | D11: Vesti - ProRoi | E11: RED ROCK (R) | F11: ProRoi | G11: Vesti Light | H11: 249 | I11: 249 | K11: 267 | P11: =SUM(K11:N11)-O11 -> 267 | S11: =MONTH(B11) -> 3
A12: 01/2026 | B12: 45363 | D12: Sete | E12: Fabio's Moda Intima | F12: Vesti (Cartão) | G12: Vesti Light | H12: 249 | I12: 249 | K12: 267 | P12: =SUM(K12:N12)-O12 -> 267 | S12: =MONTH(B12) -> 3
A13: 01/2026 | B13: 45379 | D13: Zoom- Cardume | E13: RL Modas | F13: Vesti (Cartão) | G13: Vesti Light | H13: 249 | I13: 249 | K13: 267 | P13: =SUM(K13:N13)-O13 -> 267 | S13: =MONTH(B13) -> 3
A14: 01/2026 | B14: 45393 | D14: Vesti - Tizzefy | E14: Aline Confecções | F14: Vesti (Cartão) | G14: Vesti Light | H14: 249 | I14: 267 | K14: 267 | P14: =SUM(K14:N14)-O14 -> 267 | S14: =MONTH(B14) -> 4
A15: 01/2026 | B15: 45411 | D15: Vesti - Tizzefy | E15: Igmar | F15: Vesti (Cartão) | G15: Vesti Light | H15: 249 | I15: 267 | K15: 267 | P15: =SUM(K15:N15)-O15 -> 267 | S15: =MONTH(B15) -> 4
A16: 01/2026 | B16: 45418 | D16: Vesti - Tizzefy | E16: Worldstar Lingerie | F16: Vesti (Cartão) | G16: Vesti Light | H16: 249 | I16: 267 | K16: 267 | P16: =SUM(K16:N16)-O16 -> 267 | S16: =MONTH(B16) -> 5
A17: 01/2026 | B17: 45425 | D17: Vesti - ProRoi | E17: Bella Fe | F17: Vesti (Cartão) | G17: Vesti Light | H17: 249 | I17: 267 | K17: 267 | P17: =SUM(K17:N17)-O17 -> 267 | S17: =MONTH(B17) -> 5
A18: 01/2026 | B18: 45434 | C18: ok | D18: Vesti - ProRoi | E18: RIBELIM | F18: Vesti - ProRoi | G18: Vesti Light | H18: 249 | I18: 285 | K18: 285 | P18: =SUM(K18:N18)-O18 -> 285 | S18: =MONTH(B18) -> 5
A19: 01/2026 | B19: 45446 | C19: ok | D19: VESTI | E19: Lupus Wear | F19: Vesti Light | G19: Vesti Light | H19: 249 | I19: 267 | K19: 267 | P19: =SUM(K19:N19)-O19 -> 267 | S19: =MONTH(B19) -> 6
A20: 01/2026 | B20: 45448 | C20: ok | D20: Zoom- Cardume | E20: Felps Confecções | F20: Vesti Light | G20: Vesti Light | H20: 0 | I20: 267 | K20: 267 | P20: =SUM(K20:N20)-O20 -> 267 | S20: =MONTH(B20) -> 6
A21: 01/2026 | B21: 45457 | C21: ok | D21: Vesti - Tizzefy | E21: MINOLLI | F21: Vesti - Tizzefy | G21: Vesti Light | H21: 249 | I21: 267 | K21: 267 | P21: =SUM(K21:N21)-O21 -> 267 | S21: =MONTH(B21) -> 6
A22: 01/2026 | B22: 45462 | C22: ok | D22: VESTI | E22: Urban Race | F22: Vesti Light | G22: Vesti Light | H22: 299 | I22: 317 | K22: 317 | P22: =SUM(K22:N22)-O22 -> 317 | S22: =MONTH(B22) -> 6
A23: 01/2026 | B23: 45462 | C23: ok | D23: VESTI | E23: Planet Charm | F23: Vesti Light | G23: Vesti Light | H23: 299 | I23: 317 | K23: 317 | P23: =SUM(K23:N23)-O23 -> 317 | S23: =MONTH(B23) -> 6
A24: 01/2026 | B24: 45489 | D24: Vê Vantagens | E24: PEROLA ORIENTAL LK&D | F24: Vê Vantagens | G24: Vesti Light | H24: 249 | I24: 267 | K24: 267 | P24: =SUM(K24:N24)-O24 -> 267 | S24: =MONTH(B24) -> 7
A25: 01/2026 | B25: 45498 | D25: VESTI | E25: IZZA PVH | F25: Vesti Multimarcas | G25: Vesti Multimarca | H25: 99 | I25: 99 | K25: 99 | P25: =SUM(K25:N25)-O25 -> 99 | R25: 31506519000170 | S25: =MONTH(B25) -> 7
A26: 01/2026 | B26: 45500 | D26: Vesti - ProRoi | E26: BegKids | F26: Vesti - ProRoi | G26: Vesti Light | H26: 299 | I26: 317 | K26: 317 | P26: =SUM(K26:N26)-O26 -> 317 | S26: =MONTH(B26) -> 7
A27: 01/2026 | B27: 45501 | D27: VESTI | E27: Agridoce | F27: Vesti Light | G27: Vesti Light | H27: 699 | I27: 299 | K27: 299 | P27: =SUM(K27:N27)-O27 -> 299 | S27: =MONTH(B27) -> 7
A28: 01/2026 | B28: 45505 | C28: OK | D28: VESTI | E28: Arary | F28: Vesti Light | G28: Vesti Light | H28: 299 | I28: 317 | K28: 317 | P28: =SUM(K28:N28)-O28 -> 317 | S28: =MONTH(B28) -> 8
A29: 01/2026 | B29: 45506 | C29: OK | D29: Vê Vantagens | E29: Aurami | F29: Vê Vantagens | G29: Vesti Light | H29: 299 | I29: 317 | K29: 317 | P29: =SUM(K29:N29)-O29 -> 317 | S29: =MONTH(B29) -> 8
A30: 01/2026 | B30: 45509 | C30: OK | D30: VESTI | E30: Valentina Fashion | F30: Vesti Multimarcas | G30: Vesti Multimarca | H30: 99 | I30: 117 | K30: 117 | O30: 18 | P30: =SUM(K30:N30)-O30 -> 99 | R30: 39554207000143 | S30: =MONTH(B30) -> 8
A31: 01/2026 | B31: 45506 | C31: OK | D31: VESTI | E31: TNT Moda Fitness | F31: Vesti Light | G31: Vesti Light | H31: 299 | I31: 317 | K31: 317 | P31: =SUM(K31:N31)-O31 -> 317 | S31: =MONTH(B31) -> 8
A32: 01/2026 | B32: 45519 | C32: OK | D32: Vê Vantagens | E32: PEROLA ORIENTAL = M&K | F32: Vê Vantagens | G32: Vesti Light | H32: 299 | I32: 267 | K32: 267 | P32: =SUM(K32:N32)-O32 -> 267 | S32: =MONTH(B32) -> 8
A33: 01/2026 | B33: 45532 | C33: OK | D33: VESTI | E33: Lado Doce | F33: Vesti Light | G33: Vesti Light | H33: 800 | I33: 317 | K33: 317 | P33: =SUM(K33:N33)-O33 -> 317 | S33: =MONTH(B33) -> 8
A34: 01/2026 | B34: 45533 | C34: OK | D34: VESTI | E34: Espaço Berta | F34: Vesti Multimarcas | G34: Vesti Multimarca | H34: 99 | I34: 99 | K34: 99 | P34: =SUM(K34:N34)-O34 -> 99 | R34: 25225294120 | S34: =MONTH(B34) -> 8
A35: 01/2026 | B35: 45533 | C35: OK | D35: VESTI | E35: A Rouparia | F35: Vesti Multimarcas | G35: Vesti Multimarca | H35: 99 | I35: 117 | K35: 117 | P35: =SUM(K35:N35)-O35 -> 117 | R35: 32979501000158 | S35: =MONTH(B35) -> 8
A36: 01/2026 | B36: 45539 | C36: ok | D36: VESTI | E36: Drika Confeccoes | F36: Vesti Light | G36: Vesti Light | H36: 800 | I36: 317 | K36: 317 | P36: =SUM(K36:N36)-O36 -> 317 | S36: =MONTH(B36) -> 9
A37: 01/2026 | B37: 45539 | C37: ok | D37: Vesti - Tizzefy | E37: VLY JEANS | F37: Vesti - Tizzefy | G37: Vesti Light | H37: 800 | I37: 267 | K37: 267 | P37: =SUM(K37:N37)-O37 -> 267 | S37: =MONTH(B37) -> 9
A38: 01/2026 | B38: 45539 | C38: ok | D38: VESTI | E38: Veste Vegana | F38: Vesti Light | G38: Vesti Light | H38: 249 | I38: 267 | K38: 267 | P38: =SUM(K38:N38)-O38 -> 267 | S38: =MONTH(B38) -> 9
A39: 01/2026 | B39: 45541 | C39: ok | D39: VESTI | E39: Dominio​ Conceito | F39: Vesti Light | G39: Vesti Light | H39: =800+299 -> 1099 | I39: 317 | K39: 317 | P39: =SUM(K39:N39)-O39 -> 317 | S39: =MONTH(B39) -> 9
A40: 01/2026 | B40: 45547 | C40: ok | D40: VESTI | E40: Alice Amaral Brand Store | F40: Vesti Multimarcas | G40: Vesti Multimarca | H40: 99 | I40: 99 | K40: 99 | P40: =SUM(K40:N40)-O40 -> 99 | R40: 30707302000165 | S40: =MONTH(B40) -> 9
A41: 01/2026 | B41: 45548 | C41: ok | D41: VESTI | E41: Julia Andrade Bijuterias​ | F41: Vesti Light | G41: Vesti Light | H41: 299 | I41: 317 | K41: 317 | P41: =SUM(K41:N41)-O41 -> 317 | S41: =MONTH(B41) -> 9
A42: 01/2026 | B42: 45548 | C42: ok | D42: VESTI | E42: Little Star | F42: Vesti Light | G42: Vesti Light | H42: 299 | I42: 317 | K42: 317 | P42: =SUM(K42:N42)-O42 -> 317 | S42: =MONTH(B42) -> 9
A43: 01/2026 | B43: 45509 | C43: OK | D43: VESTI | E43: Chocoberry | F43: Vesti Light | G43: Vesti Light | H43: 299 | I43: 317 | K43: 317 | P43: =SUM(K43:N43)-O43 -> 317 | S43: =MONTH(B43) -> 8
A44: 01/2026 | B44: 45553 | D44: VESTI | E44: Lado Doce | F44: Vesti Light | G44: Assistente | H44: 300 | M44: 300 | P44: =SUM(K44:N44)-O44 -> 300 | S44: =MONTH(B44) -> 9
A45: 01/2026 | B45: 45554 | C45: ok | D45: VESTI | E45: New Gomone | F45: Vesti Light | G45: Vesti Light | H45: 299 | I45: 317 | K45: 317 | P45: =SUM(K45:N45)-O45 -> 317 | S45: =MONTH(B45) -> 9
A46: 01/2026 | B46: 45558 | C46: ok | D46: VESTI | E46: New Mire Aviamentos | F46: Vesti Light | G46: Vesti Light | H46: 299 | I46: 317 | K46: 317 | M46: 149 | P46: =SUM(K46:N46)-O46 -> 466 | S46: =MONTH(B46) -> 9
A47: 01/2026 | B47: 45566 | C47: 18 | D47: VESTI | E47: Full Stop | F47: Vesti Light | G47: Vesti Light | H47: 299 | I47: 299 | J47: 18 | K47: 317 | P47: =SUM(K47:N47)-O47 -> 317 | S47: =MONTH(B47) -> 10
A48: 01/2026 | B48: 45566 | D48: VESTI | E48: G2K JEANS | F48: Vesti Light | G48: Vesti Light | H48: =800+299 -> 1099 | I48: 317 | K48: 317 | P48: =SUM(K48:N48)-O48 -> 317 | S48: =MONTH(B48) -> 10
A49: 01/2026 | B49: 45566 | D49: VESTI | E49: Donna Veste Moda Feminina | F49: Vesti Multimarcas | G49: Catálogo | I49: 29.9 | K49: 29.9 | P49: =SUM(K49:N49)-O49 -> 29.9 | R49: 38105487000140 | S49: =MONTH(B49) -> 10
A50: 01/2026 | B50: 45567 | C50: 18 | D50: VESTI | E50: HARD ADVENTURE | F50: Vesti Light | G50: Vesti Light | H50: 299 | I50: 299 | J50: 18 | K50: 317 | P50: =SUM(K50:N50)-O50 -> 317 | S50: =MONTH(B50) -> 10
A51: 01/2026 | B51: 45572 | C51: 18 | D51: Vesti - ProRoi | E51: Caronly | F51: Vesti - ProRoi | G51: Vesti Light | H51: 299 | I51: 299 | J51: 18 | K51: 317 | P51: =SUM(K51:N51)-O51 -> 317 | S51: =MONTH(B51) -> 10
A52: 01/2026 | B52: 45568 | C52: 18 | D52: Vesti - ProRoi | E52: Brand Fitness | F52: Vesti - ProRoi | G52: Vesti Light | H52: 299 | I52: 299 | J52: 18 | K52: 317 | P52: =SUM(K52:N52)-O52 -> 317 | S52: =MONTH(B52) -> 10
A53: 01/2026 | B53: 45576 | D53: VESTI | E53: TIAGO SILVA LULA | F53: Vesti Multimarcas | G53: Vesti Conecta | H53: 99 | I53: 99 | K53: 99 | P53: =SUM(K53:N53)-O53 -> 99 | R53: 42740652000102 | S53: =MONTH(B53) -> 10
A54: 01/2026 | B54: 45580 | C54: 18 | D54: Vesti - Uemtel | E54: F C Mamani | F54: Vesti - Uemtel | G54: Vesti Light | H54: 299 | I54: 299 | J54: 18 | K54: 317 | P54: =SUM(K54:N54)-O54 -> 317 | S54: =MONTH(B54) -> 10
A55: 01/2026 | B55: 45581 | D55: Vesti - ProRoi | E55: Brand Fitness | F55: Vesti - ProRoi | G55: Integração | H55: 800 | P55: =SUM(K55:N55)-O55 -> 0 | S55: =MONTH(B55) -> 10
A56: 01/2026 | B56: 45582 | C56: 18 | D56: Vesti - Tizzefy | E56: Ganso Outlet- TGR Denim | F56: Vesti - Tizzefy | G56: Vesti Light | H56: 299 | I56: 299 | J56: 18 | K56: 317 | P56: =SUM(K56:N56)-O56 -> 317 | S56: =MONTH(B56) -> 10
A57: 01/2026 | B57: 45583 | C57: 18 | D57: VESTI | E57: Karal | F57: Vesti Light | G57: Vesti Light | H57: 299 | I57: 299 | J57: 18 | K57: 317 | P57: =SUM(K57:N57)-O57 -> 317 | S57: =MONTH(B57) -> 10
A58: 01/2026 | B58: 45583 | C58: 18 | D58: Vê Vantagens | E58: Espaço Hada | F58: Vê Vantagens | G58: Vesti Light | H58: 299 | I58: 299 | J58: 18 | K58: 317 | P58: =SUM(K58:N58)-O58 -> 317 | S58: =MONTH(B58) -> 10
A59: 01/2026 | B59: 45586 | D59: Zoom- Cardume | E59: República Caipira | F59: Mensalidade Vesti | G59: Vesti Light- Filial | N59: 249 | P59: =SUM(K59:N59)-O59 -> 249 | S59: =MONTH(B59) -> 10
A60: 01/2026 | B60: 45587 | C60: 18 | D60: Vesti - ProRoi | E60: Imporio Fitness | F60: Vesti - ProRoi | G60: Vesti Light | H60: 299 | I60: 299 | J60: 18 | K60: 317 | P60: =SUM(K60:N60)-O60 -> 317 | S60: =MONTH(B60) -> 10
A61: 01/2026 | B61: 45593 | C61: 18 | D61: Vesti - Tizzefy | E61: Evelyn Fashion | F61: Vesti Light | G61: Vesti Light | H61: 299 | I61: 299 | J61: 18 | K61: 317 | P61: =SUM(K61:N61)-O61 -> 317 | S61: =MONTH(B61) -> 10
A62: 01/2026 | B62: 45594 | C62: 18 | D62: Vesti - Uemtel | E62: Ary Fashions Femininas | F62: Vesti - Uemtel | G62: Vesti Light | H62: 299 | I62: 299 | J62: 18 | K62: 317 | P62: =SUM(K62:N62)-O62 -> 317 | S62: =MONTH(B62) -> 10
A63: 01/2026 | B63: 45594 | C63: 18 | D63: VESTI | E63: Carmen Jeans | F63: Vesti Light | G63: Vesti Light | I63: 299 | J63: 18 | K63: 317 | P63: =SUM(K63:N63)-O63 -> 317 | S63: =MONTH(B63) -> 10
A64: 01/2026 | B64: 45594 | C64: 18 | D64: Vesti - ProRoi | E64: Sued T-shirt | F64: Vesti - ProRoi | G64: Vesti Light | H64: 299 | I64: 299 | J64: 18 | K64: 317 | P64: =SUM(K64:N64)-O64 -> 317 | S64: =MONTH(B64) -> 10
A65: 01/2026 | B65: 45594 | C65: 18 | D65: Vesti - Tizzefy | E65: Afri.co | F65: Vesti - Tizzefy | G65: Vesti Light | H65: =800+299 -> 1099 | I65: 299 | J65: 18 | K65: 317 | P65: =SUM(K65:N65)-O65 -> 317 | S65: =MONTH(B65) -> 10
A66: 01/2026 | B66: 45595 | C66: 18 | D66: Vê Vantagens | E66: Ma Che Bella | F66: Vê Vantagens | G66: Vesti Light | H66: 299 | I66: 299 | J66: 18 | K66: 317 | P66: =SUM(K66:N66)-O66 -> 317 | S66: =MONTH(B66) -> 10
A67: 01/2026 | B67: 45546 | C67: ok | D67: VESTI | E67: Armored Jeans | F67: Vesti Light | G67: Vesti Light | H67: 299 | I67: 317 | K67: 317 | P67: =SUM(K67:N67)-O67 -> 317 | S67: =MONTH(B67) -> 9
A68: 01/2026 | B68: 45600 | D68: VESTI | E68: Traffos Atacado | F68: Vesti Light | G68: Vesti Light | H68: 299 | I68: 317 | K68: =I68 -> 317 | P68: =SUM(K68:N68)-O68 -> 317 | S68: =MONTH(B68) -> 11
A69: 01/2026 | B69: 45601 | D69: VESTI | E69: Look Kids | F69: Vesti Multimarcas | G69: Catálogo | H69: 29.9 | I69: 29.9 | K69: =I69 -> 29.9 | P69: =SUM(K69:N69)-O69 -> 29.9 | S69: =MONTH(B69) -> 11
A70: 01/2026 | B70: 45603 | D70: VESTI | E70: Dazz Modas | F70: Vesti Light | G70: Vesti Light | H70: 299 | I70: 317 | K70: =I70 -> 317 | P70: =SUM(K70:N70)-O70 -> 317 | S70: =MONTH(B70) -> 11
A71: 01/2026 | B71: 45603 | D71: Vesti - Glads | E71: Wyllara | F71: Vesti - Glads | G71: Vesti Light | H71: 299 | I71: 317 | K71: =I71 -> 317 | P71: =SUM(K71:N71)-O71 -> 317 | R71: 19219215000126​ | S71: =MONTH(B71) -> 11
A72: 01/2026 | B72: 45604 | D72: Vesti - ProRoi | E72: ASDN | F72: Vesti - ProRoi | G72: Integração | H72: 800 | K72: =I72 | P72: =SUM(K72:N72)-O72 -> 0 | R72: 47519875000168 | S72: =MONTH(B72) -> 11
A73: 01/2026 | B73: 45604 | D73: VESTI | E73: ThreeSix 3/6 | F73: Vesti Light | G73: Vesti Light | H73: 299 | I73: 317 | K73: =I73 -> 317 | P73: =SUM(K73:N73)-O73 -> 317 | R73: 36443627000164 | S73: =MONTH(B73) -> 11
A74: 01/2026 | B74: 45608 | D74: Vesti - Glads | E74: ​Erilluz Jeans | F74: Vesti Light | G74: Vesti Light | H74: 299 | I74: 317 | K74: =I74 -> 317 | P74: =SUM(K74:N74)-O74 -> 317 | R74: 32796225000192​ | S74: =MONTH(B74) -> 11
A75: 01/2026 | B75: 45610 | D75: VESTI | E75: Hellas Boutique | F75: Vesti Multimarcas | G75: Catálogo | H75: 29.9 | I75: 29.9 | K75: =I75 -> 29.9 | P75: =SUM(K75:N75)-O75 -> 29.9 | R75: 07159050000165 | S75: =MONTH(B75) -> 11
A76: 01/2026 | B76: 45614 | D76: VESTI | E76: Lie | F76: Vesti Light | G76: Vesti Light | H76: 299 | I76: 317 | K76: =I76 -> 317 | P76: =SUM(K76:N76)-O76 -> 317 | R76: 12151080447 | S76: =MONTH(B76) -> 11
A77: 01/2026 | B77: 45617 | D77: VESTI | E77: ​By Picle | F77: Vesti Light | G77: Vesti Light | H77: 299 | I77: 317 | K77: =I77 -> 317 | P77: =SUM(K77:N77)-O77 -> 317 | R77: 17267627000106 | S77: =MONTH(B77) -> 11
A78: 01/2026 | B78: 45617 | D78: Vesti - Glads | E78: Beach Cat Atacado | F78: Vesti Light | G78: Vesti Light | H78: 299 | I78: 317 | K78: =I78 -> 317 | P78: =SUM(K78:N78)-O78 -> 317 | R78: 07039154870 | S78: =MONTH(B78) -> 11
A79: 01/2026 | B79: 45618 | D79: VESTI | E79: MINI DIVA | F79: Vesti Multimarcas | G79: Catálogo | H79: 29.9 | I79: 29.9 | K79: =I79 -> 29.9 | P79: =SUM(K79:N79)-O79 -> 29.9 | R79: 05189065405 | S79: =MONTH(B79) -> 11
A80: 01/2026 | B80: 45623 | D80: VESTI | E80: Bela Palu | F80: Vesti Light | G80: Vesti Light | H80: 299 | I80: 317 | K80: =I80 -> 317 | P80: =SUM(K80:N80)-O80 -> 317 | R80: 15865836000126 | S80: =MONTH(B80) -> 11
A81: 01/2026 | B81: 45623 | D81: VESTI | E81: BS Multimarcas | F81: Vesti Multimarcas | G81: Catálogo | H81: 29.9 | I81: 29.9 | K81: =I81 -> 29.9 | P81: =SUM(K81:N81)-O81 -> 29.9 | R81: 49226900000140 | S81: =MONTH(B81) -> 11
A82: 01/2026 | B82: 45623 | D82: Vesti - Tizzefy | E82: KVG Oficial | F82: Vesti Light | G82: Vesti Light | H82: 800 | I82: 317 | K82: =I82 -> 317 | P82: =SUM(K82:N82)-O82 -> 317 | R82: 10417765000185​ | S82: =MONTH(B82) -> 11
A83: 01/2026 | B83: 45625 | D83: VESTI | E83: New Mire Aviamentos | F83: Vesti Light | G83: Assistente | H83: 240 | M83: 240 | P83: =SUM(K83:N83)-O83 -> 240 | S83: =MONTH(B83) -> 11
A84: 01/2026 | B84: 45572 | C84: 18 | D84: VESTI | E84: MEIATRÊS | F84: Vesti(assinatura) | G84: Vesti Light | H84: 249 | I84: 249 | J84: 18 | K84: 267 | P84: =SUM(K84:N84)-O84 -> 267 | S84: =MONTH(B84) -> 10
A85: 01/2026 | B85: 45629 | D85: Vesti - Glads | E85: CavWeillers- Moda Fitness | F85: Vesti Light | G85: Vesti Light | H85: 299 | I85: 299 | K85: =I85 -> 299 | P85: =SUM(K85:N85)-O85 -> 299 | R85: 36269709000134 | S85: =MONTH(B85) -> 12
A86: 01/2026 | B86: 45637 | D86: VESTI | E86: Viotto | F86: Vesti Light | G86: Vesti Light | H86: 299 | I86: 299 | K86: =I86 -> 299 | P86: =SUM(K86:N86)-O86 -> 299 | R86: 55170272000121 | S86: =MONTH(B86) -> 12
A87: 01/2026 | B87: 45638 | D87: VESTI | E87: Longhini Semijoias | F87: Vesti Multimarcas | G87: Vesti Loja | H87: 99.9 | I87: 99.9 | K87: =I87 -> 99.9 | P87: =SUM(K87:N87)-O87 -> 99.9 | R87: 48900768000148 | S87: =MONTH(B87) -> 12
A88: 01/2026 | B88: 45639 | D88: VESTI | E88: Adoratta Noivas & Festas | F88: Vesti Multimarcas | G88: Catálogo | H88: 29.9 | I88: 29.9 | K88: =I88 -> 29.9 | P88: =SUM(K88:N88)-O88 -> 29.9 | R88: 28089163000101 | S88: =MONTH(B88) -> 12
A89: 01/2026 | B89: 45659 | C89: Novo | D89: VESTI | E89: Doce Infancia kids Teen | F89: Vesti Multimarcas | G89: Catálogo | H89: 29.9 | I89: 29.9 | K89: =I89 -> 29.9 | P89: =SUM(K89:N89)-O89 -> 29.9 | Q89: Vanessa Silva Alves Begnini | R89: 02057238105 | S89: 1
A90: 01/2026 | B90: 45665 | C90: Novo | D90: Vesti - Glads | E90: Mavem | F90: Vesti - Glads | G90: Vesti Light | H90: 299 | I90: 299 | K90: =I90 -> 299 | P90: =SUM(K90:N90)-O90 -> 299 | R90: 15583317000175 | S90: 1
A91: 01/2026 | B91: 45665 | C91: Novo | D91: VESTI | E91: Moa Plus Size | F91: Vesti Light | G91: Vesti Light | H91: 299 | I91: 299 | K91: =I91 -> 299 | P91: =SUM(K91:N91)-O91 -> 299 | Q91: Celeb | R91: 47661072000143 | S91: 1
A92: 01/2026 | B92: 45665 | C92: Novo | D92: Vesti - Tizzefy | E92: Pedrita Baby | F92: Vesti Light | G92: Vesti Light | H92: 299 | I92: 299 | K92: =I92 -> 299 | P92: =SUM(K92:N92)-O92 -> 299 | R92: 31482182000108 | S92: 1
A93: 01/2026 | B93: 45667 | C93: Novo | D93: VESTI | E93: B.W multiservices | F93: Vesti Multimarcas | G93: Vesti Loja | H93: 99.9 | I93: 99.9 | K93: =I93 -> 99.9 | P93: =SUM(K93:N93)-O93 -> 99.9 | R93: 50336661000160 | S93: 1
A94: 01/2026 | B94: 45670 | C94: Novo | D94: Vesti - Tizzefy | E94: ​Savannah | F94: Vesti Light | G94: Vesti Light | H94: 299 | I94: 299 | K94: =I94 -> 299 | P94: =SUM(K94:N94)-O94 -> 299 | Q94: Esj Confeccoes | R94: 35945794000140 | S94: 1
A95: 01/2026 | B95: 45671 | C95: Novo | D95: Vesti - Glads | E95: Gigantinho Kids | F95: Vesti - Glads | G95: Vesti Light | H95: 299 | I95: 299 | K95: =I95 -> 299 | P95: =SUM(K95:N95)-O95 -> 299 | Q95: Gigantinho Kids | R95: 11787907465 | S95: 1
A96: 01/2026 | B96: 45671 | C96: Novo | D96: VESTI | E96: Outlet JV | F96: Vesti Multimarcas | G96: Catálogo | H96: 29.9 | I96: 29.9 | K96: =I96 -> 29.9 | P96: =SUM(K96:N96)-O96 -> 29.9 | R96: 31923070000145 | S96: 1
A97: 01/2026 | B97: 45673 | C97: Novo | D97: Vesti - Glads | E97: Brilho Trend | F97: Vesti - Glads | G97: Vesti Light | H97: 299 | I97: 299 | K97: =I97 -> 299 | P97: =SUM(K97:N97)-O97 -> 299 | Q97: Giovanna Carvalho | R97: 44851232000129 | S97: 1
A98: 01/2026 | B98: 45673 | C98: Novo | D98: Vesti- Glads | E98: ​Era Uma Vez​ | F98: Vesti Light | G98: Vesti Light | H98: 800 | I98: 299 | K98: =I98 -> 299 | P98: =SUM(K98:N98)-O98 -> 299 | R98: 38479807000121 | S98: 1
A99: 01/2026 | B99: 45681 | C99: Novo | D99: VESTI | E99: Closet Moura | F99: Vesti Multimarcas | G99: Catálogo | H99: 29.9 | I99: 29.9 | K99: =I99 -> 29.9 | P99: =SUM(K99:N99)-O99 -> 29.9 | R99: 58429877000182 | S99: 1
A100: 01/2026 | B100: 45687 | C100: Novo | D100: Vesti - Uemtel | E100: BellaGirassol | F100: Vesti - Uemtel | G100: Vesti Light | H100: 1029 | I100: 299 | K100: =I100 -> 299 | P100: =SUM(K100:N100)-O100 -> 299 | R100: 46896753000128 | S100: 1
...

Sheet Vesti 012026
A1: Fat.2025 | B1: ANIVERSÁRIO | C1: REAJUSTE ANUAL | D1: CANAL | E1: MARCA | F1: Subconta | G1: PLANO | H1: SETUP | I1: MENSALIDADE INICIAL | J1: VALOR REAJUSTE | K1: MENSALIDADE | L1: INTEGRAÇÃO | M1: ASSISTENTE | N1: FILIAL | O1: DESCONTOS | P1: TOTAL COBRADO | Q1: OBSERVAÇÕES | R1: Dia Vencimento | S1: Mês de Reajuste | T1: CPFCNPJ | U1: NOME/RAZÃO SOCIAL
A2: 01/2026 | B2: 42795 | D2: VESTI | E2: TNW Jeans | F2: Vesti (Assinatura) | G2: Profissional | I2: 1156 | K2: 1156 | P2: =SUM(K2:N2)-O2 -> 1156 | R2: 17 | S2: 04 | T2: 4937453000108 | U2: TNW JEANS = TNW CONFECCOES LTDA
A3: 01/2026 | B3: 42937 | C3: ok | D3: Atta | E3: Peonia | F3: Atta | G3: Essencial | I3: 302 | K3: 302 | P3: =SUM(K3:N3)-O3 -> 302 | R3: 20 | S3: 4 | T3: 07993188000165
A4: 01/2026 | B4: 43160 | D4: Atta | E4: Maria De Chita | F4: Vesti (Assinatura) | G4: Profissional | I4: 724 | K4: 724 | P4: =SUM(K4:N4)-O4 -> 724 | R4: 15 | S4: 04 | T4: 07402979000173 | U4: MARIA DE CHITA = MARIA DE CHITA CONFECCOES LTDA
A5: 01/2026 | B5: 43160 | D5: Atta | E5: Shanes | F5: Vesti (Assinatura) | G5: Profissional | I5: 1179 | K5: 1179 | P5: =SUM(K5:N5)-O5 -> 1179 | R5: 20 | S5: 04 | T5: 46446130000153 | U5: SHANES = CONFECCOES SHANES LTDA
A6: 01/2026 | B6: 43160 | D6: Atta | E6: Talgui | F6: Vesti (Assinatura) | G6: Avançado | I6: 441.33 | K6: 441.33 | P6: =SUM(K6:N6)-O6 -> 441.33 | R6: 15 | S6: 04 | T6: 05876663000198 | U6: TALGUI = TALGUI CONFECCOES DE ROUPAS LTDA
A7: 01/2026 | B7: 43160 | D7: Atta | E7: Coinage | F7: Vesti (Assinatura) | G7: Profissional | I7: 1179 | K7: 1179 | P7: =SUM(K7:N7)-O7 -> 1179 | R7: 20 | S7: 04 | T7: 33724927000123 | U7: Coinage = DON IN CONFECCOES LTDA
A8: 01/2026 | B8: 43160 | D8: Atta | E8: Moda Inn | F8: Vesti (Assinatura) | G8: Essencial | I8: 283 | K8: 283 | P8: =SUM(K8:N8)-O8 -> 283 | R8: 20 | S8: 04 | T8: 49921554000110 | U8: MODA INN = CONFECCOES SIMON LTDA
A9: 01/2026 | B9: 43160 | D9: Atta | E9: Betsey | F9: Vesti (Assinatura) | G9: Profissional | I9: 1003 | K9: 1003 | P9: =SUM(K9:N9)-O9 -> 1003 | R9: 15 | S9: 04 | T9: 06161024000109 | U9: BETSEY = BETSEY CONFECCOES LTDA
A10: 01/2026 | B10: 43160 | D10: Atta | E10: Cashier | F10: Vesti (Assinatura) | G10: Profissional | I10: 1015 | K10: 1015 | P10: =SUM(K10:N10)-O10 -> 1015 | R10: 30 | S10: 04 | T10: 60368669000162 | U10: CASHIER = CASHIER CONFECCOES LTDA
A11: 01/2026 | B11: 43160 | D11: Atta | E11: Cony Green | F11: Vesti (Assinatura) | G11: Avançado | I11: 425 | K11: 425 | P11: =SUM(K11:N11)-O11 -> 425 | R11: 15 | S11: 04 | T11: 44511277000154 | U11: CONY GREEN = CONFECCOES E MODAS CONY GREEN LTDA
A12: 01/2026 | B12: 43160 | D12: Atta | E12: Pury | F12: Vesti (Assinatura) | G12: Profissional | I12: 1327 | K12: 1327 | N12: 359 | P12: =SUM(K12:N12)-O12 -> 1686 | R12: 15 | S12: 04 | T12: 12576594000162 | U12: PURY = CONFECCOES PURY LTDA
A13: 01/2026 | B13: 43160 | D13: VESTI | E13: Tricomix | F13: Vesti (Assinatura) | G13: Avançado | I13: 1193 | K13: 1193 | L13: 350 | P13: =SUM(K13:N13)-O13 -> 1543 | R13: 11 | S13: 04 | T13: 04665515000161 | U13: TRICOMIX = TRICOMIX INDUSTRIA E COMERCIO DE CONFECCOES EIRELI
A14: 01/2026 | B14: 43160 | D14: Atta | E14: Lov It | F14: Vesti (Assinatura) | G14: Avançado | I14: 425 | K14: 425 | P14: =SUM(K14:N14)-O14 -> 425 | R14: 11 | S14: 04 | T14: 21749422000215 | U14: LOV IT = WELOVIT CONFECCOES LTDA
A15: 01/2026 | B15: 43160 | D15: Atta | E15: Hemix | F15: Vesti (Assinatura) | G15: Essencial | I15: 283 | K15: 283 | M15: =550+120 -> 670 | P15: =SUM(K15:N15)-O15 -> 953 | R15: 15 | S15: 04 | T15: 07389520000187 | U15: HEMIX = HEMIX CONFECCOES LTDA
A16: 01/2026 | B16: 43160 | D16: Miredata | E16: Mottive | F16: Vesti (Assinatura) | G16: Profissional | I16: 1179 | K16: 1179 | P16: =SUM(K16:N16)-O16 -> 1179 | R16: 20 | S16: 04 | T16: 24330475000104 | U16: MOTTIVE = PROBELLAS CONFECCOES LTDA EPP
A17: 01/2026 | B17: 43160 | D17: Atta | E17: Miss Alfa | F17: Vesti (Assinatura) | G17: Essencial | I17: 283 | K17: 283 | P17: =SUM(K17:N17)-O17 -> 283 | R17: 15 | S17: 04 | T17: 28497561000167 | U17: MISS ALFA = MISS ALFA COMERCIO DE ROUPAS LTDA
A18: 01/2026 | B18: 43160 | D18: VESTI | E18: Anemone | F18: Vesti (Assinatura) | G18: Avançado | I18: 1013 | K18: 1013 | P18: =SUM(K18:N18)-O18 -> 1013 | R18: 11 | S18: 04 | T18: 30962814000178 | U18: ANEMONE = MM21 INDUSTRIA E COMERCIO DE ROUPAS LTDA
A19: 01/2026 | B19: 43160 | D19: Miredata | E19: Pianeta | F19: Vesti (Assinatura) | G19: Profissional | I19: 761 | K19: 761 | P19: =SUM(K19:N19)-O19 -> 761 | R19: 20 | S19: 04 | T19: 31583000000195 | U19: PIANETA = INTERMIX CONFECCOES DE ROUPAS LTDA
A20: 01/2026 | B20: 43356 | D20: Atta | E20: Morina | F20: Vesti (Assinatura) | G20: Profissional | I20: 1138 | K20: 1138 | P20: =SUM(K20:N20)-O20 -> 1138 | R20: 15 | S20: 04 | T20: 44029041000186 | U20: Morina = FYK CONFECCOES LTDA
A21: 01/2026 | B21: 43586 | D21: Atta | E21: Artemiss | F21: Vesti (Assinatura) | G21: Avançado | I21: 569 | K21: 569 | N21: 275 | P21: =SUM(K21:N21)-O21 -> 844 | R21: 11 | S21: 04 | T21: 05320347000135 | U21: ARTEMISS = CONFECCOES ARTE E MISS LTDA
A22: 01/2026 | B22: 43586 | D22: Atta | E22: IT LOOK | F22: Vesti (Assinatura) | G22: Essencial | I22: 283 | K22: 283 | P22: =SUM(K22:N22)-O22 -> 283 | R22: 15 | S22: 04 | T22: 21659326000103 | U22: IT LOOK = IT LOOK CONFECCAO E COMERCIO DE ROUPAS LTDA
A23: 01/2026 | B23: 43586 | D23: Atta | E23: E YUNIRE | F23: Vesti (Assinatura) | G23: Essencial | I23: 354 | K23: 354 | P23: =SUM(K23:N23)-O23 -> 354 | R23: 15 | S23: 04 | T23: 45375658000116 | U23: E YUNIRE = YUNIVEST CONFECCOES LTDA
A24: 01/2026 | B24: 43593 | D24: Atta | E24: Incentive | F24: Vesti (Assinatura) | G24: Essencial | I24: 528.33 | K24: 528.33 | P24: =SUM(K24:N24)-O24 -> 528.33 | R24: 30 | S24: 04 | T24: 29780242000127 | U24: INCENTIVE = CONFECCOES INCENTIVE LTDA
A25: 01/2026 | B25: 43593 | D25: Atta | E25: Mazarin | F25: Vesti (Assinatura) | G25: Essencial | I25: 326.67 | K25: 326.67 | P25: =SUM(K25:N25)-O25 -> 326.67 | R25: 15 | S25: 04 | T25: 03598605000203 | U25: MAZARIN = CONFECCOES MAZARIN LTDA
A26: 01/2026 | B26: 43600 | D26: Atta | E26: Blue Blossom | F26: Vesti (Assinatura) | G26: Essencial | I26: 283 | K26: 283 | N26: 410 | P26: =SUM(K26:N26)-O26 -> 693 | R26: 15 | S26: 04 | T26: 30828978000107 | U26: BLUE BLOSSOM = BLUE BLOSSOM CONFECCOES EIRELI
A27: 01/2026 | B27: 43606 | D27: VESTI | E27: Crocker | F27: Vesti (Assinatura) | G27: Profissional | I27: 1179 | K27: 1179 | N27: 410 | P27: =SUM(K27:N27)-O27 -> 1589 | R27: 15 | S27: 04 | T27: 60652948000153 | U27: CROCKER = US BRASIL INDUSTRIA E COMERCIO DE ROUPAS LTDA
A28: 01/2026 | B28: 43606 | D28: VESTI | E28: Lesto | F28: Vesti (Assinatura) | G28: Essencial | I28: 284.33 | K28: 284.33 | P28: =SUM(K28:N28)-O28 -> 284.33 | R28: 15 | S28: 04 | T28: 58418377000145 | U28: LESTO = LESTO CONFECCOES LTDA
A29: 01/2026 | B29: 43619 | D29: Atta | E29: Ellen One | F29: Vesti (Cartão) | G29: Essencial | I29: 283 | K29: 283 | P29: =SUM(K29:N29)-O29 -> 283 | R29: 06 | S29: 4 | T29: 07554437000116 | U29: Ellen One = CONFECCOES ELLEN ONE EIRELI
A30: 01/2026 | B30: 43619 | D30: Atta | E30: Instar | F30: Vesti (Assinatura) | G30: Essencial | I30: 283 | K30: 283 | P30: =SUM(K30:N30)-O30 -> 283 | R30: 15 | S30: 04 | T30: 32649954000116 | U30: INSTAR = CLASSY MISSY CONFECCAO DE ROUPAS LTDA
A31: 01/2026 | B31: 43633 | D31: Atta | E31: Aramodu | F31: Vesti (Assinatura) | G31: Essencial | I31: 283 | K31: 283 | P31: =SUM(K31:N31)-O31 -> 283 | R31: 11 | S31: 04 | T31: 97541061000106 | U31: ARAMODU = CONFECCOES ARAMODU EIRELI
A32: 01/2026 | B32: 43643 | D32: Atta | E32: Scera | F32: Vesti (Assinatura) | G32: Essencial | I32: 283 | K32: 283 | O32: 283 | P32: =SUM(K32:N32)-O32 -> 0 | Q32: Desconto concedido devido a marca ter cancelado a filial em setembro e ter sido cobrado por dois meses. cobrar em 02/2025 | R32: 15 | S32: 04 | T32: 23333642000108 | U32: SCERA = SCERA MODA FEMININA LTDA
A33: 01/2026 | B33: 43649 | C33: ok | D33: Atta | E33: Fama Fashion | F33: Vesti (Assinatura) | G33: Essencial | I33: 283 | K33: 283 | P33: =SUM(K33:N33)-O33 -> 283 | R33: 20 | S33: 04 | T33: 54451398000101 | U33: FAMA FASHION = FAMA FASHION CREACOES LTDA
A34: 01/2026 | B34: 43649 | C34: ok | D34: VESTI | E34: Paloma Concept | F34: Vesti (Assinatura) | G34: Essencial | I34: 283 | K34: 283 | P34: =SUM(K34:N34)-O34 -> 283 | R34: 15 | S34: 04 | T34: 16579598000155 | U34: PALOMA CONCEPT = FABIO DE ARAUJO LIMA FERREIRA EIRELI
A35: 01/2026 | B35: 43656 | C35: ok | D35: Atta | E35: Cheers | F35: Vesti (Assinatura) | G35: Profissional | I35: 1179 | K35: 1179 | P35: =SUM(K35:N35)-O35 -> 1179 | R35: 11 | S35: 04 | T35: 53659785000175 | U35: CHEERS = MODAS VISION LTDA
A36: 01/2026 | B36: 43656 | C36: ok | D36: Atta | E36: Fesperamor | F36: Vesti (Assinatura) | G36: Profissional | I36: 1179 | K36: 1179 | P36: =SUM(K36:N36)-O36 -> 1179 | R36: 15 | S36: 04 | T36: 22015485000120 | U36: FESPERAMOR = JEH CONFECCOES LTDA
A37: 01/2026 | B37: 43675 | C37: ok | D37: Atta | E37: Quebela | F37: Vesti (Assinatura) | G37: Essencial | I37: 425 | K37: 425 | N37: 369 | P37: =SUM(K37:N37)-O37 -> 794 | R37: 20 | S37: 04 | T37: 58525007000107 | U37: QUEBELA = CONFECCOES QUEBELA LTDA
A38: 01/2026 | B38: 43684 | D38: Atta | E38: Genesis Jeans | F38: Vesti (Assinatura) | G38: Essencial | I38: 283 | K38: 283 | P38: =SUM(K38:N38)-O38 -> 283 | R38: 15 | S38: 04 | T38: 21352130000163 | U38: GENESIS JEANS = GENESIS JEANS LTDA
A39: 01/2026 | B39: 43713 | D39: Vesti | E39: AMISKA - MISS MILLIE | F39: Vesti (Assinatura) | G39: Essencial | I39: 303 | K39: 303 | P39: =SUM(K39:N39)-O39 -> 303 | R39: 15 | S39: 04 | T39: 24721940000138 | U39: AMISKA MISS MILLIE = CONFECCOES MISS MILLIE INDUSTRIA E COMERCIO DE ROUPAS LTDA EPP
A40: 01/2026 | B40: 43718 | D40: VESTI | E40: Join Curves | F40: Vesti (Assinatura) | G40: Avançado | I40: 486 | K40: 486 | M40: 1000 | N40: 600 | P40: =SUM(K40:N40)-O40 -> 2086 | R40: 28 | S40: 04 | T40: 07867580000168 | U40: Join Curves = JULIA A H INDUSTRIA E COMERCIO DE ROUPAS LTDA
A41: 01/2026 | B41: 43719 | D41: Atta | E41: Namine | F41: Vesti (Assinatura) | G41: Profissional | I41: 1005 | K41: 1005 | N41: =266+900 -> 1166 | P41: =SUM(K41:N41)-O41 -> 2171 | R41: 15 | S41: 04 | T41: 17820490000256 | U41: NAMINE = NAMINE CONFECCOES LTDA
A42: 01/2026 | B42: 43731 | D42: VESTI | E42: Diamantes | F42: Vesti (Assinatura) | G42: Profissional | I42: 1400 | K42: 1400 | N42: =38*161.95+5 -> 6159.1 | P42: =SUM(K42:N42)-O42 -> 7559.1 | R42: 15 | S42: 04 | T42: 13649755000163 | U42: DIAMANTES = DIAMANTES LINGERIE LTDA
A43: 01/2026 | B43: 43738 | D43: Atta | E43: Lily Daisy | F43: Vesti (Assinatura) | G43: Essencial | I43: 283 | K43: 283 | P43: =SUM(K43:N43)-O43 -> 283 | R43: 15 | S43: 04 | T43: 34500000000172 | U43: LILY DAISY = ATELIER LILY DAISY CONFECCOES LTDA
A44: 01/2026 | B44: 43745 | D44: VESTI | E44: Ana Gonçalves Tricot = Luis Guilherme | F44: Vesti (Assinatura) | G44: Profissional | I44: 1179 | K44: 1179 | N44: 598 | P44: =SUM(K44:N44)-O44 -> 1777 | R44: 15 | S44: 04 | T44: 11582787000163 | U44: Ana Goncalves Tricot = LUIS GUILHERME GONCALVES LEMES EIRELI
A45: 01/2026 | B45: 43755 | D45: Atta | E45: Delight | F45: Vesti (Assinatura) | G45: Essencial | I45: 283 | K45: 283 | P45: =SUM(K45:N45)-O45 -> 283 | R45: 15 | S45: 04 | T45: 21520947000101 | U45: DELIGHT = DELIGHT MODA FEMININA LTDA
A46: 01/2026 | B46: 43755 | D46: Atta | E46: Sori | F46: Vesti (Assinatura) | G46: Profissional | I46: 1179 | K46: 1179 | P46: =SUM(K46:N46)-O46 -> 1179 | R46: 15 | S46: 04 | T46: 06987979000110 | U46: SORI = C. S. CHOI MODAS
A47: 01/2026 | B47: 43768 | D47: Atta | E47: Mx | F47: Vesti (Assinatura) | G47: Profissional | I47: 1179 | K47: 1179 | P47: =SUM(K47:N47)-O47 -> 1179 | R47: 20 | S47: 04 | T47: 05888414000112 | U47: MX = CREACOES MX FASHION LTDA
A48: 01/2026 | B48: 43774 | D48: Atta | E48: Donna Ritz | F48: Vesti (Assinatura) | G48: Profissional | I48: 1076.67 | K48: 1076.67 | P48: =SUM(K48:N48)-O48 -> 1076.67 | R48: 15 | S48: 04 | T48: 19521267000152 | U48: DONNA RITZ = RITZ FASHION CONFECCOES EIRELI EPP
A49: 01/2026 | B49: 43802 | D49: VESTI | E49: Vida Bela | F49: Vesti (Assinatura) | G49: Essencial | I49: 283 | K49: 283 | P49: =SUM(K49:N49)-O49 -> 283 | R49: 15 | S49: 04 | T49: 45668696000167 | U49: VIDA BELA = SAMIR ABRAO BASSITT E CIA LTDA
A50: 01/2026 | B50: 43846 | D50: Atta | E50: Sedanbi | F50: Vesti (Assinatura) | G50: Essencial | I50: 283 | K50: 283 | P50: =SUM(K50:N50)-O50 -> 283 | R50: 15 | S50: 04 | T50: 00238342000306 | U50: SEDANBI = COMERCIO E CONFECCOES DE ROUPAS S H EIRELI
A51: 01/2026 | B51: 43861 | D51: VESTI | E51: Rafa Brasil | F51: Vesti (Assinatura) | G51: Essencial | I51: 283 | K51: 283 | P51: =SUM(K51:N51)-O51 -> 283 | R51: 15 | S51: 04 | T51: 30827010000166 | U51: RAFA BRASIL = EDUARDO FERREIRA MARQUES 06879922651
A52: 01/2026 | B52: 43867 | D52: Atta | E52: Elae | F52: Vesti (Assinatura) | G52: Avançado | I52: 425 | K52: 425 | P52: =SUM(K52:N52)-O52 -> 425 | R52: 20 | S52: 04 | T52: 46924221000157 | U52: ELAE = CONFECCOES GERACAO ELAE LTDA
A53: 01/2026 | B53: 43878 | D53: Atta | E53: As Marias | F53: Vesti (Assinatura) | G53: Essencial | I53: 283 | K53: 283 | P53: =SUM(K53:N53)-O53 -> 283 | R53: 15 | S53: 04 | T53: 24487541000154 | U53: As Marias = ELSA MARIA DA SILVA SOUZA
A54: 01/2026 | B54: 43888 | D54: VESTI | E54: Suzan Zheng | F54: Vesti (Assinatura) | G54: Essencial | I54: 283 | K54: 283 | P54: =SUM(K54:N54)-O54 -> 283 | R54: 15 | S54: 04 | T54: 26551251000158 | U54: SUZAN ZHENG = Z COMERCIO DE ROUPAS EIRELI
A55: 01/2026 | B55: 43892 | D55: VESTI | E55: Gliss Jeans | F55: Vesti (Assinatura) | G55: Essencial | I55: 283 | K55: 283 | N55: 199 | P55: =SUM(K55:N55)-O55 -> 482 | R55: 11 | S55: 04 | T55: 55251292001107 | U55: GLISS JEANS = JURRO INDUSTRIA E COMERCIO DE CONFECCOES LTDA
A56: 01/2026 | B56: 43903 | D56: VESTI | E56: Bauarte | F56: Vesti (Assinatura) | G56: Avançado | I56: 1231 | K56: 1231 | L56: 350 | P56: =SUM(K56:N56)-O56 -> 1581 | R56: 20 | S56: 04 | T56: 08754784000155 | U56: BAUARTE = JP MONTEIRO ACESSORIOS DA MODA LTDA
A57: 01/2026 | B57: 43920 | D57: Atta | E57: Alcance Jeans | F57: Vesti (Assinatura) | G57: Profissional | I57: 1243.35 | K57: 1243.35 | N57: 250 | P57: =SUM(K57:N57)-O57 -> 1493.35 | R57: 11 | S57: 04 | T57: 34411241000145 | U57: ALCANCE JEANS = ALC INDUSTRIA E COMERCIO DE ROUPAS LTDA
A58: 01/2026 | B58: 43943 | D58: VESTI | E58: Sanreed | F58: Vesti (Assinatura) | G58: Essencial | I58: 283 | K58: 283 | N58: 359 | P58: =SUM(K58:N58)-O58 -> 642 | R58: 15 | S58: 04 | T58: 23735214000292 | U58: Sanreed = WIBE CONFECCOES EIRELI
A59: 01/2026 | B59: 43949 | D59: VESTI | E59: Vigor Basic | F59: Vesti (Assinatura) | G59: Essencial | I59: 283 | K59: 283 | P59: =SUM(K59:N59)-O59 -> 283 | R59: 11 | S59: 04 | T59: 07085032000186 | U59: Vigor Basic = VIGOR TOTAL INDUSTRIA E COMERCIO DO VESTUARIO LTDA
A60: 01/2026 | B60: 43950 | D60: VESTI | E60: Manaca= Visuh | F60: Vesti (Assinatura) | G60: Profissional | I60: 1179 | K60: 1179 | P60: =SUM(K60:N60)-O60 -> 1179 | R60: 20 | S60: 04 | T60: 22221114000102 | U60: MANACA = VISUH CONFECCOES LTDA EPP
A61: 01/2026 | B61: 43955 | D61: Atta | E61: Bokeh | F61: Vesti (Assinatura) | G61: Avançado | I61: 425 | K61: 425 | P61: =SUM(K61:N61)-O61 -> 425 | R61: 20 | S61: 04 | T61: 28489878000232 | U61: BOKEH = CONFECCOES CHESED LTDA EPP
A62: 01/2026 | B62: 43958 | D62: Atta | E62: Hanabee | F62: Vesti (Assinatura) | G62: Avançado | I62: 425 | K62: 425 | P62: =SUM(K62:N62)-O62 -> 425 | R62: 20 | S62: 04 | T62: 12395643000160 | U62: HANABEE = ESLEE CONFECCOES LTDA EPP
A63: 01/2026 | B63: 43958 | C63: ok | D63: Atta | E63: Innocence | F63: Vesti (Assinatura) | G63: Avançado | I63: 835 | K63: 835 | L63: 250 | P63: =SUM(K63:N63)-O63 -> 1085 | R63: 15 | S63: 04 | T63: 17258262000153 | U63: INNOCENCE = SUN JOO KIM CONFECCOES
A64: 01/2026 | B64: 43962 | D64: VESTI | E64: Cris Fael | F64: Vesti (Assinatura) | G64: Avançado | I64: 425 | K64: 425 | P64: =SUM(K64:N64)-O64 -> 425 | R64: 15 | S64: 04 | T64: 52341858000113 | U64: CRIS FAEL = CRISFAEL COMERCIO DE ACESSORIOS DA MODA LTDA
A65: 01/2026 | B65: 43965 | D65: Atta | E65: Caroll | F65: Vesti (Assinatura) | G65: Avançado | I65: 665 | K65: 665 | P65: =SUM(K65:N65)-O65 -> 665 | R65: 11 | S65: 04 | T65: 02683338000110 | U65: CAROLL COLLECTION = CAROLL CONFECCOES IMPORTACAO E EXPORTACAO LTDA
A66: 01/2026 | B66: 43965 | D66: Atta | E66: Kalli | F66: Vesti (Assinatura) | G66: Avançado | I66: 698 | K66: 698 | P66: =SUM(K66:N66)-O66 -> 698 | R66: 11 | S66: 04 | T66: 17685726000108 | U66: Kalli = CONFECCOES KALLI LTDA
A67: 01/2026 | B67: 43965 | D67: Atta | E67: Sexy Cookie | F67: Vesti (Assinatura) | G67: Profissional | I67: 1179 | K67: 1179 | P67: =SUM(K67:N67)-O67 -> 1179 | R67: 11 | S67: 04 | T67: 08151457000109 | U67: Sexy Cookie = SEXY COOKIE CONFECCOES LTDA
A68: 01/2026 | B68: 43966 | D68: VESTI | E68: Adizza | F68: Vesti (Assinatura) | G68: Essencial | I68: 283 | K68: 283 | N68: 410 | P68: =SUM(K68:N68)-O68 -> 693 | R68: 15 | S68: 04 | T68: 24881140000184 | U68: ADIZZA = PAULO CESAR VALERIANO SILVA
A69: 01/2026 | B69: 43966 | D69: VESTI | E69: Anahi | F69: Vesti (Assinatura) | G69: Avançado | I69: 425 | K69: 425 | P69: =SUM(K69:N69)-O69 -> 425 | R69: 20 | S69: 04 | T69: 04049767000166 | U69: Anahi = ALTA MUN BIANCA CONFECCOES LTDA EPP
A70: 01/2026 | B70: 43972 | D70: Atta | E70: Ezee | F70: Vesti (Assinatura) | G70: Essencial | I70: 342.67 | K70: 342.67 | P70: =SUM(K70:N70)-O70 -> 342.67 | R70: 15 | S70: 04 | T70: 28314192000120 | U70: EZEE = EZEE CONFECCOES DE ROUPAS EIRELI
A71: 01/2026 | B71: 43978 | D71: Atta | E71: Nakepe | F71: Vesti (Assinatura) | G71: Avançado | I71: 425 | K71: 425 | P71: =SUM(K71:N71)-O71 -> 425 | R71: 22 | S71: 04 | T71: 00764187000108 | U71: NAKEPE = NAKEPE CREACOES LTDA
A72: 01/2026 | B72: 43978 | D72: Atta | E72: Ste Fashion | F72: Vesti (Assinatura) | G72: Avançado | I72: 425 | K72: 425 | P72: =SUM(K72:N72)-O72 -> 425 | R72: 15 | S72: 04 | T72: 12648298000120 | U72: STE FASHION = CHOCO'S ARTIGOS DO VESTUARIO EIRELI
A73: 01/2026 | B73: 43979 | D73: Atta | E73: Lilian Plus | F73: Vesti (Assinatura) | G73: Avançado | I73: 425 | K73: 425 | P73: =SUM(K73:N73)-O73 -> 425 | R73: 15 | S73: 04 | T73: 51200947000187 | U73: Lilian Plus = CONFECCOES LILIAN LTDA
A74: 01/2026 | B74: 43983 | D74: VESTI | E74: Blubetty | F74: Vesti (Assinatura) | G74: Profissional | I74: 1330 | K74: 1330 | L74: 350 | P74: =SUM(K74:N74)-O74 -> 1680 | R74: 15 | S74: 04 | T74: 01102343000120 | U74: Blubetty = KAPITON CONFECCOES LTDA
A75: 01/2026 | B75: 43983 | D75: VESTI | E75: Di Collani | F75: Vesti (Assinatura) | G75: Profissional | I75: 2110.33 | K75: 2110.33 | L75: 500 | P75: =SUM(K75:N75)-O75 -> 2610.33 | R75: 11 | S75: 04 | T75: 01102343000120 | U75: Di Collani = KAPITON CONFECCOES LTDA
A76: 01/2026 | B76: 43983 | D76: VESTI | E76: Jeanseria | F76: Vesti (Assinatura) | G76: Profissional | I76: 405 | K76: 405 | L76: 350 | P76: =SUM(K76:N76)-O76 -> 755 | R76: 11 | S76: 04 | T76: 01102343000120 | U76: Jeanseria = KAPITON CONFECCOES LTDA
A77: 01/2026 | B77: 43984 | D77: Atta | E77: Coqueta | F77: Vesti (Assinatura) | G77: Avançado | I77: 472.33 | K77: 472.33 | N77: 380 | P77: =SUM(K77:N77)-O77 -> 852.33 | R77: 11 | S77: 04 | T77: 58687526000171 | U77: Coqueta = CONFECCOES COQUETA LTDA
A78: 01/2026 | B78: 43986 | D78: Atta | E78: Clio | F78: Vesti (Assinatura) | G78: Avançado | I78: 425 | K78: 425 | P78: =SUM(K78:N78)-O78 -> 425 | R78: 15 | S78: 04 | T78: 05550677000117 | U78: Clio = CLIO CONFECCOES IMPORTACAO E EXPORTACAO LTDA
A79: 01/2026 | B79: 43986 | D79: Atta | E79: Planchet | F79: Vesti (Assinatura) | G79: Avançado | I79: 425 | K79: 425 | P79: =SUM(K79:N79)-O79 -> 425 | R79: 15 | S79: 04 | T79: 03243396000196 | U79: Planchet = CONFECCOES PLANCHET EIRELI
A80: 01/2026 | B80: 43990 | D80: Atta | E80: Bestié | F80: Vesti (Assinatura) | G80: Avançado | I80: 425 | K80: 425 | P80: =SUM(K80:N80)-O80 -> 425 | R80: 12 | S80: 04 | T80: 50751845000197 | U80: Bestie = CONFECCOES BESTIE LTDA
A81: 01/2026 | B81: 43992 | D81: VESTI | E81: Monclos | F81: Vesti (Assinatura) | G81: Avançado | I81: 426.33 | K81: 426.33 | P81: =SUM(K81:N81)-O81 -> 426.33 | R81: 11 | S81: 04 | T81: 59812453000246 | U81: Monclos = CAN FLOW CONFECCOES LTDA
A82: 01/2026 | B82: 43994 | D82: Atta | E82: Moirai | F82: Vesti (Assinatura) | G82: Avançado | I82: 452.67 | K82: 452.67 | P82: =SUM(K82:N82)-O82 -> 452.67 | R82: 15 | S82: 04 | T82: 29380107000194 | U82: MOIRAI = MOIRAI CONFECCAO DE ROUPAS EIRELI
A83: 01/2026 | B83: 44000 | D83: Atta | E83: Noir | F83: Vesti (Assinatura) | G83: Avançado | I83: 425 | K83: 425 | P83: =SUM(K83:N83)-O83 -> 425 | R83: 15 | S83: 04 | T83: 02415964000126 | U83: Noir = CONFECCOES NOIR LTDA
A84: 01/2026 | B84: 44006 | D84: Atta | E84: French Kiss | F84: Vesti (Assinatura) | G84: Avançado | I84: 457 | K84: 457 | P84: =SUM(K84:N84)-O84 -> 457 | R84: 15 | S84: 04 | T84: 65977878000127 | U84: French Kiss = GUARNIERIUS MODAS LTDA
A85: 01/2026 | B85: 44006 | D85: VESTI | E85: Wool Line | F85: Vesti (Assinatura) | G85: Avançado | I85: 425 | K85: 425 | P85: =SUM(K85:N85)-O85 -> 425 | R85: 11 | S85: 04 | T85: 23398902000123 | U85: Wool Line = WOOL LINE CONFECCOES EIRELI
A86: 01/2026 | B86: 44007 | D86: VESTI | E86: Amofany | F86: Vesti (Assinatura) | G86: Profissional | I86: 1179 | K86: 1179 | L86: 350 | P86: =SUM(K86:N86)-O86 -> 1529 | R86: 15 | S86: 04 | T86: 09657596000171 | U86: AMOFANY = Mabli confeccoes de roupas LTDA EPP
A87: 01/2026 | B87: 44008 | D87: VESTI | E87: Four One | F87: Vesti (Assinatura) | G87: Avançado | I87: 425 | K87: 425 | N87: 359 | P87: =SUM(K87:N87)-O87 -> 784 | R87: 15 | S87: 04 | T87: 55646228000145 | U87: Four One Jeans = FOUR ONE INDUSTRIA E COMERCIO EIRELI
A88: 01/2026 | B88: 44008 | D88: VESTI | E88: Peri Plus Size | F88: Vesti (Assinatura) | G88: Avançado | I88: 425 | K88: 425 | P88: =SUM(K88:N88)-O88 -> 425 | R88: 15 | S88: 04 | T88: 41090419000169 | U88: Peri Plus Size = MODAS PERI LTDA
A89: 01/2026 | B89: 44013 | C89: ok | D89: Atta | E89: Vitral | F89: Vesti (Assinatura) | G89: Profissional | I89: 1179 | K89: 1179 | P89: =SUM(K89:N89)-O89 -> 1179 | R89: 20 | S89: 04 | T89: 13578271000170 | U89: VITRAL = J Y KIM CONFECCOES LTDA
A90: 01/2026 | B90: 44014 | C90: ok | D90: Atta | E90: Seiss & Deiss | F90: Vesti (Assinatura) | G90: Essencial | I90: 364.67 | K90: 364.67 | P90: =SUM(K90:N90)-O90 -> 364.67 | R90: 15 | S90: 04 | T90: 17685722000120 | U90: SEISS & DEISS = DEISS CONFECCOES EIRELI
A91: 01/2026 | B91: 44015 | D91: VESTI | E91: Buccanes | F91: Vesti (Assinatura) | G91: Essencial | I91: 283 | K91: 283 | P91: =SUM(K91:N91)-O91 -> 283 | R91: 15 | S91: 04 | T91: 55251292000127 | U91: BUCCANES = JURRO INDUSTRIA E COMERCIO DE CONFECCOES LTDA
A92: 01/2026 | B92: 44017 | C92: ok | D92: Atta | E92: Hirus | F92: Vesti (Assinatura) | G92: Avançado | I92: 509 | K92: 509 | P92: =SUM(K92:N92)-O92 -> 509 | R92: 15 | S92: 04 | T92: 07752324000206 | U92: HIRUS = CONFECCOES BONDADE LTDA
A93: 01/2026 | B93: 44020 | D93: Atta | E93: Rubicon | F93: Vesti (Assinatura) | G93: Avançado | I93: 425 | K93: 425 | P93: =SUM(K93:N93)-O93 -> 425 | R93: 15 | S93: 04 | T93: 24002700000183 | U93: RUBICON = RUBICON MODAS LTDA
A94: 01/2026 | B94: 44021 | D94: VESTI | E94: Lorsa | F94: Vesti (Assinatura) | G94: Avançado | I94: 425 | K94: 425 | P94: =SUM(K94:N94)-O94 -> 425 | R94: 22 | S94: 04 | T94: 46046876000170 | U94: LORSA = L ORSA MODAS E CONFECCOES LTDA
A95: 01/2026 | B95: 44025 | C95: ok | D95: VESTI | E95: Equivoco | F95: Vesti (Assinatura) | G95: Avançado | I95: 425 | K95: 425 | P95: =SUM(K95:N95)-O95 -> 425 | R95: 22 | S95: 04 | T95: 46046876000927 | U95: Equivoco Jeans = L ORSA MODAS E CONFECCOES LTDA
A96: 01/2026 | B96: 44027 | C96: ok | D96: Atta | E96: Acqua Marine | F96: Vesti (Assinatura) | G96: Avançado | I96: 509 | K96: 509 | P96: =SUM(K96:N96)-O96 -> 509 | R96: 20 | S96: 04 | T96: 56353866000130 | U96: ACQUA MARINE = SJLEE CONFECCOES ME
A97: 01/2026 | B97: 44032 | C97: ok | D97: VESTI | E97: Lupim Camisaria | F97: Vesti (Assinatura) | G97: Avançado | I97: 509 | K97: 509 | P97: =SUM(K97:N97)-O97 -> 509 | R97: 15 | S97: 04 | T97: 92302520000177 | U97: Lupim Camisaria = LUPIM INDUSTRIA E COMERCIO DO VESTUARIO LTDA
A98: 01/2026 | B98: 44033 | C98: ok | D98: Atta | E98: Bem me quer | F98: Vesti (Assinatura) | G98: Avançado | I98: 453 | K98: 453 | P98: =SUM(K98:N98)-O98 -> 453 | R98: 20 | S98: 04 | T98: 22905439000287 | U98: BEM ME QUER = E T LEE CONFECOES EPP
A99: 01/2026 | B99: 44034 | C99: ok | D99: VESTI | E99: Ina Modas | F99: Vesti (Assinatura) | G99: Essencial | I99: 340 | K99: 340 | P99: =SUM(K99:N99)-O99 -> 340 | R99: 15 | S99: 04 | T99: 55832331000180 | U99: Ina Modas = CONFECCOES S TELLES LTDA
A100: 01/2026 | B100: 44039 | C100: ok | D100: VESTI | E100: Sheslaine Brand | F100: Vesti (Assinatura) | G100: Avançado | I100: 509 | K100: 509 | P100: =SUM(K100:N100)-O100 -> 509 | R100: 15 | S100: 04 | T100: 03586007000125 | U100: Sheslaine Brand = SG DE ANDRADE CONFECCOES
...

Sheet Starter 032026
A1: Fat.2026 | B1: ANIVERSÁRIO | C1: CANAL/Agência | D1: MARCA | E1: Subconta | F1: PLANO | G1: SETUP | H1: MENSALIDADE INICIAL | I1: VALOR REAJUSTE | J1: MENSALIDADE | K1: INTEGRAÇÃO | L1: ASSISTENTE | M1: FILIAL | N1: DESCONTOS | O1: TOTAL COBRADO | P1: OBSERVAÇÕES | Q1: CPF e CNPJ | R1: Mês de Reajuste
A2: 03/2026 | B2: 45259 | C2: Zoom- Cardume | D2: WA Baby | E2: Vesti (Cartão) | F2: Vesti Light | G2: 0 | H2: 317 | J2: =H2+I2 -> 317 | O2: =SUM(J2:M2)-N2 -> 317 | R2: =MONTH(B2) -> 11
A3: 03/2026 | B3: 45307 | C3: Vesti - Glads | D3: Levitheo | E3: Vesti (Cartão) | F3: Vesti Light | G3: 249 | H3: 267 | J3: 285 | O3: =SUM(J3:M3)-N3 -> 285 | R3: 01
A4: 03/2026 | B4: 45315 | C4: Sete | D4: Donna Stella | E4: Vesti (Cartão) | F4: Vesti Light | G4: 249 | H4: 267 | J4: 285 | O4: =SUM(J4:M4)-N4 -> 285 | R4: 01
A5: 03/2026 | B5: 45320 | C5: VESTI | D5: Nadri | E5: Vesti (Cartão) | F5: Vesti Light | G5: 249 | H5: 267 | J5: 285 | O5: =SUM(J5:M5)-N5 -> 285 | R5: 01
A6: 03/2026 | B6: 45323 | C6: Zoom- Cardume | D6: GO Padel | E6: Vesti (Cartão) | F6: Vesti Light | G6: 249 | H6: 285 | J6: 285 | O6: =SUM(J6:M6)-N6 -> 285 | R6: 02
A7: 03/2026 | B7: 45323 | C7: Vesti - Glads | D7: Kroft Oficial | E7: Vesti (Cartão) | F7: Vesti Light | G7: 249 | H7: 285 | J7: 285 | O7: =SUM(J7:M7)-N7 -> 285 | R7: 02
A8: 03/2026 | B8: 45337 | C8: Zoom- Cardume | D8: Divas Vero | E8: Vesti (Cartão) | F8: Vesti Light | G8: 249 | H8: 285 | J8: 285 | O8: =SUM(J8:M8)-N8 -> 285 | R8: 02
A9: 03/2026 | B9: 45342 | C9: Vesti - ProRoi | D9: Repete Conf | E9: Vesti (Cartão) | F9: Vesti Light | G9: 249 | H9: 285 | J9: 285 | O9: =SUM(J9:M9)-N9 -> 285 | R9: 02
A10: 03/2026 | B10: 45352 | C10: Sete | D10: Monnika Marikinha Brand | E10: Vesti (Cartão) | F10: Vesti Light | G10: 249 | H10: 249 | J10: 267 | O10: =SUM(J10:M10)-N10 -> 267 | R10: =MONTH(B10) -> 3
A11: 03/2026 | B11: 45352 | C11: Vesti - ProRoi | D11: RED ROCK (R) | E11: ProRoi | F11: Vesti Light | G11: 249 | H11: 249 | J11: 267 | O11: =SUM(J11:M11)-N11 -> 267 | P11: Redline | Q11: 18.623.259.0001-54 | R11: =MONTH(B11) -> 3
A12: 03/2026 | B12: 45379 | C12: Zoom- Cardume | D12: RL Modas | E12: Vesti (Cartão) | F12: Vesti Light | G12: 249 | H12: 249 | J12: 267 | O12: =SUM(J12:M12)-N12 -> 267 | R12: =MONTH(B12) -> 3
A13: 03/2026 | B13: 45393 | C13: Vesti - Tizzefy | D13: Aline Confecções | E13: Vesti (Cartão) | F13: Vesti Light | G13: 249 | H13: 267 | J13: 267 | O13: =SUM(J13:M13)-N13 -> 267 | R13: =MONTH(B13) -> 4
A14: 03/2026 | B14: 45411 | C14: Vesti - Tizzefy | D14: Igmar | E14: Vesti (Cartão) | F14: Vesti Light | G14: 249 | H14: 267 | J14: 267 | O14: =SUM(J14:M14)-N14 -> 267 | R14: =MONTH(B14) -> 4
A15: 03/2026 | B15: 45425 | C15: Vesti - ProRoi | D15: Bella Fe | E15: Vesti (Cartão) | F15: Vesti Light | G15: 249 | H15: 267 | J15: 267 | O15: =SUM(J15:M15)-N15 -> 267 | R15: =MONTH(B15) -> 5
A16: 03/2026 | B16: 45446 | C16: VESTI | D16: Lupus Wear | E16: Vesti Light | F16: Vesti Light | G16: 249 | H16: 267 | J16: 267 | O16: =SUM(J16:M16)-N16 -> 267 | R16: =MONTH(B16) -> 6
A17: 03/2026 | B17: 45448 | C17: Zoom- Cardume | D17: Felps Confecções | E17: Vesti Light | F17: Vesti Light | G17: 0 | H17: 267 | J17: 267 | O17: =SUM(J17:M17)-N17 -> 267 | R17: =MONTH(B17) -> 6
A18: 03/2026 | B18: 45457 | C18: Vesti - Tizzefy | D18: MINOLLI | E18: Vesti - Tizzefy | F18: Vesti Light | G18: 249 | H18: 267 | J18: 267 | O18: =SUM(J18:M18)-N18 -> 267 | R18: =MONTH(B18) -> 6
A19: 03/2026 | B19: 45462 | C19: VESTI | D19: Urban Race | E19: Vesti Light | F19: Vesti Light | G19: 299 | H19: 317 | J19: 317 | O19: =SUM(J19:M19)-N19 -> 317 | R19: =MONTH(B19) -> 6
A20: 03/2026 | B20: 45462 | C20: VESTI | D20: Planet Charm | E20: Vesti Light | F20: Vesti Light | G20: 299 | H20: 317 | J20: 317 | O20: =SUM(J20:M20)-N20 -> 317 | R20: =MONTH(B20) -> 6
A21: 03/2026 | B21: 45489 | C21: Vê Vantagens | D21: PEROLA ORIENTAL LK&D | E21: Vê Vantagens | F21: Vesti Light | G21: 249 | H21: 267 | J21: 267 | O21: =SUM(J21:M21)-N21 -> 267 | R21: =MONTH(B21) -> 7
A22: 03/2026 | B22: 45498 | C22: VESTI | D22: IZZA PVH | E22: Vesti Multimarcas | F22: Vesti Multimarca | G22: 99 | H22: 99 | J22: 99 | O22: =SUM(J22:M22)-N22 -> 99 | Q22: 31506519000170 | R22: =MONTH(B22) -> 7
A23: 03/2026 | B23: 45500 | C23: Vesti - ProRoi | D23: BegKids | E23: Vesti - ProRoi | F23: Vesti Light | G23: 299 | H23: 317 | J23: 317 | O23: =SUM(J23:M23)-N23 -> 317 | R23: =MONTH(B23) -> 7
A24: 03/2026 | B24: 45501 | C24: VESTI | D24: Agridoce | E24: Vesti Light | F24: Vesti Light | G24: 699 | H24: 299 | J24: 299 | O24: =SUM(J24:M24)-N24 -> 299 | R24: =MONTH(B24) -> 7
A25: 03/2026 | B25: 45505 | C25: VESTI | D25: Arary | E25: Vesti Light | F25: Vesti Light | G25: 299 | H25: 317 | J25: 317 | O25: =SUM(J25:M25)-N25 -> 317 | R25: =MONTH(B25) -> 8
A26: 03/2026 | B26: 45506 | C26: Vê Vantagens | D26: Aurami | E26: Vê Vantagens | F26: Vesti Light | G26: 299 | H26: 317 | J26: 317 | O26: =SUM(J26:M26)-N26 -> 317 | R26: =MONTH(B26) -> 8
A27: 03/2026 | B27: 45509 | C27: VESTI | D27: Valentina Fashion | E27: Vesti Multimarcas | F27: Vesti Multimarca | G27: 99 | H27: 117 | J27: 117 | N27: 18 | O27: =SUM(J27:M27)-N27 -> 99 | Q27: 39554207000143 | R27: =MONTH(B27) -> 8
A28: 03/2026 | B28: 45506 | C28: VESTI | D28: TNT Moda Fitness | E28: Vesti Light | F28: Vesti Light | G28: 299 | H28: 317 | J28: 317 | O28: =SUM(J28:M28)-N28 -> 317 | R28: =MONTH(B28) -> 8
A29: 03/2026 | B29: 45519 | C29: Vê Vantagens | D29: PEROLA ORIENTAL = M&K | E29: Vê Vantagens | F29: Vesti Light | G29: 299 | H29: 267 | J29: 267 | O29: =SUM(J29:M29)-N29 -> 267 | R29: =MONTH(B29) -> 8
A30: 03/2026 | B30: 45532 | C30: VESTI | D30: Lado Doce | E30: Vesti Light | F30: Vesti Light | G30: 800 | H30: 317 | J30: 317 | O30: =SUM(J30:M30)-N30 -> 317 | R30: =MONTH(B30) -> 8
A31: 03/2026 | B31: 45533 | C31: VESTI | D31: Espaço Berta | E31: Vesti Multimarcas | F31: Vesti Multimarca | G31: 99 | H31: 99 | J31: 99 | O31: =SUM(J31:M31)-N31 -> 99 | Q31: 25225294120 | R31: =MONTH(B31) -> 8
A32: 03/2026 | B32: 45533 | C32: VESTI | D32: A Rouparia | E32: Vesti Multimarcas | F32: Vesti Multimarca | G32: 99 | H32: 117 | J32: 117 | O32: =SUM(J32:M32)-N32 -> 117 | Q32: 32979501000158 | R32: =MONTH(B32) -> 8
A33: 03/2026 | B33: 45539 | C33: VESTI | D33: Drika Confeccoes | E33: Vesti Light | F33: Vesti Light | G33: 800 | H33: 317 | J33: 317 | O33: =SUM(J33:M33)-N33 -> 317 | R33: =MONTH(B33) -> 9
A34: 03/2026 | B34: 45539 | C34: Vesti - Tizzefy | D34: VLY JEANS | E34: Vesti - Tizzefy | F34: Vesti Light | G34: 800 | H34: 267 | J34: 267 | O34: =SUM(J34:M34)-N34 -> 267 | R34: =MONTH(B34) -> 9
A35: 03/2026 | B35: 45539 | C35: VESTI | D35: Veste Vegana | E35: Vesti Light | F35: Vesti Light | G35: 249 | H35: 267 | J35: 267 | O35: =SUM(J35:M35)-N35 -> 267 | R35: =MONTH(B35) -> 9
A36: 03/2026 | B36: 45541 | C36: VESTI | D36: Dominio​ Conceito | E36: Vesti Light | F36: Vesti Light | G36: =800+299 -> 1099 | H36: 317 | J36: 317 | O36: =SUM(J36:M36)-N36 -> 317 | R36: =MONTH(B36) -> 9
A37: 03/2026 | B37: 45547 | C37: VESTI | D37: Alice Amaral Brand Store | E37: Vesti Multimarcas | F37: Vesti Multimarca | G37: 99 | H37: 99 | J37: 99 | O37: =SUM(J37:M37)-N37 -> 99 | Q37: 30707302000165 | R37: =MONTH(B37) -> 9
A38: 03/2026 | B38: 45548 | C38: VESTI | D38: Julia Andrade Bijuterias​ | E38: Vesti Light | F38: Vesti Light | G38: 299 | H38: 317 | J38: 317 | O38: =SUM(J38:M38)-N38 -> 317 | R38: =MONTH(B38) -> 9
A39: 03/2026 | B39: 45548 | C39: VESTI | D39: Little Star | E39: Vesti Light | F39: Vesti Light | G39: 299 | H39: 317 | J39: 317 | O39: =SUM(J39:M39)-N39 -> 317 | R39: =MONTH(B39) -> 9
A40: 03/2026 | B40: 45509 | C40: VESTI | D40: Chocoberry | E40: Vesti Light | F40: Vesti Light | G40: 299 | H40: 317 | J40: 317 | O40: =SUM(J40:M40)-N40 -> 317 | R40: =MONTH(B40) -> 8
A41: 03/2026 | B41: 45553 | C41: VESTI | D41: Lado Doce | E41: Vesti Light | F41: Assistente | G41: 300 | L41: 300 | O41: =SUM(J41:M41)-N41 -> 300 | R41: =MONTH(B41) -> 9
A42: 03/2026 | B42: 45554 | C42: VESTI | D42: New Gomone | E42: Vesti Light | F42: Vesti Light | G42: 299 | H42: 317 | J42: 317 | O42: =SUM(J42:M42)-N42 -> 317 | R42: =MONTH(B42) -> 9
A43: 03/2026 | B43: 45558 | C43: VESTI | D43: New Mire Aviamentos | E43: Vesti Light | F43: Vesti Light | G43: 299 | H43: 317 | J43: 317 | L43: 149 | O43: =SUM(J43:M43)-N43 -> 466 | R43: =MONTH(B43) -> 9
A44: 03/2026 | B44: 45566 | C44: VESTI | D44: Full Stop | E44: Vesti Light | F44: Vesti Light | G44: 299 | H44: 299 | J44: 317 | O44: =SUM(J44:M44)-N44 -> 317 | R44: =MONTH(B44) -> 10
A45: 03/2026 | B45: 45566 | C45: VESTI | D45: G2K JEANS | E45: Vesti Light | F45: Vesti Light | G45: =800+299 -> 1099 | H45: 317 | J45: 317 | O45: =SUM(J45:M45)-N45 -> 317 | R45: =MONTH(B45) -> 10
A46: 03/2026 | B46: 45566 | C46: VESTI | D46: Donna Veste Moda Feminina | E46: Vesti Multimarcas | F46: Catálogo | H46: 29.9 | J46: 29.9 | O46: =SUM(J46:M46)-N46 -> 29.9 | Q46: 38105487000140 | R46: =MONTH(B46) -> 10
A47: 03/2026 | B47: 45567 | C47: VESTI | D47: HARD ADVENTURE | E47: Vesti Light | F47: Vesti Light | G47: 299 | H47: 299 | J47: 317 | O47: =SUM(J47:M47)-N47 -> 317 | R47: =MONTH(B47) -> 10
A48: 03/2026 | B48: 45572 | C48: Vesti - ProRoi | D48: Caronly | E48: Vesti - ProRoi | F48: Vesti Light | G48: 299 | H48: 299 | J48: 317 | O48: =SUM(J48:M48)-N48 -> 317 | R48: =MONTH(B48) -> 10
A49: 03/2026 | B49: 45568 | C49: Vesti - ProRoi | D49: Brand Fitness | E49: Vesti - ProRoi | F49: Vesti Light | G49: 299 | H49: 299 | J49: 317 | O49: =SUM(J49:M49)-N49 -> 317 | R49: =MONTH(B49) -> 10
A50: 03/2026 | B50: 45580 | C50: Vesti - Uemtel | D50: F C Mamani | E50: Vesti - Uemtel | F50: Vesti Light | G50: 299 | H50: 299 | J50: 317 | O50: =SUM(J50:M50)-N50 -> 317 | R50: =MONTH(B50) -> 10
A51: 03/2026 | B51: 45581 | C51: Vesti - ProRoi | D51: Brand Fitness | E51: Vesti - ProRoi | F51: Integração | G51: 800 | O51: =SUM(J51:M51)-N51 -> 0 | R51: =MONTH(B51) -> 10
A52: 03/2026 | B52: 45582 | C52: Vesti - Tizzefy | D52: Ganso Outlet- TGR Denim | E52: Vesti - Tizzefy | F52: Vesti Light | G52: 299 | H52: 299 | J52: 317 | O52: =SUM(J52:M52)-N52 -> 317 | R52: =MONTH(B52) -> 10
A53: 03/2026 | B53: 45583 | C53: VESTI | D53: Karal | E53: Vesti Light | F53: Vesti Light | G53: 299 | H53: 299 | J53: 317 | O53: =SUM(J53:M53)-N53 -> 317 | R53: =MONTH(B53) -> 10
A54: 03/2026 | B54: 45583 | C54: Vê Vantagens | D54: Espaço Hada | E54: Vê Vantagens | F54: Vesti Light | G54: 299 | H54: 299 | J54: 317 | O54: =SUM(J54:M54)-N54 -> 317 | R54: =MONTH(B54) -> 10
A55: 03/2026 | B55: 45587 | C55: Vesti - ProRoi | D55: Imporio Fitness | E55: Vesti - ProRoi | F55: Vesti Light | G55: 299 | H55: 299 | J55: 317 | O55: =SUM(J55:M55)-N55 -> 317 | R55: =MONTH(B55) -> 10
A56: 03/2026 | B56: 45593 | C56: Vesti - Tizzefy | D56: Evelyn Fashion | E56: Vesti Light | F56: Vesti Light | G56: 299 | H56: 299 | J56: 317 | O56: =SUM(J56:M56)-N56 -> 317 | R56: =MONTH(B56) -> 10
A57: 03/2026 | B57: 45594 | C57: Vesti - Uemtel | D57: Ary Fashions Femininas | E57: Vesti - Uemtel | F57: Vesti Light | G57: 299 | H57: 299 | J57: 317 | O57: =SUM(J57:M57)-N57 -> 317 | R57: =MONTH(B57) -> 10
A58: 03/2026 | B58: 45594 | C58: VESTI | D58: Carmen Jeans | E58: Vesti Light | F58: Vesti Light | H58: 299 | J58: 317 | O58: =SUM(J58:M58)-N58 -> 317 | R58: =MONTH(B58) -> 10
A59: 03/2026 | B59: 45594 | C59: Vesti - ProRoi | D59: Sued T-shirt | E59: Vesti - ProRoi | F59: Vesti Light | G59: 299 | H59: 299 | J59: 317 | O59: =SUM(J59:M59)-N59 -> 317 | R59: =MONTH(B59) -> 10
A60: 03/2026 | B60: 45594 | C60: Vesti - Tizzefy | D60: Afri.co | E60: Vesti - Tizzefy | F60: Vesti Light | G60: =800+299 -> 1099 | H60: 299 | J60: 317 | O60: =SUM(J60:M60)-N60 -> 317 | R60: =MONTH(B60) -> 10
A61: 03/2026 | B61: 45595 | C61: Vê Vantagens | D61: Ma Che Bella | E61: Vê Vantagens | F61: Vesti Light | G61: 299 | H61: 299 | J61: 317 | O61: =SUM(J61:M61)-N61 -> 317 | R61: =MONTH(B61) -> 10
A62: 03/2026 | B62: 45546 | C62: VESTI | D62: Armored Jeans | E62: Vesti Light | F62: Vesti Light | G62: 299 | H62: 317 | J62: 317 | O62: =SUM(J62:M62)-N62 -> 317 | R62: =MONTH(B62) -> 9
A63: 03/2026 | B63: 45600 | C63: VESTI | D63: Traffos Atacado | E63: Vesti Light | F63: Vesti Light | G63: 299 | H63: 317 | J63: =H63 -> 317 | O63: =SUM(J63:M63)-N63 -> 317 | R63: =MONTH(B63) -> 11
A64: 03/2026 | B64: 45601 | C64: VESTI | D64: Look Kids | E64: Vesti Multimarcas | F64: Catálogo | G64: 29.9 | H64: 29.9 | J64: =H64 -> 29.9 | O64: =SUM(J64:M64)-N64 -> 29.9 | R64: =MONTH(B64) -> 11
A65: 03/2026 | B65: 45603 | C65: VESTI | D65: Dazz Modas | E65: Vesti Light | F65: Vesti Light | G65: 299 | H65: 317 | J65: =H65 -> 317 | O65: =SUM(J65:M65)-N65 -> 317 | R65: =MONTH(B65) -> 11
A66: 03/2026 | B66: 45603 | C66: Vesti - Glads | D66: Wyllara | E66: Vesti - Glads | F66: Vesti Light | G66: 299 | H66: 317 | J66: =H66 -> 317 | O66: =SUM(J66:M66)-N66 -> 317 | Q66: 19219215000126​ | R66: =MONTH(B66) -> 11
A67: 03/2026 | B67: 45604 | C67: Vesti - ProRoi | D67: ASDN | E67: Vesti - ProRoi | F67: Integração | G67: 800 | J67: =H67 | O67: =SUM(J67:M67)-N67 -> 0 | Q67: 47519875000168 | R67: =MONTH(B67) -> 11
A68: 03/2026 | B68: 45604 | C68: VESTI | D68: ThreeSix 3/6 | E68: Vesti Light | F68: Vesti Light | G68: 299 | H68: 317 | J68: =H68 -> 317 | O68: =SUM(J68:M68)-N68 -> 317 | Q68: 36443627000164 | R68: =MONTH(B68) -> 11
A69: 03/2026 | B69: 45608 | C69: Vesti - Glads | D69: ​Erilluz Jeans | E69: Vesti Light | F69: Vesti Light | G69: 299 | H69: 317 | J69: =H69 -> 317 | O69: =SUM(J69:M69)-N69 -> 317 | Q69: 32796225000192​ | R69: =MONTH(B69) -> 11
A70: 03/2026 | B70: 45610 | C70: VESTI | D70: Hellas Boutique | E70: Vesti Multimarcas | F70: Catálogo | G70: 29.9 | H70: 29.9 | J70: =H70 -> 29.9 | O70: =SUM(J70:M70)-N70 -> 29.9 | Q70: 07159050000165 | R70: =MONTH(B70) -> 11
A71: 03/2026 | B71: 45614 | C71: VESTI | D71: Lie | E71: Vesti Light | F71: Vesti Light | G71: 299 | H71: 317 | J71: =H71 -> 317 | O71: =SUM(J71:M71)-N71 -> 317 | Q71: 12151080447 | R71: =MONTH(B71) -> 11
A72: 03/2026 | B72: 45617 | C72: VESTI | D72: ​By Picle | E72: Vesti Light | F72: Vesti Light | G72: 299 | H72: 317 | J72: =H72 -> 317 | O72: =SUM(J72:M72)-N72 -> 317 | Q72: 17267627000106 | R72: =MONTH(B72) -> 11
A73: 03/2026 | B73: 45617 | C73: Vesti - Glads | D73: Beach Cat Atacado | E73: Vesti Light | F73: Vesti Light | G73: 299 | H73: 317 | J73: =H73 -> 317 | O73: =SUM(J73:M73)-N73 -> 317 | Q73: 07039154870 | R73: =MONTH(B73) -> 11
A74: 03/2026 | B74: 45618 | C74: VESTI | D74: MINI DIVA | E74: Vesti Multimarcas | F74: Catálogo | G74: 29.9 | H74: 29.9 | J74: =H74 -> 29.9 | O74: =SUM(J74:M74)-N74 -> 29.9 | Q74: 05189065405 | R74: =MONTH(B74) -> 11
A75: 03/2026 | B75: 45623 | C75: VESTI | D75: Bela Palu | E75: Vesti Light | F75: Vesti Light | G75: 299 | H75: 317 | J75: =H75 -> 317 | O75: =SUM(J75:M75)-N75 -> 317 | Q75: 15865836000126 | R75: =MONTH(B75) -> 11
A76: 03/2026 | B76: 45623 | C76: VESTI | D76: BS Multimarcas | E76: Vesti Multimarcas | F76: Catálogo | G76: 29.9 | H76: 29.9 | J76: =H76 -> 29.9 | O76: =SUM(J76:M76)-N76 -> 29.9 | Q76: 49226900000140 | R76: =MONTH(B76) -> 11
A77: 03/2026 | B77: 45623 | C77: Vesti - Tizzefy | D77: KVG Oficial | E77: Vesti Light | F77: Vesti Light | G77: 800 | H77: 317 | J77: =H77 -> 317 | O77: =SUM(J77:M77)-N77 -> 317 | Q77: 10417765000185​ | R77: =MONTH(B77) -> 11
A78: 03/2026 | B78: 45625 | C78: VESTI | D78: New Mire Aviamentos | E78: Vesti Light | F78: Assistente | G78: 240 | L78: 240 | O78: =SUM(J78:M78)-N78 -> 240 | R78: =MONTH(B78) -> 11
A79: 03/2026 | B79: 45572 | C79: VESTI | D79: MEIATRÊS | E79: Vesti(assinatura) | F79: Vesti Light | G79: 249 | H79: 249 | J79: 267 | O79: =SUM(J79:M79)-N79 -> 267 | R79: =MONTH(B79) -> 10
A80: 03/2026 | B80: 45629 | C80: Vesti - Glads | D80: CavWeillers- Moda Fitness | E80: Vesti Light | F80: Vesti Light | G80: 299 | H80: 299 | J80: =H80 -> 299 | O80: =SUM(J80:M80)-N80 -> 299 | Q80: 36269709000134 | R80: =MONTH(B80) -> 12
A81: 03/2026 | B81: 45637 | C81: VESTI | D81: Viotto | E81: Vesti Light | F81: Vesti Light | G81: 299 | H81: 299 | J81: =H81 -> 299 | O81: =SUM(J81:M81)-N81 -> 299 | Q81: 55170272000121 | R81: =MONTH(B81) -> 12
A82: 03/2026 | B82: 45638 | C82: VESTI | D82: Longhini Semijoias | E82: Vesti Multimarcas | F82: Vesti Loja | G82: 99.9 | H82: 99.9 | J82: =H82 -> 99.9 | O82: =SUM(J82:M82)-N82 -> 99.9 | Q82: 48900768000148 | R82: =MONTH(B82) -> 12
A83: 03/2026 | B83: 45639 | C83: VESTI | D83: Adoratta Noivas & Festas | E83: Vesti Multimarcas | F83: Catálogo | G83: 29.9 | H83: 29.9 | J83: =H83 -> 29.9 | O83: =SUM(J83:M83)-N83 -> 29.9 | Q83: 28089163000101 | R83: =MONTH(B83) -> 12
A84: 03/2026 | B84: 45659 | C84: VESTI | D84: Doce Infancia kids Teen | E84: Vesti Multimarcas | F84: Catálogo | G84: 29.9 | H84: 29.9 | J84: 29.9 | O84: =SUM(J84:M84)-N84 -> 29.9 | P84: Vanessa Silva Alves Begnini | Q84: 02057238105 | R84: 01
A85: 03/2026 | B85: 45665 | C85: Vesti - Glads | D85: Mavem | E85: Vesti - Glads | F85: Vesti Light | G85: 299 | H85: 299 | J85: 317 | O85: =SUM(J85:M85)-N85 -> 317 | Q85: 15583317000175 | R85: 01
A86: 03/2026 | B86: 45665 | C86: VESTI | D86: Moa Plus Size | E86: Vesti Light | F86: Vesti Light | G86: 299 | H86: 299 | J86: 317 | O86: =SUM(J86:M86)-N86 -> 317 | P86: Celeb | Q86: 47661072000143 | R86: 01
A87: 03/2026 | B87: 45665 | C87: Vesti - Tizzefy | D87: Pedrita Baby | E87: Vesti Light | F87: Vesti Light | G87: 299 | H87: 299 | J87: 317 | O87: =SUM(J87:M87)-N87 -> 317 | Q87: 31482182000108 | R87: 01
A88: 03/2026 | B88: 45667 | C88: VESTI | D88: B.W multiservices | E88: Vesti Multimarcas | F88: Vesti Loja | G88: 99.9 | H88: 99.9 | J88: 117.9 | O88: =SUM(J88:M88)-N88 -> 117.9 | Q88: 50336661000160 | R88: 01
A89: 03/2026 | B89: 45670 | C89: Vesti - Tizzefy | D89: ​Savannah | E89: Vesti Light | F89: Vesti Light | G89: 299 | H89: 299 | J89: 317 | O89: =SUM(J89:M89)-N89 -> 317 | P89: Esj Confeccoes | Q89: 35945794000140 | R89: 01
A90: 03/2026 | B90: 45671 | C90: Vesti - Glads | D90: Gigantinho Kids | E90: Vesti - Glads | F90: Vesti Light | G90: 299 | H90: 299 | J90: 317 | O90: =SUM(J90:M90)-N90 -> 317 | P90: Gigantinho Kids | Q90: 11787907465 | R90: 01
A91: 03/2026 | B91: 45671 | C91: VESTI | D91: Outlet JV | E91: Vesti Multimarcas | F91: Catálogo | G91: 29.9 | H91: 29.9 | J91: 29.9 | O91: =SUM(J91:M91)-N91 -> 29.9 | Q91: 31923070000145 | R91: 01
A92: 03/2026 | B92: 45673 | C92: Vesti - Glads | D92: Brilho Trend | E92: Vesti - Glads | F92: Vesti Light | G92: 299 | H92: 299 | J92: 317 | O92: =SUM(J92:M92)-N92 -> 317 | P92: Giovanna Carvalho | Q92: 44851232000129 | R92: 01
A93: 03/2026 | B93: 45673 | C93: Vesti- Glads | D93: ​Era Uma Vez​ | E93: Vesti Light | F93: Vesti Light | G93: 800 | H93: 299 | J93: 317 | O93: =SUM(J93:M93)-N93 -> 317 | Q93: 38479807000121 | R93: 01
A94: 03/2026 | B94: 45681 | C94: VESTI | D94: Closet Moura | E94: Vesti Multimarcas | F94: Catálogo | G94: 29.9 | H94: 29.9 | J94: 29.9 | O94: =SUM(J94:M94)-N94 -> 29.9 | Q94: 58429877000182 | R94: 01
A95: 03/2026 | B95: 45687 | C95: Vesti - Uemtel | D95: BellaGirassol | E95: Vesti - Uemtel | F95: Vesti Light | G95: 1029 | H95: 299 | J95: 317 | O95: =SUM(J95:M95)-N95 -> 317 | Q95: 46896753000128 | R95: 01
A96: 03/2026 | B96: 45688 | C96: Vesti - UP | D96: Merci Modas | E96: Vesti Light | F96: Vesti Light | G96: 299 | H96: 299 | J96: 317 | O96: =SUM(J96:M96)-N96 -> 317 | Q96: 10645642000363 | R96: 01
A97: 03/2026 | B97: 45562 | C97: Vesti - ProRoi | D97: ASDN | E97: Vesti - ProRoi | F97: Vesti Light | G97: 299 | H97: 317 | J97: 317 | O97: =SUM(J97:M97)-N97 -> 317 | R97: =MONTH(B97) -> 9
A98: 03/2026 | B98: 45691 | C98: VESTI | D98: Lídia Fontgaland Store | E98: Vesti Multimarcas | F98: Catálogo | G98: 29.9 | H98: 29.9 | J98: 29.9 | O98: =SUM(J98:M98)-N98 -> 29.9 | Q98: 20601892000193 | R98: 02
A99: 03/2026 | B99: 45691 | C99: VESTI | D99: Elegant Modas | E99: Vesti Multimarcas | F99: Catálogo | G99: 29.9 | H99: 29.9 | J99: 29.9 | O99: =SUM(J99:M99)-N99 -> 29.9 | Q99: 08933599000128 | R99: 02
A100: 03/2026 | B100: 45693 | C100: VESTI | D100: Favorita Modas | E100: Vesti Multimarcas | F100: Catálogo | G100: 29.9 | H100: 29.9 | J100: 29.9 | O100: =SUM(J100:M100)-N100 -> 29.9 | Q100: 10707746000193 | R100: 02
...

Sheet Vesti 032026
A1: Fat.2026 | B1: ANIVERSÁRIO | C1: CANAL | D1: MARCA | E1: Subconta | F1: PLANO | G1: SETUP | H1: MENSALIDADE INICIAL | I1: VALOR REAJUSTE | J1: MENSALIDADE | K1: INTEGRAÇÃO | L1: ASSISTENTE | M1: FILIAL | N1: DESCONTOS | O1: TOTAL COBRADO | P1: OBSERVAÇÕES | Q1: Dia Vencimento | R1: Mês de Reajuste | S1: CPFCNPJ
A2: 03/2026 | B2: 42795 | C2: VESTI | D2: TNW Jeans | E2: Vesti (Assinatura) | F2: Profissional | H2: 1156 | J2: 1156 | O2: =SUM(J2:M2)-N2 -> 1156 | Q2: 17 | R2: 04 | S2: 4937453000108
A3: 03/2026 | B3: 42937 | C3: Atta | D3: Peonia | E3: Atta | F3: Essencial | H3: 302 | J3: 302 | O3: =SUM(J3:M3)-N3 -> 302 | Q3: 20 | R3: 4 | S3: 07993188000165
A4: 03/2026 | B4: 43160 | C4: Atta | D4: Maria De Chita | E4: Vesti (Assinatura) | F4: Profissional | H4: 724 | J4: 724 | O4: =SUM(J4:M4)-N4 -> 724 | Q4: 15 | R4: 04 | S4: 07402979000173
A5: 03/2026 | B5: 43160 | C5: Atta | D5: Shanes | E5: Vesti (Assinatura) | F5: Profissional | H5: 1179 | J5: 1179 | O5: =SUM(J5:M5)-N5 -> 1179 | Q5: 20 | R5: 04 | S5: 46446130000153
A6: 03/2026 | B6: 43160 | C6: Atta | D6: Talgui | E6: Vesti (Assinatura) | F6: Avançado | H6: 441.33 | J6: 441.33 | O6: =SUM(J6:M6)-N6 -> 441.33 | Q6: 15 | R6: 04 | S6: 05876663000198
A7: 03/2026 | B7: 43160 | C7: Atta | D7: Coinage | E7: Vesti (Assinatura) | F7: Profissional | H7: 1179 | J7: 1179 | O7: =SUM(J7:M7)-N7 -> 1179 | Q7: 20 | R7: 04 | S7: 33724927000123
A8: 03/2026 | B8: 43160 | C8: Atta | D8: Moda Inn | E8: Vesti (Assinatura) | F8: Essencial | H8: 283 | J8: 283 | O8: =SUM(J8:M8)-N8 -> 283 | Q8: 20 | R8: 04 | S8: 49921554000110
A9: 03/2026 | B9: 43160 | C9: Atta | D9: Betsey | E9: Vesti (Assinatura) | F9: Profissional | H9: 1003 | J9: 1003 | O9: =SUM(J9:M9)-N9 -> 1003 | Q9: 15 | R9: 04 | S9: 06161024000109
A10: 03/2026 | B10: 43160 | C10: Atta | D10: Cashier | E10: Vesti (Assinatura) | F10: Profissional | H10: 1015 | J10: 1015 | O10: =SUM(J10:M10)-N10 -> 1015 | Q10: 30 | R10: 04 | S10: 60368669000162
A11: 03/2026 | B11: 43160 | C11: Atta | D11: Cony Green | E11: Vesti (Assinatura) | F11: Avançado | H11: 425 | J11: 425 | O11: =SUM(J11:M11)-N11 -> 425 | Q11: 15 | R11: 04 | S11: 44511277000154
A12: 03/2026 | B12: 43160 | C12: Atta | D12: Pury | E12: Vesti (Assinatura) | F12: Profissional | H12: 1327 | J12: 1327 | M12: 359 | O12: =SUM(J12:M12)-N12 -> 1686 | Q12: 15 | R12: 04 | S12: 12576594000162
A13: 03/2026 | B13: 43160 | C13: VESTI | D13: Tricomix | E13: Vesti (Assinatura) | F13: Avançado | H13: 1193 | J13: 1193 | K13: 350 | O13: =SUM(J13:M13)-N13 -> 1543 | Q13: 11 | R13: 04 | S13: 04665515000161
A14: 03/2026 | B14: 43160 | C14: Atta | D14: Lov It | E14: Vesti (Assinatura) | F14: Avançado | H14: 425 | J14: 425 | O14: =SUM(J14:M14)-N14 -> 425 | Q14: 11 | R14: 04 | S14: 21749422000215
A15: 03/2026 | B15: 43160 | C15: Atta | D15: Hemix | E15: Vesti (Assinatura) | F15: Essencial | H15: 283 | J15: 283 | L15: =550+120 -> 670 | O15: =SUM(J15:M15)-N15 -> 953 | Q15: 15 | R15: 04 | S15: 07389520000187
A16: 03/2026 | B16: 43160 | C16: Miredata | D16: Mottive | E16: Vesti (Assinatura) | F16: Profissional | H16: 1179 | J16: 1179 | O16: =SUM(J16:M16)-N16 -> 1179 | Q16: 20 | R16: 04 | S16: 24330475000104
A17: 03/2026 | B17: 43160 | C17: Atta | D17: Miss Alfa | E17: Vesti (Assinatura) | F17: Essencial | H17: 283 | J17: 283 | O17: =SUM(J17:M17)-N17 -> 283 | Q17: 15 | R17: 04 | S17: 28497561000167
A18: 03/2026 | B18: 43160 | C18: VESTI | D18: Anemone | E18: Vesti (Assinatura) | F18: Avançado | H18: 1013 | J18: 1013 | O18: =SUM(J18:M18)-N18 -> 1013 | Q18: 11 | R18: 04 | S18: 30962814000178
A19: 03/2026 | B19: 43160 | C19: Miredata | D19: Pianeta | E19: Vesti (Assinatura) | F19: Profissional | H19: 761 | J19: 761 | O19: =SUM(J19:M19)-N19 -> 761 | Q19: 20 | R19: 04 | S19: 31583000000195
A20: 03/2026 | B20: 43356 | C20: Atta | D20: Morina | E20: Vesti (Assinatura) | F20: Profissional | H20: 1138 | J20: 1138 | O20: =SUM(J20:M20)-N20 -> 1138 | Q20: 15 | R20: 04 | S20: 44029041000186
A21: 03/2026 | B21: 43586 | C21: Atta | D21: Artemiss | E21: Vesti (Assinatura) | F21: Avançado | H21: 569 | J21: 569 | M21: 275 | O21: =SUM(J21:M21)-N21 -> 844 | Q21: 11 | R21: 04 | S21: 05320347000135
A22: 03/2026 | B22: 43586 | C22: Atta | D22: IT LOOK | E22: Vesti (Assinatura) | F22: Essencial | H22: 283 | J22: 283 | O22: =SUM(J22:M22)-N22 -> 283 | Q22: 15 | R22: 04 | S22: 21659326000103
A23: 03/2026 | B23: 43586 | C23: Atta | D23: E YUNIRE | E23: Vesti (Assinatura) | F23: Essencial | H23: 354 | J23: 354 | O23: =SUM(J23:M23)-N23 -> 354 | Q23: 15 | R23: 04 | S23: 45375658000116
A24: 03/2026 | B24: 43593 | C24: Atta | D24: Incentive | E24: Vesti (Assinatura) | F24: Essencial | H24: 528.33 | J24: 528.33 | O24: =SUM(J24:M24)-N24 -> 528.33 | Q24: 30 | R24: 04 | S24: 29780242000127
A25: 03/2026 | B25: 43593 | C25: Atta | D25: Mazarin | E25: Vesti (Assinatura) | F25: Essencial | H25: 326.67 | J25: 326.67 | O25: =SUM(J25:M25)-N25 -> 326.67 | Q25: 15 | R25: 04 | S25: 03598605000203
A26: 03/2026 | B26: 43600 | C26: Atta | D26: Blue Blossom | E26: Vesti (Assinatura) | F26: Essencial | H26: 283 | J26: 283 | M26: 410 | O26: =SUM(J26:M26)-N26 -> 693 | Q26: 15 | R26: 04 | S26: 30828978000107
A27: 03/2026 | B27: 43606 | C27: VESTI | D27: Crocker | E27: Vesti (Assinatura) | F27: Profissional | H27: 1179 | J27: 1179 | M27: 410 | O27: =SUM(J27:M27)-N27 -> 1589 | Q27: 15 | R27: 04 | S27: 60652948000153
A28: 03/2026 | B28: 43606 | C28: VESTI | D28: Lesto | E28: Vesti (Assinatura) | F28: Essencial | H28: 284.33 | J28: 284.33 | O28: =SUM(J28:M28)-N28 -> 284.33 | Q28: 15 | R28: 04 | S28: 58418377000145
A29: 03/2026 | B29: 43619 | C29: Atta | D29: Ellen One | E29: Vesti (Cartão) | F29: Essencial | H29: 283 | J29: 283 | O29: =SUM(J29:M29)-N29 -> 283 | Q29: 06 | R29: 4 | S29: 07554437000116
A30: 03/2026 | B30: 43619 | C30: Atta | D30: Instar | E30: Vesti (Assinatura) | F30: Essencial | H30: 283 | J30: 283 | O30: =SUM(J30:M30)-N30 -> 283 | Q30: 15 | R30: 04 | S30: 32649954000116
A31: 03/2026 | B31: 43633 | C31: Atta | D31: Aramodu | E31: Vesti (Assinatura) | F31: Essencial | H31: 283 | J31: 283 | O31: =SUM(J31:M31)-N31 -> 283 | Q31: 11 | R31: 04 | S31: 97541061000106
A32: 03/2026 | B32: 43643 | C32: Atta | D32: Scera | E32: Vesti (Assinatura) | F32: Essencial | H32: 283 | J32: 283 | O32: =SUM(J32:M32)-N32 -> 283 | Q32: 15 | R32: 04 | S32: 23333642000108
A33: 03/2026 | B33: 43649 | C33: Atta | D33: Fama Fashion | E33: Vesti (Assinatura) | F33: Essencial | H33: 283 | J33: 283 | O33: =SUM(J33:M33)-N33 -> 283 | Q33: 20 | R33: 04 | S33: 54451398000101
A34: 03/2026 | B34: 43649 | C34: VESTI | D34: Paloma Concept | E34: Vesti (Assinatura) | F34: Essencial | H34: 283 | J34: 283 | O34: =SUM(J34:M34)-N34 -> 283 | Q34: 15 | R34: 04 | S34: 16579598000155
A35: 03/2026 | B35: 43656 | C35: Atta | D35: Cheers | E35: Vesti (Assinatura) | F35: Profissional | H35: 1179 | J35: 1179 | O35: =SUM(J35:M35)-N35 -> 1179 | Q35: 11 | R35: 04 | S35: 53659785000175
A36: 03/2026 | B36: 43656 | C36: Atta | D36: Fesperamor | E36: Vesti (Assinatura) | F36: Profissional | H36: 1179 | J36: 1179 | O36: =SUM(J36:M36)-N36 -> 1179 | Q36: 15 | R36: 04 | S36: 22015485000120
A37: 03/2026 | B37: 43675 | C37: Atta | D37: Quebela | E37: Vesti (Assinatura) | F37: Essencial | H37: 425 | J37: 425 | M37: 369 | O37: =SUM(J37:M37)-N37 -> 794 | Q37: 20 | R37: 04 | S37: 58525007000107
A38: 03/2026 | B38: 43684 | C38: Atta | D38: Genesis Jeans | E38: Vesti (Assinatura) | F38: Essencial | H38: 283 | J38: 283 | O38: =SUM(J38:M38)-N38 -> 283 | Q38: 15 | R38: 04 | S38: 21352130000163
A39: 03/2026 | B39: 43713 | C39: Vesti | D39: AMISKA - MISS MILLIE | E39: Vesti (Assinatura) | F39: Essencial | H39: 303 | J39: 303 | O39: =SUM(J39:M39)-N39 -> 303 | Q39: 15 | R39: 04 | S39: 24721940000138
A40: 03/2026 | B40: 43718 | C40: VESTI | D40: Join Curves | E40: Vesti (Assinatura) | F40: Avançado | H40: 486 | J40: 486 | L40: 1000 | M40: 600 | O40: =SUM(J40:M40)-N40 -> 2086 | Q40: 28 | R40: 04 | S40: 07867580000168
A41: 03/2026 | B41: 43719 | C41: Atta | D41: Namine | E41: Vesti (Assinatura) | F41: Profissional | H41: 1005 | J41: 1005 | M41: =266+900 -> 1166 | O41: =SUM(J41:M41)-N41 -> 2171 | Q41: 15 | R41: 04 | S41: 17820490000256
A42: 03/2026 | B42: 43731 | C42: VESTI | D42: Diamantes | E42: Vesti (Assinatura) | F42: Profissional | H42: 1400 | J42: 1400 | M42: =38*161.95+5 -> 6159.1 | O42: =SUM(J42:M42)-N42 -> 7559.1 | Q42: 15 | R42: 04 | S42: 13649755000163
A43: 03/2026 | B43: 43738 | C43: Atta | D43: Lily Daisy | E43: Vesti (Assinatura) | F43: Essencial | H43: 283 | J43: 283 | O43: =SUM(J43:M43)-N43 -> 283 | Q43: 15 | R43: 04 | S43: 34500000000172
A44: 03/2026 | B44: 43745 | C44: VESTI | D44: Ana Gonçalves Tricot = Luis Guilherme | E44: Vesti (Assinatura) | F44: Profissional | H44: 1179 | J44: 1179 | M44: 598 | O44: =SUM(J44:M44)-N44 -> 1777 | Q44: 15 | R44: 04 | S44: 11582787000163
A45: 03/2026 | B45: 43755 | C45: Atta | D45: Delight | E45: Vesti (Assinatura) | F45: Essencial | H45: 283 | J45: 283 | O45: =SUM(J45:M45)-N45 -> 283 | Q45: 15 | R45: 04 | S45: 21520947000101
A46: 03/2026 | B46: 43755 | C46: Atta | D46: Sori | E46: Vesti (Assinatura) | F46: Profissional | H46: 1179 | J46: 1179 | O46: =SUM(J46:M46)-N46 -> 1179 | Q46: 15 | R46: 04 | S46: 06987979000110
A47: 03/2026 | B47: 43768 | C47: Atta | D47: Mx | E47: Vesti (Assinatura) | F47: Profissional | H47: 1179 | J47: 1179 | O47: =SUM(J47:M47)-N47 -> 1179 | Q47: 20 | R47: 04 | S47: 05888414000112
A48: 03/2026 | B48: 43774 | C48: Atta | D48: Donna Ritz | E48: Vesti (Assinatura) | F48: Profissional | H48: 1076.67 | J48: 1076.67 | O48: =SUM(J48:M48)-N48 -> 1076.67 | Q48: 15 | R48: 04 | S48: 19521267000152
A49: 03/2026 | B49: 43802 | C49: VESTI | D49: Vida Bela | E49: Vesti (Assinatura) | F49: Essencial | H49: 283 | J49: 283 | O49: =SUM(J49:M49)-N49 -> 283 | Q49: 15 | R49: 04 | S49: 45668696000167
A50: 03/2026 | B50: 43846 | C50: Atta | D50: Sedanbi | E50: Vesti (Assinatura) | F50: Essencial | H50: 283 | J50: 283 | O50: =SUM(J50:M50)-N50 -> 283 | Q50: 15 | R50: 04 | S50: 00238342000306
A51: 03/2026 | B51: 43861 | C51: VESTI | D51: Rafa Brasil | E51: Vesti (Assinatura) | F51: Essencial | H51: 283 | J51: 283 | O51: =SUM(J51:M51)-N51 -> 283 | Q51: 15 | R51: 04 | S51: 30827010000166
A52: 03/2026 | B52: 43867 | C52: Atta | D52: Elae | E52: Vesti (Assinatura) | F52: Avançado | H52: 425 | J52: 425 | O52: =SUM(J52:M52)-N52 -> 425 | Q52: 20 | R52: 04 | S52: 46924221000157
A53: 03/2026 | B53: 43878 | C53: Atta | D53: As Marias | E53: Vesti (Assinatura) | F53: Essencial | H53: 283 | J53: 283 | O53: =SUM(J53:M53)-N53 -> 283 | Q53: 15 | R53: 04 | S53: 24487541000154
A54: 03/2026 | B54: 43888 | C54: VESTI | D54: Suzan Zheng | E54: Vesti (Assinatura) | F54: Essencial | H54: 283 | J54: 283 | O54: =SUM(J54:M54)-N54 -> 283 | Q54: 15 | R54: 04 | S54: 26551251000158
A55: 03/2026 | B55: 43892 | C55: VESTI | D55: Gliss Jeans | E55: Vesti (Assinatura) | F55: Essencial | H55: 283 | J55: 283 | M55: 199 | O55: =SUM(J55:M55)-N55 -> 482 | Q55: 11 | R55: 04 | S55: 55251292001107
A56: 03/2026 | B56: 43903 | C56: VESTI | D56: Bauarte | E56: Vesti (Assinatura) | F56: Avançado | H56: 1231 | J56: 1231 | K56: 350 | O56: =SUM(J56:M56)-N56 -> 1581 | Q56: 20 | R56: 04 | S56: 08754784000155
A57: 03/2026 | B57: 43920 | C57: Atta | D57: Alcance Jeans | E57: Vesti (Assinatura) | F57: Profissional | H57: 1243.35 | J57: 1243.35 | M57: 250 | O57: =SUM(J57:M57)-N57 -> 1493.35 | Q57: 11 | R57: 04 | S57: 34411241000145
A58: 03/2026 | B58: 43943 | C58: VESTI | D58: Sanreed | E58: Vesti (Assinatura) | F58: Essencial | H58: 283 | J58: 283 | M58: 359 | O58: =SUM(J58:M58)-N58 -> 642 | Q58: 15 | R58: 04 | S58: 23735214000292
A59: 03/2026 | B59: 43949 | C59: VESTI | D59: Vigor Basic | E59: Vesti (Assinatura) | F59: Essencial | H59: 283 | J59: 283 | O59: =SUM(J59:M59)-N59 -> 283 | Q59: 11 | R59: 04 | S59: 07085032000186
A60: 03/2026 | B60: 43950 | C60: VESTI | D60: Manaca= Visuh | E60: Vesti (Assinatura) | F60: Profissional | H60: 1179 | J60: 1179 | O60: =SUM(J60:M60)-N60 -> 1179 | Q60: 20 | R60: 04 | S60: 22221114000102
A61: 03/2026 | B61: 43955 | C61: Atta | D61: Bokeh | E61: Vesti (Assinatura) | F61: Avançado | H61: 425 | J61: 425 | O61: =SUM(J61:M61)-N61 -> 425 | Q61: 20 | R61: 04 | S61: 28489878000232
A62: 03/2026 | B62: 43958 | C62: Atta | D62: Hanabee | E62: Vesti (Assinatura) | F62: Avançado | H62: 425 | J62: 425 | O62: =SUM(J62:M62)-N62 -> 425 | Q62: 20 | R62: 04 | S62: 12395643000160
A63: 03/2026 | B63: 43962 | C63: VESTI | D63: Cris Fael | E63: Vesti (Assinatura) | F63: Avançado | H63: 425 | J63: 425 | O63: =SUM(J63:M63)-N63 -> 425 | Q63: 15 | R63: 04 | S63: 52341858000113
A64: 03/2026 | B64: 43965 | C64: Atta | D64: Caroll | E64: Vesti (Assinatura) | F64: Avançado | H64: 665 | J64: 665 | O64: =SUM(J64:M64)-N64 -> 665 | Q64: 11 | R64: 04 | S64: 02683338000110
A65: 03/2026 | B65: 43965 | C65: Atta | D65: Kalli | E65: Vesti (Assinatura) | F65: Avançado | H65: 698 | J65: 698 | O65: =SUM(J65:M65)-N65 -> 698 | Q65: 11 | R65: 04 | S65: 17685726000108
A66: 03/2026 | B66: 43965 | C66: Atta | D66: Sexy Cookie | E66: Vesti (Assinatura) | F66: Profissional | H66: 1179 | J66: 1179 | O66: =SUM(J66:M66)-N66 -> 1179 | Q66: 11 | R66: 04 | S66: 08151457000109
A67: 03/2026 | B67: 43966 | C67: VESTI | D67: Adizza | E67: Vesti (Assinatura) | F67: Essencial | H67: 283 | J67: 283 | M67: 410 | O67: =SUM(J67:M67)-N67 -> 693 | Q67: 15 | R67: 04 | S67: 24881140000184
A68: 03/2026 | B68: 43966 | C68: VESTI | D68: Anahi | E68: Vesti (Assinatura) | F68: Avançado | H68: 425 | J68: 425 | O68: =SUM(J68:M68)-N68 -> 425 | Q68: 20 | R68: 04 | S68: 04049767000166
A69: 03/2026 | B69: 43972 | C69: Atta | D69: Ezee | E69: Vesti (Assinatura) | F69: Essencial | H69: 342.67 | J69: 342.67 | O69: =SUM(J69:M69)-N69 -> 342.67 | Q69: 15 | R69: 04 | S69: 28314192000120
A70: 03/2026 | B70: 43978 | C70: Atta | D70: Nakepe | E70: Vesti (Assinatura) | F70: Avançado | H70: 425 | J70: 425 | O70: =SUM(J70:M70)-N70 -> 425 | Q70: 22 | R70: 04 | S70: 00764187000108
A71: 03/2026 | B71: 43978 | C71: Atta | D71: Ste Fashion | E71: Vesti (Assinatura) | F71: Avançado | H71: 425 | J71: 425 | O71: =SUM(J71:M71)-N71 -> 425 | Q71: 15 | R71: 04 | S71: 12648298000120
A72: 03/2026 | B72: 43979 | C72: Atta | D72: Lilian Plus | E72: Vesti (Assinatura) | F72: Avançado | H72: 425 | J72: 425 | O72: =SUM(J72:M72)-N72 -> 425 | Q72: 15 | R72: 04 | S72: 51200947000187
A73: 03/2026 | B73: 43983 | C73: VESTI | D73: Di Collani | E73: Vesti (Assinatura) | F73: Profissional | H73: 2110.33 | J73: 2110.33 | K73: 500 | O73: =SUM(J73:M73)-N73 -> 2610.33 | Q73: 11 | R73: 04 | S73: 01102343000120
A74: 03/2026 | B74: 43983 | C74: VESTI | D74: Jeanseria | E74: Vesti (Assinatura) | F74: Profissional | H74: 405 | J74: 405 | K74: 350 | O74: =SUM(J74:M74)-N74 -> 755 | Q74: 11 | R74: 04 | S74: 01102343000120
A75: 03/2026 | B75: 43984 | C75: Atta | D75: Coqueta | E75: Vesti (Assinatura) | F75: Avançado | H75: 472.33 | J75: 472.33 | M75: 380 | O75: =SUM(J75:M75)-N75 -> 852.33 | Q75: 11 | R75: 04 | S75: 58687526000171
A76: 03/2026 | B76: 43986 | C76: Atta | D76: Clio | E76: Vesti (Assinatura) | F76: Avançado | H76: 425 | J76: 425 | O76: =SUM(J76:M76)-N76 -> 425 | Q76: 15 | R76: 04 | S76: 05550677000117
A77: 03/2026 | B77: 43986 | C77: Atta | D77: Planchet | E77: Vesti (Assinatura) | F77: Avançado | H77: 425 | J77: 425 | O77: =SUM(J77:M77)-N77 -> 425 | Q77: 15 | R77: 04 | S77: 03243396000196
A78: 03/2026 | B78: 43992 | C78: VESTI | D78: Monclos | E78: Vesti (Assinatura) | F78: Avançado | H78: 426.33 | J78: 426.33 | O78: =SUM(J78:M78)-N78 -> 426.33 | Q78: 11 | R78: 04 | S78: 59812453000246
A79: 03/2026 | B79: 43994 | C79: Atta | D79: Moirai | E79: Vesti (Assinatura) | F79: Avançado | H79: 452.67 | J79: 452.67 | O79: =SUM(J79:M79)-N79 -> 452.67 | Q79: 15 | R79: 04 | S79: 29380107000194
A80: 03/2026 | B80: 44000 | C80: Atta | D80: Noir | E80: Vesti (Assinatura) | F80: Avançado | H80: 425 | J80: 425 | O80: =SUM(J80:M80)-N80 -> 425 | Q80: 15 | R80: 04 | S80: 02415964000126
A81: 03/2026 | B81: 44006 | C81: Atta | D81: French Kiss | E81: Vesti (Assinatura) | F81: Avançado | H81: 457 | J81: 457 | O81: =SUM(J81:M81)-N81 -> 457 | Q81: 15 | R81: 04 | S81: 65977878000127
A82: 03/2026 | B82: 44006 | C82: VESTI | D82: Wool Line | E82: Vesti (Assinatura) | F82: Avançado | H82: 425 | J82: 425 | O82: =SUM(J82:M82)-N82 -> 425 | Q82: 11 | R82: 04 | S82: 23398902000123
A83: 03/2026 | B83: 44007 | C83: VESTI | D83: Amofany | E83: Vesti (Assinatura) | F83: Profissional | H83: 1179 | J83: 1179 | K83: 350 | O83: =SUM(J83:M83)-N83 -> 1529 | Q83: 15 | R83: 04 | S83: 09657596000171
A84: 03/2026 | B84: 44008 | C84: VESTI | D84: Four One | E84: Vesti (Assinatura) | F84: Avançado | H84: 425 | J84: 425 | M84: 359 | O84: =SUM(J84:M84)-N84 -> 784 | Q84: 15 | R84: 04 | S84: 55646228000145
A85: 03/2026 | B85: 44008 | C85: VESTI | D85: Peri Plus Size | E85: Vesti (Assinatura) | F85: Avançado | H85: 425 | J85: 425 | O85: =SUM(J85:M85)-N85 -> 425 | Q85: 15 | R85: 04 | S85: 41090419000169
A86: 03/2026 | B86: 44013 | C86: Atta | D86: Vitral | E86: Vesti (Assinatura) | F86: Profissional | H86: 1179 | J86: 1179 | O86: =SUM(J86:M86)-N86 -> 1179 | Q86: 20 | R86: 04 | S86: 13578271000170
A87: 03/2026 | B87: 44014 | C87: Atta | D87: Seiss & Deiss | E87: Vesti (Assinatura) | F87: Essencial | H87: 364.67 | J87: 364.67 | O87: =SUM(J87:M87)-N87 -> 364.67 | Q87: 15 | R87: 04 | S87: 17685722000120
A88: 03/2026 | B88: 44015 | C88: VESTI | D88: Buccanes | E88: Vesti (Assinatura) | F88: Essencial | H88: 283 | J88: 283 | O88: =SUM(J88:M88)-N88 -> 283 | Q88: 15 | R88: 04 | S88: 55251292000127
A89: 03/2026 | B89: 44017 | C89: Atta | D89: Hirus | E89: Vesti (Assinatura) | F89: Avançado | H89: 509 | J89: 509 | O89: =SUM(J89:M89)-N89 -> 509 | Q89: 15 | R89: 04 | S89: 07752324000206
A90: 03/2026 | B90: 44020 | C90: Atta | D90: Rubicon | E90: Vesti (Assinatura) | F90: Avançado | H90: 425 | J90: 425 | O90: =SUM(J90:M90)-N90 -> 425 | Q90: 15 | R90: 04 | S90: 24002700000183
A91: 03/2026 | B91: 44021 | C91: VESTI | D91: Lorsa | E91: Vesti (Assinatura) | F91: Avançado | H91: 425 | J91: 425 | O91: =SUM(J91:M91)-N91 -> 425 | Q91: 22 | R91: 04 | S91: 46046876000170
A92: 03/2026 | B92: 44025 | C92: VESTI | D92: Equivoco | E92: Vesti (Assinatura) | F92: Avançado | H92: 425 | J92: 425 | O92: =SUM(J92:M92)-N92 -> 425 | Q92: 22 | R92: 04 | S92: 46046876000927
A93: 03/2026 | B93: 44027 | C93: Atta | D93: Acqua Marine | E93: Vesti (Assinatura) | F93: Avançado | H93: 509 | J93: 509 | O93: =SUM(J93:M93)-N93 -> 509 | Q93: 20 | R93: 04 | S93: 56353866000130
A94: 03/2026 | B94: 44032 | C94: VESTI | D94: Lupim Camisaria | E94: Vesti (Assinatura) | F94: Avançado | H94: 509 | J94: 509 | O94: =SUM(J94:M94)-N94 -> 509 | Q94: 15 | R94: 04 | S94: 92302520000177
A95: 03/2026 | B95: 44033 | C95: Atta | D95: Bem me quer | E95: Vesti (Assinatura) | F95: Avançado | H95: 453 | J95: 453 | O95: =SUM(J95:M95)-N95 -> 453 | Q95: 20 | R95: 04 | S95: 22905439000287
A96: 03/2026 | B96: 44034 | C96: VESTI | D96: Ina Modas | E96: Vesti (Assinatura) | F96: Essencial | H96: 340 | J96: 340 | O96: =SUM(J96:M96)-N96 -> 340 | Q96: 15 | R96: 04 | S96: 55832331000180
... A103: 03/2026 | B103: 44048 | C103: Atta | D103: Yegrin | E103: Vesti (Assinatura) | F103: Avançado | H103: 471 | J103: 471 | O103: =SUM(J103:M103)-N103 -> 471 | Q103: 20 | R103: 04 | S103: 57839870000176
A104: 03/2026 | B104: 44049 | C104: Atta | D104: Chaville | E104: Vesti (Assinatura) | F104: Avançado | G104: 2770 | H104: 425 | J104: 425 | O104: =SUM(J104:M104)-N104 -> 425 | Q104: 15 | R104: 04 | S104: 60193547000182
A105: 03/2026 | B105: 44057 | C105: Atta | D105: Passione | E105: Vesti (Assinatura) | F105: Avançado | H105: 425 | J105: 425 | O105: =SUM(J105:M105)-N105 -> 425 | Q105: 20 | R105: 04 | S105: 24578961000146
A106: 03/2026 | B106: 44059 | C106: VESTI | D106: Gule Gule= Erreerre | E106: Vesti (Assinatura) | F106: Profissional | H106: 1179 | J106: 1179 | L106: 750 | O106: =SUM(J106:M106)-N106 -> 1929 | Q106: 15 | R106: 04 | S106: 54904388000184
...

Sheet 01-02-0325
A1: Fat.2025 | B1: ANIVERSÁRIO | C1: REAJUSTE ANUAL | D1: CANAL/Agência | E1: MARCA | F1: Subconta | G1: PLANO | H1: SETUP | I1: MENSALIDADE INICIAL | J1: VALOR REAJUSTE | K1: MENSALIDADE | L1: INTEGRAÇÃO | M1: ASSISTENTE | N1: FILIAL | O1: DESCONTOS | P1: TOTAL COBRADO | Q1: OBSERVAÇÕES | R1: CPF e CNPJ | S1: Mês de Reajuste
A2: 01/2025 | B2: 45257 | D2: Zoom | E2: República Caipira | F2: Mensalidade Vesti | G2: Vesti Light | H2: 0 | I2: 267 | K2: =I2+J2 -> 267 | P2: =SUM(K2:N2)-O2 -> 267 | S2: =MONTH(B2) -> 11
A3: 01/2025 | B3: 45259 | D3: Zoom | E3: WA Baby | F3: Vesti (Cartão) | G3: Vesti Light | H3: 0 | I3: 267 | K3: =I3+J3 -> 267 | P3: =SUM(K3:N3)-O3 -> 267 | S3: =MONTH(B3) -> 11
A4: 01/2025 | B4: 45307 | C4: 18 | D4: Sete | E4: Levitheo | F4: Vesti (Cartão) | G4: Vesti Light | H4: 249 | I4: 249 | J4: 18 | K4: =I4+J4 -> 267 | P4: =SUM(K4:N4)-O4 -> 267 | S4: =MONTH(B4) -> 1
A5: 01/2025 | B5: 45314 | C5: 18 | D5: ProRoi | E5: Wave Core | F5: Vesti (Cartão) | G5: Vesti Light | H5: 249 | I5: 249 | J5: 18 | K5: =I5+J5 -> 267 | P5: =SUM(K5:N5)-O5 -> 267 | S5: =MONTH(B5) -> 1
A6: 01/2025 | B6: 45315 | C6: 18 | D6: Sete | E6: Donna Stella | F6: Vesti (Cartão) | G6: Vesti Light | H6: 249 | I6: 249 | J6: 18 | K6: =I6+J6 -> 267 | P6: =SUM(K6:N6)-O6 -> 267 | S6: =MONTH(B6) -> 1
A7: 01/2025 | B7: 45320 | C7: 18 | D7: VESTI | E7: Nadri | F7: Vesti (Cartão) | G7: Vesti Light | H7: 249 | I7: 249 | J7: 18 | K7: =I7+J7 -> 267 | P7: =SUM(K7:N7)-O7 -> 267 | S7: =MONTH(B7) -> 1
A8: 01/2025 | B8: 45323 | D8: Zoom | E8: GO Padel | F8: Vesti (Cartão) | G8: Vesti Light | H8: 249 | I8: 249 | K8: =I8 -> 249 | P8: =SUM(K8:N8)-O8 -> 249 | S8: =MONTH(B8) -> 2
A9: 01/2025 | B9: 45323 | D9: Sete | E9: Kroft Oficial | F9: Vesti (Cartão) | G9: Vesti Light | H9: 249 | I9: 249 | K9: =I9 -> 249 | P9: =SUM(K9:N9)-O9 -> 249 | S9: =MONTH(B9) -> 2
A10: 01/2025 | B10: 45337 | D10: Zoom | E10: Divas Vero | F10: Vesti (Cartão) | G10: Vesti Light | H10: 249 | I10: 249 | K10: =I10 -> 249 | P10: =SUM(K10:N10)-O10 -> 249 | S10: =MONTH(B10) -> 2
A11: 01/2025 | B11: 45342 | D11: ProRoi | E11: Repete Conf | F11: Vesti (Cartão) | G11: Vesti Light | H11: 249 | I11: 249 | K11: =I11 -> 249 | P11: =SUM(K11:N11)-O11 -> 249 | S11: =MONTH(B11) -> 2
A12: 01/2025 | B12: 45352 | D12: Sete | E12: Monnika Marikinha Brand | F12: Vesti (Cartão) | G12: Vesti Light | H12: 249 | I12: 249 | K12: =I12 -> 249 | P12: =SUM(K12:N12)-O12 -> 249 | S12: =MONTH(B12) -> 3
A13: 01/2025 | B13: 45352 | D13: ProRoi | E13: RED ROCK (R) | F13: ProRoi | G13: Vesti Light | H13: 249 | I13: 249 | K13: 249 | P13: =SUM(K13:N13)-O13 -> 249 | S13: =MONTH(B13) -> 3
A14: 01/2025 | B14: 45357 | D14: ProRoi | E14: V&S ou S&V | F14: Vesti (Cartão) | G14: Vesti Light | H14: 249 | I14: 249 | K14: 249 | P14: =SUM(K14:N14)-O14 -> 249 | S14: =MONTH(B14) -> 3
A15: 01/2025 | B15: 45363 | D15: Sete | E15: Fabio's Moda Intima | F15: Vesti (Cartão) | G15: Vesti Light | H15: 249 | I15: 249 | K15: 249 | P15: =SUM(K15:N15)-O15 -> 249 | S15: =MONTH(B15) -> 3
A16: 01/2025 | B16: 45364 | D16: ProRoi | E16: Portullaca | F16: Vesti (Cartão) | G16: Vesti Light | H16: 249 | I16: 249 | K16: 249 | P16: =SUM(K16:N16)-O16 -> 249 | S16: =MONTH(B16) -> 3
A17: 01/2025 | B17: 45379 | D17: Zoom | E17: RL Modas | F17: Vesti (Cartão) | G17: Vesti Light | H17: 249 | I17: 249 | K17: 249 | P17: =SUM(K17:N17)-O17 -> 249 | S17: =MONTH(B17) -> 3
A18: 01/2025 | B18: 45384 | D18: VESTI | E18: Blommer | F18: Vesti (Cartão) | G18: Vesti Light | H18: 249 | I18: 249 | K18: 249 | P18: =SUM(K18:N18)-O18 -> 249 | S18: =MONTH(B18) -> 4
A19: 01/2025 | B19: 45393 | D19: Tizzefy | E19: Aline Confecções | F19: Vesti (Cartão) | G19: Vesti Light | H19: 249 | I19: 249 | K19: 249 | P19: =SUM(K19:N19)-O19 -> 249 | S19: =MONTH(B19) -> 4
A20: 01/2025 | B20: 45411 | D20: Tizzefy | E20: Igmar | F20: Vesti (Cartão) | G20: Vesti Light | H20: 249 | I20: 249 | K20: 249 | P20: =SUM(K20:N20)-O20 -> 249 | S20: =MONTH(B20) -> 4
A21: 01/2025 | B21: 45418 | D21: Tizzefy | E21: Worldstar Lingerie | F21: Vesti (Cartão) | G21: Vesti Light | H21: 249 | I21: 249 | K21: 249 | P21: =SUM(K21:N21)-O21 -> 249 | S21: =MONTH(B21) -> 5
A22: 01/2025 | B22: 45425 | D22: ProRoi | E22: Bella Fe | F22: Vesti (Cartão) | G22: Vesti Light | H22: 249 | I22: 249 | K22: 249 | P22: =SUM(K22:N22)-O22 -> 249 | S22: =MONTH(B22) -> 5
A23: 01/2025 | B23: 45429 | C23: ok | D23: Vê Vantagens | E23: Loja Luu's | F23: Vê Vantagens | G23: Vesti Light | H23: 249 | I23: 249 | J23: 18 | K23: 267 | P23: =SUM(K23:N23)-O23 -> 267 | S23: =MONTH(B23) -> 5
A24: 01/2025 | B24: 45434 | C24: ok | D24: ProRoi | E24: RIBELIM | F24: Vesti - ProRoi | G24: Vesti Light | H24: 249 | I24: 249 | K24: 267 | P24: =SUM(K24:N24)-O24 -> 267 | S24: =MONTH(B24) -> 5
A25: 01/2025 | B25: 45439 | C25: ok | D25: Vê Vantagens | E25: Anne Blanc | F25: Vê Vantagens | G25: Vesti Light | H25: 249 | I25: 249 | J25: 18 | K25: 267 | P25: =SUM(K25:N25)-O25 -> 267 | S25: =MONTH(B25) -> 5
A26: 01/2025 | B26: 45446 | D26: VESTI | E26: Lupus Wear | F26: Vesti Light | G26: Vesti Light | H26: 249 | I26: 249 | K26: 249 | P26: =SUM(K26:N26)-O26 -> 249 | S26: =MONTH(B26) -> 6
A27: 01/2025 | B27: 45448 | D27: VESTI | E27: Felps Confecções | F27: Vesti Light | G27: Vesti Light | H27: 0 | I27: 249 | K27: =I27 -> 249 | P27: =SUM(K27:N27)-O27 -> 249 | S27: =MONTH(B27) -> 6
A28: 01/2025 | B28: 45457 | D28: Tizzefy | E28: MINOLLI | F28: Vesti - Tizzefy | G28: Vesti Light | H28: 249 | I28: 249 | K28: 249 | P28: =SUM(K28:N28)-O28 -> 249 | S28: =MONTH(B28) -> 6
A29: 01/2025 | B29: 45460 | D29: VESTI | E29: Minha Nina | F29: Vesti Light | G29: Vesti Light | H29: 249 | I29: 249 | K29: 249 | P29: =SUM(K29:N29)-O29 -> 249 | S29: =MONTH(B29) -> 6
A30: 01/2025 | B30: 45462 | D30: VESTI | E30: Urban Race | F30: Vesti Light | G30: Vesti Light | H30: 299 | I30: 299 | K30: 299 | P30: =SUM(K30:N30)-O30 -> 299 | S30: =MONTH(B30) -> 6
A31: 01/2025 | B31: 45462 | D31: VESTI | E31: Planet Charm | F31: Vesti Light | G31: Vesti Light | H31: 299 | I31: 299 | K31: 299 | P31: =SUM(K31:N31)-O31 -> 299 | S31: =MONTH(B31) -> 6
A32: 01/2025 | B32: 45533 | D32: VESTI | E32: A Rouparia | F32: Vesti Multimarcas | G32: Vesti Multimarca | H32: 99 | I32: 99 | K32: 99 | P32: =SUM(K32:N32)-O32 -> 99 | R32: 32979501000158 | S32: =MONTH(B32) -> 8
A33: 01/2025 | B33: 45489 | D33: Vê Vantagens | E33: PEROLA ORIENTAL LK&D | F33: Vê Vantagens | G33: Vesti Light | H33: 249 | I33: 249 | K33: 249 | P33: =SUM(K33:N33)-O33 -> 249 | S33: =MONTH(B33) -> 7
A34: 01/2025 | B34: 45639 | D34: VESTI | E34: Adoratta Noivas & Festas | F34: Vesti Multimarcas | G34: Catálogo | H34: 29.9 | I34: 29.9 | K34: =I34 -> 29.9 | P34: =SUM(K34:N34)-O34 -> 29.9 | R34: 28089163000101 | S34: =MONTH(B34) -> 12
A35: 01/2025 | B35: 45540 | D35: VESTI | E35: ADRI GUERRERO | F35: Vesti Multimarcas | G35: Vesti Multimarca | H35: 99 | I35: 99 | K35: 99 | P35: =SUM(K35:N35)-O35 -> 99 | R35: 05808690000123 | S35: =MONTH(B35) -> 9
A36: 01/2025 | B36: 45495 | D36: VESTI | E36: Tatyta Plus Size | F36: Vesti Light | G36: Vesti Light | H36: 299 | I36: 299 | K36: 299 | P36: =SUM(K36:N36)-O36 -> 299 | S36: =MONTH(B36) -> 7
A37: 01/2025 | B37: 45500 | D37: ProRoi | E37: BegKids | F37: Vesti - ProRoi | G37: Vesti Light | H37: 299 | I37: 299 | K37: 299 | P37: =SUM(K37:N37)-O37 -> 299 | S37: =MONTH(B37) -> 7
A38: 01/2025 | B38: 45501 | D38: VESTI | E38: Agridoce | F38: Vesti Light | G38: Vesti Light | H38: 699 | I38: 299 | K38: 299 | P38: =SUM(K38:N38)-O38 -> 299 | S38: =MONTH(B38) -> 7
A39: 01/2025 | B39: 45532 | D39: Atta | E39: Amavela | F39: Vesti Light | G39: Vesti Light | H39: 699 | I39: 299 | K39: 299 | P39: =SUM(K39:N39)-O39 -> 299 | S39: =MONTH(B39) -> 8
A40: 01/2025 | B40: 45505 | D40: VESTI | E40: Arary | F40: Vesti Light | G40: Vesti Light | H40: 299 | I40: 299 | K40: 299 | P40: =SUM(K40:N40)-O40 -> 299 | S40: =MONTH(B40) -> 8
A41: 01/2025 | B41: 45506 | D41: VESTI | E41: Ylle Lingerie | F41: Vesti Light | G41: Vesti Light | H41: 299 | I41: 299 | K41: 299 | P41: =SUM(K41:N41)-O41 -> 299 | S41: =MONTH(B41) -> 8
A42: 01/2025 | B42: 45506 | D42: Vê Vantagens | E42: Aurami | F42: Vê Vantagens | G42: Vesti Light | H42: 299 | I42: 299 | K42: 299 | P42: =SUM(K42:N42)-O42 -> 299 | S42: =MONTH(B42) -> 8
A43: 01/2025 | B43: 45610 | D43: VESTI | E43: Agua&lua Moda Praia e Fitness | F43: Vesti Multimarcas | G43: Vesti Loja | H43: 99.9 | I43: 99.9 | K43: =I43 -> 99.9 | P43: =SUM(K43:N43)-O43 -> 99.9 | R43: 21686782000134 | S43: =MONTH(B43) -> 11
A44: 01/2025 | B44: 45547 | D44: VESTI | E44: Alice Amaral Brand Store | F44: Vesti Multimarcas | G44: Vesti Multimarca | H44: 99 | I44: 99 | K44: 99 | P44: =SUM(K44:N44)-O44 -> 99 | R44: 30707302000165 | S44: =MONTH(B44) -> 9
A45: 01/2025 | B45: 45624 | D45: VESTI | E45: Amalliah Perfumaria | F45: Vesti Multimarcas | G45: Vesti Loja | H45: 99.9 | I45: 99.9 | K45: =I45 -> 99.9 | P45: =SUM(K45:N45)-O45 -> 99.9 | R45: 58249280000156 | S45: =MONTH(B45) -> 11
A46: 01/2025 | B46: 45506 | D46: VESTI | E46: TNT Moda Fitness | F46: Vesti Light | G46: Vesti Light | H46: 299 | I46: 299 | K46: 299 | P46: =SUM(K46:N46)-O46 -> 299 | S46: =MONTH(B46) -> 8
A47: 01/2025 | B47: 45603 | D47: VESTI | E47: Amor & Amor Teen Kids | F47: Vesti Multimarcas | G47: Vesti Loja | H47: 99.9 | I47: 99.9 | K47: =I47 -> 99.9 | P47: =SUM(K47:N47)-O47 -> 99.9 | S47: =MONTH(B47) -> 11
A48: 01/2025 | B48: 45516 | D48: VESTI | E48: Bordô Store | F48: Vesti Light | G48: Vesti Light | H48: 299 | I48: 299 | K48: 299 | P48: =SUM(K48:N48)-O48 -> 299 | S48: =MONTH(B48) -> 8
A49: 01/2025 | B49: 45552 | D49: VESTI | E49: Amora Multimodas | F49: Vesti Multimarcas | G49: Vesti Conecta | H49: 99 | I49: 99 | K49: =I49 -> 99 | P49: =SUM(K49:N49)-O49 -> 99 | R49: 24898292000190 | S49: =MONTH(B49) -> 9
A50: 01/2025 | B50: 45518 | D50: VESTI | E50: Karmel | F50: Vesti Light | G50: Vesti Light | H50: 299 | I50: 299 | K50: 299 | P50: =SUM(K50:N50)-O50 -> 299 | S50: =MONTH(B50) -> 8
A51: 01/2025 | B51: 45519 | D51: Atta | E51: La Folie | F51: Vesti Light | G51: Vesti Light | H51: 299 | I51: 299 | K51: 299 | P51: =SUM(K51:N51)-O51 -> 299 | S51: =MONTH(B51) -> 8
A52: 01/2025 | B52: 45519 | D52: Vê Vantagens | E52: PEROLA ORIENTAL = M&K | F52: Vê Vantagens | G52: Vesti Light | H52: 299 | I52: 249 | K52: 249 | P52: =SUM(K52:N52)-O52 -> 249 | S52: =MONTH(B52) -> 8
A53: 01/2025 | B53: 45520 | D53: Vê Vantagens | E53: HI LOOK | F53: Vê Vantagens | G53: Vesti Light | H53: 299 | I53: 299 | K53: 299 | P53: =SUM(K53:N53)-O53 -> 299 | S53: =MONTH(B53) -> 8
A54: 01/2025 | B54: 45520 | D54: VESTI | E54: Dádiva | F54: Vesti Light | G54: Vesti Light | H54: 299 | I54: 299 | K54: 299 | P54: =SUM(K54:N54)-O54 -> 299 | S54: =MONTH(B54) -> 8
A55: 01/2025 | B55: 45607 | D55: VESTI | E55: Anna Garcia Ateliê | F55: Vesti Multimarcas | G55: Catálogo | H55: 29.9 | I55: 29.9 | K55: =I55 -> 29.9 | P55: =SUM(K55:N55)-O55 -> 29.9 | R55: 22439127000144 | S55: =MONTH(B55) -> 11
A56: 01/2025 | B56: 45638 | D56: VESTI | E56: Arco e Flecha | F56: Vesti Multimarcas | G56: Catálogo | H56: 29.9 | I56: 29.9 | K56: =I56 -> 29.9 | P56: =SUM(K56:N56)-O56 -> 29.9 | R56: 03759999301 | S56: =MONTH(B56) -> 12
A57: 01/2025 | B57: 45531 | D57: VESTI | E57: TNT Moda Fitness | F57: Vesti Light | G57: Vesti Light | H57: 299 | I57: 299 | K57: 299 | P57: =SUM(K57:N57)-O57 -> 299 | S57: =MONTH(B57) -> 8
A58: 01/2025 | B58: 45532 | D58: VESTI | E58: Asimi | F58: Vesti Multimarcas | G58: Vesti Multimarca | H58: 159 | I58: 159 | K58: 159 | P58: =SUM(K58:N58)-O58 -> 159 | R58: 50951099000185 | S58: =MONTH(B58) -> 8
A59: 01/2025 | B59: 45532 | D59: VESTI | E59: Lado Doce | F59: Vesti Light | G59: Vesti Light | H59: 800 | I59: 299 | K59: 299 | P59: =SUM(K59:N59)-O59 -> 299 | S59: =MONTH(B59) -> 8
A60: 01/2025 | B60: 45618 | D60: VESTI | E60: BASIC & CHIC | F60: Vesti Multimarcas | G60: Catálogo | H60: 29.9 | I60: 29.9 | K60: =I60 -> 29.9 | P60: =SUM(K60:N60)-O60 -> 29.9 | R60: 63363852568 | S60: =MONTH(B60) -> 11
A61: 01/2025 | B61: 45622 | D61: VESTI | E61: BETEL VARIEDADES | F61: Vesti Multimarcas | G61: Vesti Loja | H61: 99.9 | I61: 99.9 | K61: =I61 -> 99.9 | P61: =SUM(K61:N61)-O61 -> 99.9 | S61: =MONTH(B61) -> 11
A62: 01/2025 | B62: 45495 | D62: VESTI | E62: Boutique Papoula | F62: Vesti Multimarcas | G62: Vesti Multimarca | H62: 159 | I62: 159 | K62: 159 | P62: =SUM(K62:N62)-O62 -> 159 | R62: 50040039000100 | S62: =MONTH(B62) -> 7
A63: 01/2025 | B63: 45534 | D63: Zoom | E63: Gross Hunter | F63: Vesti Light | G63: Vesti Light | H63: 249 | I63: 249 | K63: =I63 -> 249 | P63: =SUM(K63:N63)-O63 -> 249 | S63: =MONTH(B63) -> 8
A64: 01/2025 | B64: 45537 | D64: VESTI | E64: Clacev | F64: Vesti Light | G64: Vesti Light | H64: 299 | I64: 299 | K64: 299 | P64: =SUM(K64:N64)-O64 -> 299 | S64: =MONTH(B64) -> 9
A65: 01/2025 | B65: 45539 | D65: VESTI | E65: Drika Confeccoes | F65: Vesti Light | G65: Vesti Light | H65: 800 | I65: 598 | K65: 598 | P65: =SUM(K65:N65)-O65 -> 598 | S65: =MONTH(B65) -> 9
A66: 01/2025 | B66: 45539 | D66: Tizzefy | E66: VLY JEANS | F66: Vesti - Tizzefy | G66: Vesti Light | H66: 800 | I66: 249 | K66: 249 | P66: =SUM(K66:N66)-O66 -> 249 | S66: =MONTH(B66) -> 9
A67: 01/2025 | B67: 45511 | D67: VESTI | E67: BOUTIQUE ZOCA'S MAISON | F67: Vesti Multimarcas | G67: Vesti Multimarca | H67: 159 | I67: 159 | K67: 159 | P67: =SUM(K67:N67)-O67 -> 159 | R67: 04886653000170 | S67: =MONTH(B67) -> 8
A68: 01/2025 | B68: 45539 | D68: VESTI | E68: Veste Vegana | F68: Vesti Light | G68: Vesti Light | H68: 249 | I68: 249 | K68: 249 | P68: =SUM(K68:N68)-O68 -> 249 | S68: =MONTH(B68) -> 9
A69: 01/2025 | B69: 45539 | D69: Atta | E69: Alle_Moda | F69: Vesti Light | G69: Vesti Light | H69: 299 | I69: 299 | K69: 299 | P69: =SUM(K69:N69)-O69 -> 299 | S69: =MONTH(B69) -> 9
A70: 01/2025 | B70: 45623 | D70: VESTI | E70: BS Multimarcas | F70: Vesti Multimarcas | G70: Catálogo | H70: 29.9 | I70: 29.9 | K70: =I70 -> 29.9 | P70: =SUM(K70:N70)-O70 -> 29.9 | R70: 49226900000140 | S70: =MONTH(B70) -> 11
A71: 01/2025 | B71: 45541 | D71: VESTI | E71: Dominio​ Conceito | F71: Vesti Light | G71: Vesti Light | H71: =800+299 -> 1099 | I71: 299 | K71: 299 | P71: =SUM(K71:N71)-O71 -> 299 | S71: =MONTH(B71) -> 9
A72: 01/2025 | B72: 45511 | D72: VESTI | E72: By Kropp | F72: Vesti Multimarcas | G72: Vesti Multimarca | H72: 99 | I72: 99 | K72: 99 | P72: =SUM(K72:N72)-O72 -> 99 | R72: 44333648000155 | S72: =MONTH(B72) -> 8
A73: 01/2025 | B73: 45580 | D73: VESTI | E73: CAMILA ROSA | F73: Vesti Multimarcas | G73: Vesti Conecta | H73: 99 | I73: 99 | K73: =I73 -> 99 | P73: =SUM(K73:N73)-O73 -> 99 | R73: 54122673000143 | S73: =MONTH(B73) -> 10
A74: 01/2025 | B74: 45546 | D74: ProRoi | E74: Gran Feliccittà | F74: Vesti - ProRoi | G74: vesti light | H74: 299 | I74: 299 | K74: 299 | P74: =SUM(K74:N74)-O74 -> 299 | S74: =MONTH(B74) -> 9
A75: 01/2025 | B75: 45565 | D75: VESTI | E75: Caroline Bueno Closet | F75: Vesti Multimarcas | G75: Vesti Conecta | H75: 99 | I75: 99 | K75: 99 | P75: =SUM(K75:N75)-O75 -> 99 | R75: 41746583000181 | S75: =MONTH(B75) -> 9
A76: 01/2025 | B76: 45548 | D76: VESTI | E76: Julia Andrade Bijuterias​ | F76: Vesti Light | G76: Vesti Light | H76: 299 | I76: 299 | K76: 299 | P76: =SUM(K76:N76)-O76 -> 299 | S76: =MONTH(B76) -> 9
A77: 01/2025 | B77: 45601 | D77: VESTI | E77: CASA IV | F77: Vesti Multimarcas | G77: Vesti Loja | H77: 99.9 | I77: 99.9 | K77: =I77 -> 99.9 | P77: =SUM(K77:N77)-O77 -> 99.9 | S77: =MONTH(B77) -> 11
A78: 01/2025 | B78: 45548 | D78: VESTI | E78: Rita Colato | F78: Vesti Light | G78: Vesti Light | H78: 299 | I78: 299 | K78: 299 | P78: =SUM(K78:N78)-O78 -> 299 | S78: =MONTH(B78) -> 9
A79: 01/2025 | B79: 45548 | D79: VESTI | E79: Little Star | F79: Vesti Light | G79: Vesti Light | H79: 299 | I79: 299 | K79: 299 | P79: =SUM(K79:N79)-O79 -> 299 | S79: =MONTH(B79) -> 9
A80: 01/2025 | B80: 45644 | D80: VESTI | E80: Cecita Boutique | F80: Vesti Multimarcas | G80: Catálogo | H80: 29.9 | I80: 29.9 | K80: =I80 -> 29.9 | P80: =SUM(K80:N80)-O80 -> 29.9 | R80: 51950341000169 | S80: =MONTH(B80) -> 12
A81: 01/2025 | B81: 45509 | D81: VESTI | E81: Chocoberry | F81: Vesti Light | G81: Vesti Light | H81: 299 | I81: 299 | K81: 299 | P81: =SUM(K81:N81)-O81 -> 299 | S81: =MONTH(B81) -> 8
A82: 01/2025 | B82: 45631 | D82: VESTI | E82: CHIC CURVES - MB Collection | F82: Vesti Multimarcas | G82: Vesti Loja | H82: 99.9 | I82: 99.9 | K82: =I82 -> 99.9 | P82: =SUM(K82:N82)-O82 -> 99.9 | R82: 38004886000114 | S82: =MONTH(B82) -> 12
A83: 01/2025 | B83: 45553 | D83: VESTI | E83: Lado Doce | F83: Vesti Light | G83: Assistente | H83: 300 | K83: 0 | M83: 300 | P83: =SUM(K83:N83)-O83 -> 300 | S83: =MONTH(B83) -> 9
A84: 01/2025 | B84: 45573 | D84: VESTI | E84: Chicamaleta | F84: Vesti Multimarcas | G84: Vesti Conecta | H84: 99 | I84: 99 | K84: =I84 -> 99 | P84: =SUM(K84:N84)-O84 -> 99 | R84: 39527050000167 | S84: =MONTH(B84) -> 10
A85: 01/2025 | B85: 45554 | D85: VESTI | E85: New Gomone | F85: Vesti Light | G85: Vesti Light | H85: 299 | I85: 299 | K85: 299 | P85: =SUM(K85:N85)-O85 -> 299 | S85: =MONTH(B85) -> 9
A86: 01/2025 | B86: 45558 | D86: VESTI | E86: New Mire Aviamentos | F86: Vesti Light | G86: Vesti Light | H86: 299 | I86: 299 | K86: 299 | M86: 149 | P86: =SUM(K86:N86)-O86 -> 448 | S86: =MONTH(B86) -> 9
A87: 01/2025 | B87: 45610 | D87: VESTI | E87: Clair Trisch | F87: Vesti Multimarcas | G87: Catálogo | H87: 29.9 | I87: 29.9 | K87: =I87 -> 29.9 | P87: =SUM(K87:N87)-O87 -> 29.9 | R87: 24921931000190 | S87: =MONTH(B87) -> 11
A88: 01/2025 | B88: 45623 | D88: VESTI | E88: Cloeh Beauty Boutique | F88: Vesti Multimarcas | G88: Catálogo | H88: 29.9 | I88: 29.9 | K88: =I88 -> 29.9 | P88: =SUM(K88:N88)-O88 -> 29.9 | R88: 35708855000156 | S88: =MONTH(B88) -> 11
A89: 01/2025 | B89: 45562 | D89: VESTI | E89: Veste Boy | F89: Vesti Light | G89: Vesti Light | H89: 299 | I89: 299 | K89: 299 | P89: =SUM(K89:N89)-O89 -> 299 | S89: =MONTH(B89) -> 9
A90: 01/2025 | B90: 45565 | D90: VESTI | E90: Closet Donna Onca | F90: Vesti Multimarcas | G90: Vesti Conecta | H90: 99 | I90: 99 | K90: 99 | P90: =SUM(K90:N90)-O90 -> 99 | R90: 44748503000115 | S90: =MONTH(B90) -> 9
A91: 01/2025 | B91: 45630 | D91: VESTI | E91: Colorê Moda Infantil | F91: Vesti Multimarcas | G91: Catálogo | H91: 29.9 | I91: 29.9 | K91: =I91 -> 29.9 | P91: =SUM(K91:N91)-O91 -> 29.9 | R91: 18801016000169 | S91: =MONTH(B91) -> 12
A92: 01/2025 | B92: 45637 | D92: VESTI | E92: Cravo e Canela | F92: Vesti Multimarcas | G92: Vesti Loja | H92: 99.9 | I92: 99.9 | K92: =I92 -> 99.9 | P92: =SUM(K92:N92)-O92 -> 99.9 | R92: 47313088000165 | S92: =MONTH(B92) -> 12
A93: 01/2025 | B93: 45545 | D93: Vesti - Uemtel | E93: Lele Modas | F93: Vesti - Uemtel | G93: Vesti Light | H93: 299 | I93: 299 | K93: 299 | P93: =SUM(K93:N93)-O93 -> 299 | S93: =MONTH(B93) -> 9
A94: 01/2025 | B94: 45520 | D94: Vesti - Uemtel | E94: RCA Flores | F94: Vesti - Uemtel | G94: Vesti Light | H94: 299 | I94: 299 | K94: 299 | P94: =SUM(K94:N94)-O94 -> 299 | S94: =MONTH(B94) -> 8
A95: 01/2025 | B95: 45565 | D95: Vesti - Uemtel | E95: Kaylee Modas | F95: Vesti - Uemtel | G95: Vesti Light | H95: 299 | I95: 299 | K95: 299 | P95: =SUM(K95:N95)-O95 -> 299 | S95: =MONTH(B95) -> 9
A96: 01/2025 | B96: 45566 | D96: VESTI | E96: Full Stop | F96: Vesti Light | G96: Vesti Light | H96: 299 | I96: 299 | K96: =I96 -> 299 | P96: =SUM(K96:N96)-O96 -> 299 | S96: =MONTH(B96) -> 10
A97: 01/2025 | B97: 45566 | D97: VESTI | E97: G2K JEANS | F97: Vesti Light | G97: Vesti Light | H97: =800+299 -> 1099 | I97: 299 | K97: =I97 -> 299 | P97: =SUM(K97:N97)-O97 -> 299 | S97: =MONTH(B97) -> 10
A98: 01/2025 | B98: 45513 | D98: VESTI | E98: D FLOR BOUTIQUE | F98: Vesti Multimarcas | G98: Vesti Multimarca | H98: 99 | I98: 99 | K98: 99 | P98: =SUM(K98:N98)-O98 -> 99 | R98: 36020989000142 | S98: =MONTH(B98) -> 8
A99: 01/2025 | B99: 45644 | D99: VESTI | E99: D Flor Woman | F99: Vesti Multimarcas | G99: Catálogo | H99: 29.9 | I99: 29.9 | K99: =I99 -> 29.9 | P99: =SUM(K99:N99)-O99 -> 29.9 | R99: 58240725000137 | S99: =MONTH(B99) -> 12
A100: 01/2025 | B100: 45566 | D100: VESTI | E100: MERCY MODA FEMININA | F100: Vesti Light | G100: Vesti Light | H100: 299 | I100: 299 | K100: =I100 -> 299 | P100: =SUM(K100:N100)-O100 -> 299 | S100: =MONTH(B100) -> 10
...

Sheet Vesti 04-2026
A1: Fat.2026 | B1: ANIVERSÁRIO | C1: DOMINIO | D1: COMPANY | E1: VENDEDORA | F1: REAJUSTE ANUAL | G1: CANAL | H1: MARCA | I1: Subconta | J1: PLANO | K1: SETUP | L1: MENSALIDADE INICIAL | M1: VALOR REAJUSTE | N1: MENSALIDADE | O1: INTEGRAÇÃO | P1: ASSISTENTE | Q1: FILIAL | R1: DESCONTOS | S1: TOTAL COBRADO | T1: OBSERVAÇÕES | U1: Dia Vencimento | V1: Mês de Reajuste | W1: CPFCNPJ
A2: 04/2026 | B2: 42795 | C2: =VLOOKUP(H2,Dominios!$A:$D,3,0) -> #REF! | D2: =VLOOKUP(H2,Dominios!$A:$D,4,0) -> #REF! | E2: =COUNTIF(#REF!,H2) -> #REF! | G2: VESTI | H2: TNW Jeans | I2: Vesti (Assinatura) | J2: Profissional | L2: 1156 | N2: 1156 | S2: =SUM(N2:Q2)-R2 -> 1156 | U2: 17 | V2: 04 | W2: 4937453000108
A3: 04/2026 | B3: 42937 | C3: =VLOOKUP(H3,Dominios!$A:$D,3,0) -> #REF! | D3: =VLOOKUP(H3,Dominios!$A:$D,4,0) -> #REF! | E3: =COUNTIF(#REF!,H3) -> #REF! | F3: ok | G3: Atta | H3: Peonia | I3: Atta | J3: Essencial | L3: 302 | N3: 302 | S3: =SUM(N3:Q3)-R3 -> 302 | U3: 20 | V3: 4 | W3: 07993188000165
A4: 04/2026 | B4: 43160 | C4: =VLOOKUP(H4,Dominios!$A:$D,3,0) -> #REF! | D4: =VLOOKUP(H4,Dominios!$A:$D,4,0) -> #REF! | E4: =COUNTIF(#REF!,H4) -> #REF! | G4: Atta | H4: Maria De Chita | I4: Vesti (Assinatura) | J4: Profissional | L4: 724 | N4: 724 | S4: =SUM(N4:Q4)-R4 -> 724 | U4: 15 | V4: 04 | W4: 07402979000173
A5: 04/2026 | B5: 43160 | C5: =VLOOKUP(H5,Dominios!$A:$D,3,0) -> #REF! | D5: =VLOOKUP(H5,Dominios!$A:$D,4,0) -> #REF! | E5: =COUNTIF(#REF!,H5) -> #REF! | G5: Atta | H5: Shanes | I5: Vesti (Assinatura) | J5: Profissional | L5: 1179 | N5: 1179 | S5: =SUM(N5:Q5)-R5 -> 1179 | U5: 20 | V5: 04 | W5: 46446130000153
A6: 04/2026 | B6: 43160 | C6: =VLOOKUP(H6,Dominios!$A:$D,3,0) -> #REF! | D6: =VLOOKUP(H6,Dominios!$A:$D,4,0) -> #REF! | E6: =COUNTIF(#REF!,H6) -> #REF! | G6: Atta | H6: Talgui | I6: Vesti (Assinatura) | J6: Avançado | L6: 441.33 | N6: 441.33 | S6: =SUM(N6:Q6)-R6 -> 441.33 | U6: 15 | V6: 04 | W6: 05876663000198
A7: 04/2026 | B7: 43160 | C7: =VLOOKUP(H7,Dominios!$A:$D,3,0) -> #REF! | D7: =VLOOKUP(H7,Dominios!$A:$D,4,0) -> #REF! | E7: =COUNTIF(#REF!,H7) -> #REF! | G7: Atta | H7: Coinage | I7: Vesti (Assinatura) | J7: Profissional | L7: 1179 | N7: 1179 | S7: =SUM(N7:Q7)-R7 -> 1179 | U7: 20 | V7: 04 | W7: 33724927000123
A8: 04/2026 | B8: 43160 | C8: =VLOOKUP(H8,Dominios!$A:$D,3,0) -> #REF! | D8: =VLOOKUP(H8,Dominios!$A:$D,4,0) -> #REF! | E8: =COUNTIF(#REF!,H8) -> #REF! | G8: Atta | H8: Moda Inn | I8: Vesti (Assinatura) | J8: Essencial | L8: 283 | N8: 283 | S8: =SUM(N8:Q8)-R8 -> 283 | U8: 20 | V8: 04 | W8: 49921554000110
A9: 04/2026 | B9: 43160 | C9: =VLOOKUP(H9,Dominios!$A:$D,3,0) -> #REF! | D9: =VLOOKUP(H9,Dominios!$A:$D,4,0) -> #REF! | E9: =COUNTIF(#REF!,H9) -> #REF! | G9: Atta | H9: Betsey | I9: Vesti (Assinatura) | J9: Profissional | L9: 1003 | N9: 1003 | S9: =SUM(N9:Q9)-R9 -> 1003 | U9: 15 | V9: 04 | W9: 06161024000109
A10: 04/2026 | B10: 43160 | C10: =VLOOKUP(H10,Dominios!$A:$D,3,0) -> #REF! | D10: =VLOOKUP(H10,Dominios!$A:$D,4,0) -> #REF! | E10: =COUNTIF(#REF!,H10) -> #REF! | G10: Atta | H10: Cashier | I10: Vesti (Assinatura) | J10: Profissional | L10: 1015 | N10: 1015 | S10: =SUM(N10:Q10)-R10 -> 1015 | U10: 30 | V10: 04 | W10: 60368669000162
A11: 04/2026 | B11: 43160 | C11: =VLOOKUP(H11,Dominios!$A:$D,3,0) -> #REF! | D11: =VLOOKUP(H11,Dominios!$A:$D,4,0) -> #REF! | E11: =COUNTIF(#REF!,H11) -> #REF! | G11: Atta | H11: Cony Green | I11: Vesti (Assinatura) | J11: Avançado | L11: 425 | N11: 425 | S11: =SUM(N11:Q11)-R11 -> 425 | U11: 15 | V11: 04 | W11: 44511277000154
A12: 04/2026 | B12: 43160 | C12: =VLOOKUP(H12,Dominios!$A:$D,3,0) -> #REF! | D12: =VLOOKUP(H12,Dominios!$A:$D,4,0) -> #REF! | E12: =COUNTIF(#REF!,H12) -> #REF! | G12: Atta | H12: Pury | I12: Vesti (Assinatura) | J12: Profissional | L12: 1327 | N12: 1327 | Q12: 359 | S12: =SUM(N12:Q12)-R12 -> 1686 | U12: 15 | V12: 04 | W12: 12576594000162
A13: 04/2026 | B13: 43160 | C13: =VLOOKUP(H13,Dominios!$A:$D,3,0) -> #REF! | D13: =VLOOKUP(H13,Dominios!$A:$D,4,0) -> #REF! | E13: =COUNTIF(#REF!,H13) -> #REF! | G13: VESTI | H13: Tricomix | I13: Vesti (Assinatura) | J13: Avançado | L13: 1193 | N13: 1193 | O13: 350 | S13: =SUM(N13:Q13)-R13 -> 1543 | U13: 11 | V13: 04 | W13: 04665515000161
